Workbook

Sheet Dashboard
A1: The Great Race Dashboard
A2: Summary of 2,879 entries across 63 race years in the main Great Race results.
A4: Race years 63 | C4: Entries 2,879 | E4: Unique drivers 1,380 | G4: DNF/non-finish rate 41.1% | J4: Top manufacturer Holden | L4: Fastest winner avg speed 167.6 kph (2024)
A8: Key tables | J8: Driver starts by event group
A9: Top manufacturers by wins | B9: Wins | D9: Top drivers by starts | E9: Starts | G9: Top drivers by wins | H9: Wins | J9: Driver | K9: 1960-62 | L9: 1963-2025 | M9: 1997-99 ST | N9: 12 Hour | O9: 24 Hour | P9: Grand Total
A10: Holden | B10: 36 | D10: Jim Richards | E10: 34 | G10: Peter Brock | H10: 9 | J10: {=_xlfn.TAKE(_xlfn.SORTBY(_xlfn._xlws.FILTER('Dashboard Data'!U2:AA3000,'Dashboard Data'!U2:U3000<>""),_xlfn._xlws.FILTER('Dashboard Data'!AA2:AA3000,'Dashboard Data'!U2:U3000<>""),-1,_xlfn._xlws.FILTER('Dashboard Data'!U2:U3000,'Dashboard Data'!U2:U3000<>""),1),10)}
A11: Ford | B11: 21 | D11: Peter Brock | E11: 33 | G11: Craig Lowndes | H11: 7
A12: Chevrolet | B12: 2 | D12: Craig Lowndes | E12: 32 | G12: Garth Tander | H12: 6
A13: Nissan | B13: 2 | D13: Allan Grice | E13: 30 | G13: Jim Richards | H13: 6
A14: Jaguar | B14: 1 | D14: Colin Bond | E14: 28 | G14: Larry Perkins | H14: 6
A15: Morris | B15: 1 | D15: Dick Johnson | E15: 28 | G15: Mark Skaife | H15: 6
D16: John Bowe | E16: 28 | G16: Steven Richards | H16: 5
D17: Bob Holden | E17: 27 | G17: Allan Moffat | H17: 4
D18: Bruce Stewart | E18: 27 | G18: Greg Murphy | H18: 4
D19: Garth Tander | E19: 27 | G19: Jamie Whincup | H19: 4

Sheet Drivers in each year
A1: 1960 | C1: 1961 | E1: 1962 | G1: 1963 | I1: 1964 | K1: 1965 | M1: 1966 | O1: 1967 | Q1: 1968 | S1: 1988 | U1: 1989 | W1: 1990 | Y1: 1991 | AA1: 1992 | AC1: 1993 | AE1: 1994 | AG1: 1995 | AI1: 1996 | AK1: 1997 | AM1: 1998 | AO1: 1999 | AQ1: 2000 | AS1: 2001 | AU1: 2002 | AW1: 2003 | AY1: 2004 | BA1: 2005 | BC1: 2006 | BE1: 2007 | BG1: 2008 | BI1: 2009 | BK1: 2010 | BM1: 2011 | BO1: 2012 | BQ1: 2013 | BS1: 2014 | BU1: 2015 | BW1: 2016 | BY1: 2017 | CA1: 2018 | CC1: 2019 | CE1: 2020 | CG1: 2021 | CI1: 2022 | CK1: 2023 | CM1: 2024 | CO1: 2025
A2: Ern | B2: Abbott | C2: Dave | D2: Anderson | E2: Don | F2: Algie | G2: Ern | H2: Abbott | I2: Arnold | J2: Ahrenfeld | K2: Ern | L2: Abbott | M2: Rauno | N2: Aaltonen | O2: Lindsay | P2: Adcock | Q2: Lindsay | R2: Adcock | S2: Jeff | T2: Allam | U2: Michael | V2: Adcock | W2: Jeff | X2: Allam | Y2: Rauno | Z2: Aaltonen | AA2: Trevor | AB2: Ashby | AC2: Jeff | AD2: Allam | AE2: Jeff | AF2: Allam | AG2: Trevor | AH2: Ashby | AI2: Trevor | AJ2: Ashby | AK2: Trevor | AL2: Ashby | AM2: Trevor | AN2: Ashby | AO2: Trevor | AP2: Ashby | AQ2: Trevor | AR2: Ashby | AS2: Marcos | AT2: Ambrose | AU2: Marcos | AV2: Ambrose | AW2: Marcos | AX2: Ambrose | AY2: Marcos | AZ2: Ambrose | BA2: Marcos | BB2: Ambrose | BC2: Craig | BD2: Baird | BE2: Craig | BF2: Baird | BG2: Craig | BH2: Baird | BI2: Damian | BJ2: Assaillit | BK2: Damian | BL2: Assaillit | BM2: Craig | BN2: Baird | BO2: Craig | BP2: Baird | BQ2: Craig | BR2: Baird | BS2: Craig | BT2: Baird | BU2: Marcos | BV2: Ambrose | BW2: Craig | BX2: Baird | BY2: Tim | BZ2: Blanchard | CA2: Earl | CB2: Bamber | CC2: Tim | CD2: Blanchard | CE2: Tim | CF2: Blanchard | CG2: Zak | CH2: Best | CI2: Zak | CJ2: Best | CK2: Kai | CL2: Allen | CM2: Kai | CN2: Allen | CO2: Kai | CP2: Allen
A3: John | B3: Amp | C3: Norm | D3: Beechey | E3: Terry | F3: Allen | G3: John | H3: Alexander | I3: Tony | J3: Allen | K3: Arnold | L3: Ahrenfeld | M3: Ern | N3: Abbott | O3: Murray | P3: Bailey | Q3: Barry | R3: Arentz | S3: John | T3: Andretti | U3: Jeff | V3: Allam | W3: Trevor | X3: Ashby | Y3: Arthur | Z3: Abrahams | AA3: Scott | AB3: Bargwanna | AC3: Trevor | AD3: Ashby | AE3: Trevor | AF3: Ashby | AG3: David | AH3: Attard | AI3: David | AJ3: Attard | AK3: Bill | AL3: Attard | AM3: Bill | AN3: Attard | AO3: Bill | AP3: Attard | AQ3: Bill | AR3: Attard | AS3: Trevor | AT3: Ashby | AU3: Craig | AV3: Baird | AW3: Craig | AX3: Baird | AY3: Craig | AZ3: Baird | BA3: Craig | BB3: Baird | BC3: Jason | BD3: Bargwanna | BE3: Jason | BF3: Bargwanna | BG3: Jason | BH3: Bargwanna | BI3: Craig | BJ3: Baird | BK3: Craig | BL3: Baird | BM3: Jason | BN3: Bargwanna | BO3: David | BP3: Besnard | BQ3: Tim | BR3: Blanchard | BS3: Tim | BT3: Blanchard | BU3: Tim | BV3: Blanchard | BW3: Tim | BX3: Blanchard | BY3: Jason | BZ3: Bright | CA3: Tim | CB3: Blanchard | CC3: Will | CD3: Brown | CE3: Jordan | CF3: Boys | CG3: Tim | CH3: Blanchard | CI3: Tim | CJ3: Blanchard | CK3: Zak | CL3: Best | CM3: Jordan | CN3: Boys | CO3: Zach | CP3: Bates
A4: David | B4: Anderson | C4: Peter | D4: Boyd-Squires | E4: Jack | F4: Anderson | G4: Tony | H4: Allen | I4: Lionel | J4: Ayers | K4: Barry | L4: Arentz | M4: Barry | N4: Arentz | O4: Kevin | P4: Bartlett | Q4: Lionel | R4: Ayers | S4: Trevor | T4: Ashby | U4: Trevor | V4: Ashby | W4: Andrew | X4: Bagnall | Y4: Trevor | Z4: Ashby | AA4: Jason | AB4: Bargwanna | AC4: Neal | AD4: Bates | AE4: George | AF4: Ayoub | AG4: Ron | AH4: Barnacle | AI4: Bill | AJ4: Attard | AK4: Craig | AL4: Baird | AM4: Jason | AN4: Bargwanna | AO4: Craig | AP4: Baird | AQ4: Craig | AR4: Baird | AS4: Craig | AT4: Baird | AU4: Jason | AV4: Bargwanna | AW4: Jason | AX4: Bargwanna | AY4: Jason | AZ4: Bargwanna | BA4: Jason | BB4: Bargwanna | BC4: David | BD4: Besnard | BE4: David | BF4: Besnard | BG4: David | BH4: Besnard | BI4: Jason | BJ4: Bargwanna | BK4: Jason | BL4: Bargwanna | BM4: David | BN4: Besnard | BO4: Tim | BP4: Blanchard | BQ4: Jeroen | BR4: Bleekemolen | BS4: Jason | BT4: Bright | BU4: Sébastien | BV4: Bourdais | BW4: Jason | BX4: Bright | BY4: Matt | BZ4: Campbell | CA4: Jason | CB4: Bright | CC4: Dean | CD4: Canto | CE4: Will | CF4: Brown | CG4: Will | CH4: Brown | CI4: Jordan | CJ4: Boys | CK4: Tim | CL4: Blanchard | CM4: Will | CN4: Brown | CO4: Zak | CP4: Best
A5: Norm | B5: Beechey | C5: Albert | D5: Bridge | E5: David | F5: Anderson | G5: Arthur | H5: Andrews | I5: Lex | J5: Bailey | K5: Phil | L5: Barnes | M5: Lionel | N5: Ayers | O5: Bob | P5: Beasley | Q5: Kevin | R5: Bartlett | S5: Andrew | T5: Bagnall | U5: Reda | V5: Awadallah | W5: Craig | X5: Baird | Y5: Reda | Z5: Awadullah | AA5: Chris | AB5: Barns | AC5: Frank | AD5: Binding | AE5: Craig | AF5: Baird | AG5: Stephen | AH5: Bell | AI5: Kerry | AJ5: Baily | AK5: Jason | AL5: Bargwanna | AM5: Neal | AN5: Bates | AO5: Jason | AP5: Bargwanna | AQ5: Jason | AR5: Bargwanna | AS5: Jason | AT5: Bargwanna | AU5: Rick | AV5: Bates | AW5: Rick | AX5: Bates | AY5: David | AZ5: Besnard | BA5: David | BB5: Besnard | BC5: John | BD5: Bowe | BE5: John | BF5: Bowe | BG5: Jason | BH5: Bright | BI5: Troy | BJ5: Bayliss | BK5: David | BL5: Besnard | BM5: Tim | BN5: Blanchard | BO5: Jason | BP5: Bright | BQ5: Jason | BR5: Bright | BS5: Alex | BT5: Buncombe | BU5: Jason | BV5: Bright | BW5: Matt | BX5: Campbell | BY5: Dean | BZ5: Canto | CA5: Will | CB5: Brown | CC5: Michael | CD5: Caruso | CE5: Michael | CF5: Caruso | CG5: Matt | CH5: Campbell | CI5: Will | CJ5: Brown | CK5: Jordan | CL5: Boys | CM5: Aaron | CN5: Cameron | CO5: Jordan | CP5: Boys
A6: Ken | B6: Brigden | C6: Ken | D6: Brigden | E6: Norm | F6: Beechey | G6: Kevin | H6: Bartlett | I6: Phil | J6: Barnes | K6: Bill | L6: Barnett | M6: Malcolm | N6: Bailey | O6: Damon | P6: Beck | Q6: Tony | R6: Basile | S6: Kerry | T6: Baily | U6: Andrew | V6: Bagnall | W6: Jason | X6: Bargwanna | Y6: Dave | Z6: Barrow | AA6: Neal | AB6: Bates | AC6: John | AD6: Blanchard | AE6: Jeff | AF6: Barnes | AG6: John | AH6: Bowe | AI6: Ron | AJ6: Barnacle | AK6: Ron | AL6: Barnacle | AM6: G | AN6: Baxter | AO6: Ron | AP6: Barnacle | AQ6: Rick | AR6: Bates | AS6: Rick | AT6: Bates | AU6: Neal | AV6: Bates | AW6: Neal | AX6: Bates | AY6: John | AZ6: Bowe | BA6: John | BB6: Bowe | BC6: David | BD6: Brabham | BE6: Michael | BF6: Caruso | BG6: Dean | BH6: Canto | BI6: David | BJ6: Besnard | BK6: David | BL6: Brabham | BM6: David | BN6: Brabham | BO6: Dean | BP6: Canto | BQ6: Ryan | BR6: Briscoe | BS6: Dean | BT6: Canto | BU6: Alex | BV6: Buncombe | BW6: Dean | BX6: Canto | BY6: Michael | BZ6: Caruso | CA6: Dean | CB6: Canto | CC6: Fabian | CD6: Coulthard | CE6: Fabian | CF6: Coulthard | CG6: Michael | CH6: Caruso | CI6: Matthew | CJ6: Campbell | CK6: Will | CL6: Brown | CM6: Michael | CN6: Caruso | CO6: Will | CP6: Brown
A7: Bob | B7: Brown | C7: John | D7: Brindley | E7: Ann | F7: Bennett | G7: Warren | H7: Blomfield | I7: Bill | J7: Barnett | K7: Kevin | L7: Bartlett | M7: Kevin | N7: Bartlett | O7: Chris | P7: Brauer | Q7: Bob | R7: Beasley | S7: Dave | T7: Barrow | U7: Kevin | V7: Bartlett | W7: Dave | X7: Barrow | Y7: Neal | Z7: Bates | AA7: Rick | AB7: Bates | AC7: Colin | AD7: Bond | AE7: Stephen | AF7: Bell | AG7: Peter | AH7: Brock | AI7: Stephen | AJ7: Bell | AK7: Stephen | AL7: Bell | AM7: Shane | AN7: Beikoff | AO7: Neal | AP7: Bates | AQ7: Neal | AR7: Bates | AS7: David | AT7: Besnard | AU7: Daryl | AV7: Beattie | AW7: David | AX7: Besnard | AY7: David | AZ7: Brabham | BA7: David | BB7: Brabham | BC7: Dale | BD7: Brede | BE7: Fabian | BF7: Coulthard | BG7: Michael | BH7: Caruso | BI7: Jason | BJ7: Bright | BK7: Jason | BL7: Bright | BM7: Jason | BN7: Bright | BO7: Michael | BP7: Caruso | BQ7: Dean | BR7: Canto | BS7: Michael | BT7: Caruso | BU7: Dean | BV7: Canto | BW7: Michael | BX7: Caruso | BY7: Fabian | BZ7: Coulthard | CA7: Michael | CB7: Caruso | CC7: James | CD7: Courtney | CE7: James | CF7: Courtney | CG7: Fabian | CH7: Coulthard | CI7: Michael | CJ7: Caruso | CK7: Michael | CL7: Caruso | CM7: Matthew | CN7: Chahda | CO7: Aaron | CP7: Cameron
A8: John | B8: Calloway | C8: Bob | D8: Brown | E8: J. | F8: Binning | G8: Paul | H8: Bolton | I8: Warren | J8: Blomfield | K8: Bob | L8: Beasley | M8: Bob | N8: Beasley | O8: Bernie | P8: Breen | Q8: Damon | R8: Beck | S8: Kevin | T8: Bartlett | U8: Neal | V8: Bates | W8: Kevin | X8: Bartlett | Y8: Rick | Z8: Bates | AA8: Peter | AB8: Beck | AC8: Terry | AD8: Bosnjak | AE8: John | AF8: Blanchard | AG8: Brian | AH8: Callaghan | AI8: John | AJ8: Bowe | AK8: John | AL8: Bowe | AM8: Stephen | AN8: Bell | AO8: John | AP8: Bowe | AQ8: Gary | AR8: Baxter | AS8: John | AT8: Bowe | AU8: David | AV8: Besnard | AW8: John | AX8: Bowe | AY8: Dale | AZ8: Brede | BA8: Dale | BB8: Brede | BC8: Jason | BD8: Bright | BE8: James | BF8: Courtney | BG8: Fabian | BH8: Coulthard | BI8: Dean | BJ8: Canto | BK8: Ryan | BL8: Briscoe | BM8: Dean | BN8: Canto | BO8: Fabian | BP8: Coulthard | BQ8: Michael | BR8: Caruso | BS8: Fabian | BT8: Coulthard | BU8: Michael | BV8: Caruso | BW8: Fabian | BX8: Coulthard | BY8: James | BZ8: Courtney | CA8: Fabian | CB8: Coulthard | CC8: Tony | CD8: D'Alberto | CE8: Tony | CF8: D'Alberto | CG8: James | CH8: Courtney | CI8: Matthew | CJ8: Chahda | CK8: Fabian | CL8: Coulthard | CM8: Fabian | CN8: Coulthard | CO8: Fabian | CP8: Coulthard
A9: Peter | B9: Candy | C9: Lou | D9: Burke | E9: J. | F9: Bodinnar | G9: Jim | H9: Bonthorne | I9: Alton | J9: Boddenberg | K9: Alton | L9: Boddenberg | M9: Alton | N9: Boddenberg | O9: Mal | P9: Brewster | Q9: Alton | R9: Boddenberg | S9: Bryan | T9: Bate | U9: Frank | V9: Biela | W9: Neal | X9: Bates | Y9: Brian | Z9: Bolwell | AA9: Frank | AB9: Binding | AC9: John | AD9: Bowe | AE9: Colin | AF9: Bond | AG9: John | AH9: Cleland | AI9: Peter | AJ9: Brock | AK9: Peter | AL9: Bradbury | AM9: Domenic | AN9: Beninca | AO9: Geoff | AP9: Brabham | AQ9: Shane | AR9: Beikoff | AS9: Geoff | AT9: Brabham | AU9: John | AV9: Bowe | AW9: David | AX9: Brabham | AY9: Jason | AZ9: Bright | BA9: Jason | BB9: Bright | BC9: Ryan | BD9: Briscoe | BE9: Tony | BF9: D'Alberto | BG9: James | BH9: Courtney | BI9: Michael | BJ9: Caruso | BK9: Dean | BL9: Canto | BM9: Michael | BN9: Caruso | BO9: James | BP9: Courtney | BQ9: Fabian | BR9: Coulthard | BS9: James | BT9: Courtney | BU9: Fabian | BV9: Coulthard | BW9: James | BX9: Courtney | BY9: Tony | BZ9: D'Alberto | CA9: James | CB9: Courtney | CC9: Will | CD9: Davison | CE9: Alex | CF9: Davison | CG9: Tony | CH9: D'Alberto | CI9: Fabian | CJ9: Coulthard | CK9: James | CL9: Courtney | CM9: James | CN9: Courtney | CO9: James | CP9: Courtney
A10: Murray | B10: Carter | C10: Alan | D10: Caelli | E10: Peter | F10: Boyd-Squires | G10: Lex | H10: Brailey | I10: Paul | J10: Bolton | K10: Colin | L10: Bond | M10: Colin | N10: Bond | O10: Peter | P10: Brown | Q10: Chris | R10: Brauer | S10: Damon | T10: Beck | U10: Colin | V10: Bond | W10: Rick | X10: Bates | Y10: Colin | Z10: Bond | AA10: John | AB10: Blanchard | AC10: David | AD10: Brabham | AE10: John | AF10: Bowe | AG10: John | AH10: Cotter | AI10: Brian | AJ10: CallaghanJr | AK10: Kerryn | AL10: Brewer | AM10: John | AN10: Bowe | AO10: David | AP10: Brabham | AQ10: David | AR10: Besnard | AS10: Dale | AT10: Brede | AU10: Dale | AV10: Brede | AW10: Dale | AX10: Brede | AY10: Peter | AZ10: Brock | BA10: Dean | BB10: Canto | BC10: Dean | BD10: Canto | BE10: Alex | BF10: Davison | BG10: Tony | BH10: D'Alberto | BI10: Ben | BJ10: Collins | BK10: Michael | BL10: Caruso | BM10: Fabian | BN10: Coulthard | BO10: Tony | BP10: D'Alberto | BQ10: James | BR10: Courtney | BS10: Tony | BT10: D'Alberto | BU10: Tony | BV10: D'Alberto | BW10: Tony | BX10: D'Alberto | BY10: Will | BZ10: Davison | CA10: Tony | CB10: D'Alberto | CC10: Alex | CD10: Davison | CE10: Will | CF10: Davison | CG10: Will | CH10: Davison | CI10: James | CJ10: Courtney | CK10: Tony | CL10: D'Alberto | CM10: Cameron | CN10: Crick | CO10: Cameron | CP10: Crick
A11: Ray | B11: Christie | C11: Peter | D11: Candy | E11: John | F11: Brindley | G11: Ken | H11: Brigden | I11: Jim | J11: Bonthorne | K11: Midge | L11: Bosworth | M11: Peter | N11: Brown | O11: Lynn | P11: Brown | Q11: Mal | R11: Brewster | S11: Colin | T11: Bond | U11: John | V11: Bowe | W11: Russell | X11: Becker | Y11: John | Z11: Bowe | AA11: Brian | AB11: Bolwell | AC11: Geoff | AD11: Brabham | AE11: Peter | AF11: Brock | AG11: Greg | AH11: Crick | AI11: John | AJ11: Cleland | AK11: Tim | AL11: Briggs | AM11: Geoff | AN11: Brabham | AO11: John | AP11: Briggs | AQ11: John | AR11: Bowe | AS11: Jason | AT11: Bright | AU11: Jason | AV11: Bright | AW11: Jason | AX11: Bright | AY11: Dean | AZ11: Canto | BA11: John | BB11: Cleland | BC11: Michael | BD11: Caruso | BE11: Will | BF11: Davison | BG11: Will | BH11: Davison | BI11: Fabian | BJ11: Coulthard | BK11: Fabian | BL11: Coulthard | BM11: James | BN11: Courtney | BO11: Will | BP11: Davison | BQ11: Tony | BR11: D'Alberto | BS11: Robert | BT11: Dahlgren | BU11: Will | BV11: Davison | BW11: Shae | BX11: Davies | BY11: Alex | BZ11: Davison | CA11: Will | CB11: Davison | CC11: Anton | CD11: dePasquale | CE11: Anton | CF11: DePasquale | CG11: Alex | CH11: Davison | CI11: Tony | CJ11: D'Alberto | CK11: Will | CL11: Davison | CM11: Tony | CN11: D'Alberto | CO11: Tony | CP11: D'Alberto
A12: Bill | B12: Clemens | C12: Eddie | D12: Clay | E12: Bob | F12: Brown | G12: John | H12: Brindley | I12: Midge | J12: Bosworth | K12: Peter | L12: Brown | M12: Bill | N12: Buckle | O12: Bill | P12: Brown | Q12: Peter | R12: Brown | S12: John | T12: Bowe | U12: Gianfranco | V12: Brancatelli | W12: Frank | X12: Biela | Y12: Gary | Z12: Brabham | AA12: Colin | AB12: Bond | AC12: Peter | AD12: Brock | AE12: Kevin | AF12: Burton | AG12: Rodney | AH12: Crick | AI12: Mike | AJ12: Conway | AK12: Jason | AL12: Bright | AM12: Kerryn | AN12: Brewer | AO12: Jason | AP12: Bright | AQ12: Geoff | AR12: Brabham | AS12: James | AT12: Brock | AU12: Peter | AV12: Brock | AW12: Dean | AX12: Canto | AY12: John | AZ12: Cleland | BA12: Matthew | BB12: Coleman | BC12: Fabian | BD12: Coulthard | BE12: Grant | BF12: Denyer | BG12: Alex | BH12: Davison | BI12: James | BJ12: Courtney | BK12: James | BL12: Courtney | BM12: Tony | BN12: D'Alberto | BO12: Alex | BP12: Davison | BQ12: Will | BR12: Davison | BS12: Will | BT12: Davison | BU12: Alex | BV12: Davison | BW12: Will | BX12: Davison | BY12: Simona | BZ12: deSilvestro | CA12: Alex | CB12: Davison | CC12: Simona | CD12: deSilvestro | CE12: Tyler | CF12: Everingham | CG12: Anton | CH12: De Pasquale | CI12: Will | CJ12: Davison | CK12: Alex | CL12: Davison | CM12: Will | CN12: Davison | CO12: Lochie | CP12: Dalton
A13: Frank | B13: Coad | C13: Frank | D13: Coad | E13: Bill | F13: Buckle | G13: Barry | H13: Broomhall | I13: Peter | J13: Brown | K13: Bill | L13: Brown | M13: Bill | N13: Burns | O13: Bill | P13: Buckle | Q13: Bill | R13: Brown | S13: Peter | T13: Brock | U13: Peter | V13: Brock | W13: Brian | X13: Bolwell | Y13: Gianfranco | Z13: Brancatelli | AA13: Terry | AB13: Bosnjak | AC13: Brian | AD13: CallaghanJr | AE13: Brian | AF13: CallaghanJr | AG13: Neil | AH13: Crompton | AI13: John | AJ13: Cotter | AK13: Peter | AL13: Brock | AM13: Tim | AN13: Briggs | AO13: Dean | AP13: Canto | AQ13: Jason | AR13: Bright | AS13: Dean | AT13: Canto | AU13: Dean | AV13: Canto | AW13: John | AX13: Cleland | AY13: Fabian | AZ13: Coulthard | BA13: Fabian | BB13: Coulthard | BC13: James | BD13: Courtney | BE13: Paul | BF13: Dumbrell | BG13: Paul | BH13: Dumbrell | BI13: Tony | BJ13: D'Alberto | BK13: Tony | BL13: D'Alberto | BM13: Alex | BN13: Davison | BO13: Jesse | BP13: Dixon | BQ13: Alex | BR13: Davison | BS13: Alex | BT13: Davison | BU13: Simona | BV13: deSilvestro | BW13: Simona | BX13: deSilvestro | BY13: Taz | BZ13: Douglas | CA13: Anton | CB13: dePasquale | CC13: Dean | CD13: Fiore | CE13: Broc | CF13: Feeney | CG13: Broc | CH13: Feeney | CI13: Alex | CJ13: Davison | CK13: Anton | CL13: de Pasquale | CM13: Anton | CN13: De Pasquale | CO13: Will | CP13: Davison
... A49: Peter | B49: Manton | C49: John | D49: Raeburn | E49: Kingsley | F49: Hibbard | G49: Tony | H49: Hill | I49: Lorraine | J49: Hill | K49: Bruce | L49: Hodgson | M49: Paddy | N49: Hopkirk | O49: Clyde | P49: Hodgins | Q49: Paul | R49: Hawkins | S49: Geoff | T49: Leeds | U49: Denny | V49: Hulme | W49: Gregg | X49: Hansford | Y49: Alan | Z49: Jones | AA49: Bob | AB49: Holden | AC49: Alan | AD49: Jones | AE49: Tony | AF49: Longhurst | AG49: Win | AH49: Percy | AI49: David | AJ49: Parsons | AK49: Greg | AL49: Murphy | AM49: Andrew | AN49: Lloyd | AO49: Brad | AP49: Jones | AQ49: Owen | AR49: Kelly | AS49: Paul | AT49: Morris | AU49: Greg | AV49: Murphy | AW49: Larry | AX49: Perkins | AY49: Mark | AZ49: Porter | BA49: Nathan | BB49: Pretty | BC49: Steven | BD49: Richards | BE49: Luke | BF49: Youlden | BG49: Mark | BH49: Skaife | BI49: Greg | BJ49: Ritter | BK49: David | BL49: Russell | BM49: Tim | BN49: Slade | BO49: Tim | BP49: Slade | BQ49: Tim | BR49: Slade | BS49: Jonathon | BT49: Webb | BU49: Ashley | BV49: Walsh | BW49: Ashley | BX49: Walsh | BY49: Jonathon | BZ49: Webb | CA49: Jonathon | CB49: Webb | CC49: Jonathon | CD49: Webb | CE49: Jamie | CF49: Whincup | CG49: Mark | CH49: Winterbottom | CI49: Tim | CJ49: Slade | CK49: Jack | CL49: Smith | CM49: Cameron | CN49: Waters | CO49: Garth | CP49: Tander
A50: Bill | B50: March | C50: George | D50: Reynolds | E50: G. | F50: Hibberd | G50: Lorraine | H50: Hill | I50: Joe | J50: Hills | K50: Bob | L50: Holden | M50: Don | N50: James | O50: Bob | P50: Holden | Q50: Ron | R50: Haylen | S50: John | T50: Leeson | U50: Roger | V50: Hurd | W50: Bob | X50: Holden | Y50: Warren | Z50: Jonsson | AA50: Peter | AB50: Hopwood | AC50: Warren | AD50: Jonsson | AE50: Ian | AF50: Love | AG50: Larry | AH50: Perkins | AI50: Larry | AJ50: Perkins | AK50: Mark | AL50: Noske | AM50: Tony | AN50: Longhurst | AO50: Todd | AP50: Kelly | AQ50: Mark | AR50: Larkham | AS50: Kevin | AT50: Mundy | AU50: Mark | AV50: Noske | AW50: Mark | AX50: Porter | AY50: Nathan | AZ50: Pretty | BA50: Paul | BB50: Radisich | BC50: Jason | BD50: Richards | BG50: Garth | BH50: Tander | BI50: David | BJ50: Sieders | BK50: Glenn | BL50: Seton | BM50: Garth | BN50: Tander | BO50: Garth | BP50: Tander | BQ50: Garth | BR50: Tander | BS50: Jamie | BT50: Whincup | BU50: Cameron | BV50: Waters | BW50: Cameron | BX50: Waters | BY50: Jamie | BZ50: Whincup | CA50: Jamie | CB50: Whincup | CC50: Jamie | CD50: Whincup | CE50: Mark | CF50: Winterbottom | CG50: Dale | CH50: Wood | CI50: Jack | CJ50: Smith | CK50: Richie | CL50: Stanaway | CM50: Jamie | CN50: Whincup | CO50: Brad | CP50: Vaughan
A51: Lionel | B51: Marsh | C51: John | D51: Roxburgh | E51: Graham | F51: Hoinville | G51: Ron | H51: Hodgson | I51: Ron | J51: Hodgson | K51: Don | L51: Holland | M51: Bill | N51: Jamieson | O51: Don | P51: Holland | Q51: Ian | R51: Haynes | S51: Ray | T51: Lintott | U51: Peter | V51: Janson | W51: Denny | X51: Hulme | Y51: Graham | Z51: Jonsson | AA51: Denny | AB51: Hulme | AC51: Kurt | AD51: Kratzmann | AE51: Craig | AF51: Lowndes | AG51: Brett | AH51: Peters | AI51: Brett | AJ51: Peters | AK51: Bill | AL51: O'Brien | AM51: Craig | AN51: Lowndes | AO51: Geoff | AP51: Kendrick | AQ51: Tim | AR51: Leahey | AS51: Greg | AT51: Murphy | AU51: Steve | AV51: Owen | AW51: Nathan | AX51: Pretty | AY51: Paul | AZ51: Radisich | BA51: Jason | BB51: Richards | BC51: Jim | BD51: Richards | BG51: Andrew | BH51: Thompson | BI51: Allan | BJ51: Simonsen | BK51: Allan | BL51: Simonsen | BM51: Andrew | BN51: Thompson | BO51: Andrew | BP51: Thompson | BQ51: Andrew | BR51: Thompson | BS51: Mark | BT51: Winterbottom | BU51: Jonathon | BV51: Webb | BW51: Jonathon | BX51: Webb | BY51: Mark | BZ51: Winterbottom | CA51: Mark | CB51: Winterbottom | CC51: Mark | CD51: Winterbottom | CE51: Dale | CF51: Wood | CG51: Luke | CH51: Youlden | CI51: Richie | CJ51: Stanaway | CK51: Garth | CL51: Tander | CM51: Mark | CN51: Winterbottom | CO51: Cameron | CP51: Waters
A52: Jack | B52: Maurer | C52: Geoff | D52: Russell | E52: D. | F52: Hooker | G52: Bob | H52: Holden | I52: Bob | J52: Holden | K52: Pat | L52: Holmes | M52: Ron | N52: Kearns | O52: Paddy | P52: Hopkirk | Q52: Bruce | R52: Hindhaugh | S52: Tony | T52: Longhurst | U52: Dick | V52: Johnson | W52: Russell | X52: Ingall | Y52: Chris | Z52: Lambden | AA52: Peter | AB52: Janson | AC52: Tony | AD52: Longhurst | AE52: Matthew | AF52: Martin | AG52: Mark | AH52: Poole | AI52: Mark | AJ52: Poole | AK52: Charlie | AL52: O'Brien | AM52: Adam | AN52: Macrow | AO52: Mark | AP52: Larkham | AQ52: Dean | AR52: Lindstrom | AS52: Rod | AT52: Nash | AU52: Larry | AV52: Perkins | AW52: Andy | AX52: Priaulx | AY52: Jason | AZ52: Richards | BA52: Steven | BB52: Richards | BC52: Greg | BD52: Ritter | BG52: Shane | BH52: vanGisbergen | BI52: Mark | BJ52: Skaife | BK52: Mark | BL52: Skaife | BM52: Shane | BN52: vanGisbergen | BO52: Shane | BP52: vanGisbergen | BQ52: Shane | BR52: vanGisbergen | BS52: Dale | BT52: Wood | BU52: Jamie | BV52: Whincup | BW52: Jamie | BX52: Whincup | BY52: Dale | BZ52: Wood | CA52: Dale | CB52: Wood | CC52: Dale | CD52: Wood | CI52: Garth | CJ52: Tander | CK52: Shane | CL52: Van Gisbergen | CM52: Ryan | CN52: Wood | CO52: Jamie | CP52: Whincup
A53: David | B53: McKay | C53: Brian | D53: Sampson | E53: J. | F53: Hume | G53: Don | H53: Holland | I53: Don | J53: Holland | K53: Paddy | L53: Hopkirk | M53: Des | N53: Kelly | O53: Bob | P53: Jane | Q53: Gary | R53: Hodge | S53: Graham | T53: Lusty | U53: Alan | V53: Jones | W53: Peter | X53: Janson | Y53: Geoff | Z53: Leeds | AA53: Dick | AB53: Johnson | AC53: Graham | AD53: Lusty | AE53: Ken | AF53: Mathews | AG53: Steve | AH53: Reed | AI53: Miles | AJ53: Pope | AK53: Danny | AL53: Osborne | AM53: Allan | AN53: McCarthy | AO53: Tim | AP53: Leahey | AQ53: Tony | AR53: Longhurst | AS53: Mark | AT53: Noske | AU53: Mark | AV53: Porter | AW53: Paul | AX53: Radisich | AY53: Steven | AZ53: Richards | BA53: Jim | BB53: Richards | BC53: Kayne | BD53: Scott | BG53: Jonathon | BH53: Webb | BI53: Tim | BJ53: Slade | BK53: Tim | BL53: Slade | BM53: David | BN53: Wall | BO53: David | BP53: Wall | BQ53: David | BR53: Wall | BS53: Luke | BT53: Youlden | BU53: Mark | BV53: Winterbottom | BW53: Mark | BX53: Winterbottom | BY53: Luke | BZ53: Youlden | CA53: Luke | CB53: Youlden | CC53: Luke | CD53: Youlden | CI53: Shane | CJ53: Van Gisbergen | CK53: Cameron | CL53: Waters | CM53: Dale | CN53: Wood | CO53: Mark | CP53: Winterbottom
A54: Max | B54: McPherson | C54: Jacques | D54: Sapir | E54: A. | F54: Humphries | G54: Sid | H54: Howard | I54: Phil | J54: Ismay | K54: Bob | L54: Jane | M54: Carl | N54: Kennedy | O54: Mike | P54: Kable | Q54: Clyde | R54: Hodgins | S54: John | T54: Lusty | U54: Brad | V54: Jones | W54: Dick | X54: Johnson | Y54: Ray | Z54: Lintott | AA54: Bob | AB54: Jones | AC54: John | AD54: Lusty | AE54: Stuart | AF54: McColl | AG54: Steven | AH54: Richards | AI54: Steve | AJ54: Reed | AK54: Ian | AL54: Palmer | AM54: Cameron | AN54: McConville | AO54: Dean | AP54: Lindstrom | AQ54: Craig | AR54: Lowndes | AS54: Steve | AT54: Owen | AU54: Will | AV54: Power | AW54: Jonny | AX54: Reid | AY54: Jim | AZ54: Richards | BA54: Greg | BB54: Ritter | BC54: Glenn | BD54: Seton | BG54: Paul | BH54: Weel | BI54: Garth | BJ54: Tander | BK54: Garth | BL54: Tander | BM54: Cameron | BN54: Waters | BO54: Cameron | BP54: Waters | BQ54: Ashley | BR54: Walsh | BU54: Dale | BV54: Wood | BW54: Dale | BX54: Wood | CI54: Cameron | CJ54: Waters | CK54: Jonathon | CL54: Webb | CO54: Ryan | CP54: Wood
A55: Austin | B55: Miller | C55: Charlie | D55: Smith | E55: Jack | F55: Hunnam | G55: Les | H55: Howard | I55: Bob | J55: Jane | K55: Don | L55: Johnston | M55: Moto | N55: Kitano | O55: Carl | P55: Kennedy | Q55: Don | R55: Holland | S55: Andrew | T55: Maher | U55: Gerald | V55: Kay | W55: Bob | X55: Jones | Y55: Tony | Z55: Longhurst | AA55: Brad | AB55: Jones | AC55: Chris | AD55: Madden | AE55: Cameron | AF55: McConville | AG55: Jim | AH55: Richards | AI55: Steven | AJ55: Richards | AK55: David | AL55: Parsons | AM55: Mark | AN55: McLaughlin | AO55: Tony | AP55: Longhurst | AQ55: Adam | AR55: Macrow | AS55: David | AT55: Parsons | AU55: Nathan | AV55: Pretty | AW55: Tony | AX55: Ricciardello | AY55: Greg | AZ55: Ritter | BA55: Phillip | BB55: Scifleet | BC55: Allan | BD55: Simonsen | BG55: Jamie | BH55: Whincup | BI55: Leanne | BJ55: Tander | BK55: Andrew | BL55: Thompson | BM55: Jonathon | BN55: Webb | BO55: Jonathon | BP55: Webb | BQ55: Jonathon | BR55: Webb | BU55: Luke | BV55: Youlden | BW55: Luke | BX55: Youlden | CI55: Jamie | CJ55: Whincup | CK55: Jamie | CL55: Whincup | CO55: Dale | CP55: Wood
A56: Clyde | B56: Miller | C56: Ian | D56: Strachan | E56: George | F56: Huse | G56: Dave | H56: Humphries | I56: Don | J56: Johnston | K56: Ray | L56: Kaleda | M56: Brian | N56: Lawler | O56: John | P56: Leffler | Q56: Don | R56: James | S56: Steve | T56: Masterton | U56: Mike | V56: King | W56: Alan | X56: Jones | Y56: Graham | Z56: Lusty | AA56: Rodney | AB56: Jones | AC56: Matthew | AD56: Martin | AE56: Peter | AF56: McKay | AG56: Paul | AH56: Romano | AI56: Jim | AJ56: Richards | AK56: Darren | AL56: Pate | AM56: Cameron | AN56: McLean | AO56: Craig | AP56: Lowndes | AQ56: Cameron | AR56: McConville | AS56: Larry | AT56: Perkins | AU56: Andy | AV56: Priaulx | AW56: Steven | AX56: Richards | AY56: Glenn | AZ56: Seton | BA56: Kayne | BB56: Scott | BC56: Mark | BD56: Skaife | BG56: Max | BH56: Wilson | BI56: Andrew | BJ56: Thompson | BK56: Shane | BL56: vanGisbergen | BM56: Jamie | BN56: Whincup | BO56: Jamie | BP56: Whincup | BQ56: Jamie | BR56: Whincup | CI56: Mark | CJ56: Winterbottom | CK56: Mark | CL56: Winterbottom
A57: Lou | B57: Molina | C57: Fred | D57: Sutherland | E57: Mike | F57: Ide | G57: Bob | H57: Jane | I57: Ray | J57: Kaleda | K57: Tony | L57: Kavanagh | M57: Alex | N57: Lazich | O57: Gerry | P57: Lister | Q57: Allan | R57: Johns | S57: Ken | T57: Mathews | U57: Chris | V57: Lambden | W57: Brad | X57: Jones | Y57: Glenn | Z57: McIntyre | AA57: Alan | AB57: Jones | AC57: Spencer | AD57: Martin | AE57: Ryan | AF57: McLeod | AG57: Warwick | AH57: Rooklyn | AI57: Paul | AJ57: Romano | AK57: Bob | AL57: Pearson | AM57: Alain | AN57: Menu | AO57: Adam | AP57: Macrow | AQ57: Dugal | AR57: McDougall | AS57: Nathan | AT57: Pretty | AU57: Paul | AV57: Radisich | AW57: Jim | AX57: Richards | AY57: Allan | AZ57: Simonsen | BA57: Glenn | BB57: Seton | BC57: Garth | BD57: Tander | BG57: Mark | BH57: Winterbottom | BI57: James | BJ57: Thompson | BK57: David | BL57: Wall | BM57: Mark | BN57: Winterbottom | BO57: Mark | BP57: Winterbottom | BQ57: Mark | BR57: Winterbottom | CI57: Dale | CJ57: Wood | CK57: Dale | CL57: Wood
A58: Brian | B58: Muir | C58: Ian | D58: Trudinger | E58: Bob | F58: Jane | G58: Doug | H58: Kelley | I58: Eric | J58: Lane | K58: Des | L58: Kelly | M58: Geoff | N58: Leeds | O58: Lindsay | P58: Little | Q58: Ernie | R58: Johnson | S58: Peter | T58: McKay | U58: Geoff | V58: Leeds | W58: Garry | X58: Jones | Y58: Tomas | Z58: Mezera | AA58: Garry | AB58: Jones | AC58: Glenn | AD58: Mason | AE58: Peter | AF58: McLeod | AG58: Wayne | AH58: Russell | AI58: Mal | AJ58: Rose | AK58: Win | AL58: Percy | AM58: Tomas | AN58: Mezera | AO58: Cameron | AP58: McConville | AQ58: Aaron | AR58: McGill | AS58: Paul | AT58: Radisich | AU58: Jason | AV58: Richards | AW58: Jason | AX58: Richards | AY58: Mark | AZ58: Skaife | BA58: Allan | BB58: Simonsen | BC58: Anthony | BD58: Tratt | BG58: Dale | BH58: Wood | BI58: Shane | BJ58: vanGisbergen | BK58: Jonathon | BL58: Webb | BM58: Dale | BN58: Wood | BO58: Dale | BP58: Wood | BQ58: Dale | BR58: Wood
A59: W. | B59: Murison | C59: Joe | D59: Vanaria | E59: Diane | F59: Leighton | G59: Graham | H59: Kelley | I59: Brian | J59: Lawler | K59: Carl | L59: Kennedy | M59: John | N59: Leffler | O59: Doug | P59: Macarthur | Q59: Mike | R59: Kable | S59: Peter | T59: McLeod | U59: John | V59: Leeson | W59: Graham | X59: Jonsson | Y59: Andrew | Z59: Miedecke | AA59: Warren | AB59: Jonsson | AC59: Steve | AD59: Masterton | AE59: Tomas | AF59: Mezera | AG59: Neil | AH59: Schembri | AI59: Wayne | AJ59: Russell | AK59: Larry | AL59: Perkins | AM59: Richard | AN59: Mork | AO59: Dugal | AP59: McDougall | AQ59: Cameron | AR59: McLean | AS59: Steve | AT59: Reed | AU59: Jim | AV59: Richards | AW59: Greg | AX59: Ritter | AY59: Paul | AZ59: Stokell | BA59: Mark | BB59: Skaife | BC59: Jonathon | BD59: Webb | BG59: Luke | BH59: Youlden | BI59: David | BJ59: Wall | BK59: Jamie | BL59: Whincup | BM59: Luke | BN59: Youlden | BO59: Luke | BP59: Youlden | BQ59: Luke | BR59: Youlden
A60: Rod | B60: Murphy | C60: M | D60: Watson | E60: Kevin | F60: Lott | G60: Carl | H60: Kennedy | I60: Bruce | J60: Maher | K60: Brian | L60: Lawler | M60: Ken | N60: Lindsay | O60: Alex | P60: Macarthur | Q60: Ron | R60: Kearns | S60: Tomas | T60: Mezera | U60: Ray | V60: Lintott | W60: Chris | X60: Lambden | Y60: Steve | Z60: Millen | AA60: Robbie | AB60: Ker | AC60: Ken | AD60: Mathews | AE60: Andrew | AF60: Miedecke | AG60: Tony | AH60: Scott | AI60: Tony | AJ60: Scott | AK60: Mark | AL60: Poole | AM60: Greg | AN60: Murphy | AO60: Cameron | AP60: McLean | AQ60: Ryan | AR60: McLeod | AS60: Tony | AT60: Ricciardello | AU60: Steven | AV60: Richards | AW60: Mal | AX60: Rose | AY60: Garth | AZ60: Tander | BA60: Alex | BB60: Tagliani | BC60: Paul | BD60: Weel | BI60: Sam | BJ60: Walter | BK60: Mark | BL60: Winterbottom
A61: Jack | B61: Murray | C61: Jim | D61: White | E61: Reg | F61: Lunn | G61: Frank | H61: Kleinig | I61: Paul | J61: Mander | K61: Ken | L61: Lindsay | M61: Gerry | N61: Lister | O61: Glen | P61: Mackinnon | Q61: Carl | R61: Kennedy | S61: Andrew | T61: Miedecke | U61: Tony | V61: Longhurst | W61: Geoff | X61: Leeds | Y61: Graham | Z61: Moore | AA61: Ed | AB61: Lamont | AC61: John | AD61: Mathews | AE61: Jamie | AF61: Miller | AG61: Glenn | AH61: Seton | AI61: Glenn | AJ61: Seton | AK61: Melinda | AL61: Price | AM61: Rod | AN61: Nash | AO61: Tomas | AP61: Mezera | AQ61: Tyler | AR61: Mecklem | AS61: Jim | AT61: Richards | AU61: Greg | AV61: Ritter | AW61: David | AX61: Russell | AY61: Anthony | AZ61: Tratt | BA61: Garth | BB61: Tander | BC61: Jamie | BD61: Whincup | BI61: Jonathon | BJ61: Webb | BK61: Dale | BL61: Wood
A62: Bill | B62: Murray | C62: Doug | D62: Whiteford | E62: Peter | F62: Macrow | G62: Terry | H62: Kratzmann | I62: Bill | J62: March | K62: Lindsay | L62: Little | M62: Alex | N62: Macarthur | O62: Peter | P62: Macrow | Q62: James | R62: Laing-Peach | S62: Allan | T62: Moffat | U62: Graham | V62: Lorimer | W62: Ray | X62: Lintott | Y62: Geoff | Z62: Morgan | AA62: Tony | AB62: Longhurst | AC62: Stuart | AD62: McColl | AE62: Paul | AF62: Morris | AG62: Richard | AH62: Shaw | AI62: Rick | AJ62: Shaw | AK62: Scott | AL62: Pruett | AM62: Mark | AN62: Noske | AO62: Andrew | AP62: Miedecke | AQ62: Alain | AR62: Menu | AS62: Jason | AT62: Richards | AU62: Phillip | AV62: Scifleet | AW62: Rickard | AX62: Rydell | AY62: Garth | AZ62: Walden | BA62: Anthony | BB62: Tratt | BC62: Max | BD62: Wilson | BI62: Jamie | BJ62: Whincup | BK62: Luke | BL62: Youlden
A63: Bill | B63: Nalder | C63: Peter | D63: Will[5] | E63: Jack | F63: Madden | G63: Brian | H63: Lawler | I63: John | J63: Marchiori | K63: Bruce | L63: Maher | M63: Paul | N63: Mander | O63: Timo | P63: Mäkinen | Q63: Gary | R63: Leggatt | S63: Graham | T63: Moore | U63: Graham | V63: Lusty | W63: Tony | X63: Longhurst | Y63: Paul | Z63: Morris | AA63: Ken | AB63: Mathews | AC63: Cameron | AD63: McConville | AE63: Greg | AF63: Murphy | AG63: Mark | AH63: Skaife | AI63: Terry | AJ63: Shiel | AK63: Trevor | AL63: Reed | AM63: Danny | AN63: Osborne | AO63: Daniel | AP63: Miller | AQ63: Tomas | AR63: Mezera | AS63: Steven | AT63: Richards | AU63: Tony | AV63: Scott | AW63: Phillip | AX63: Scifleet | AY63: Paul | AZ63: Weel | BA63: Paul | BB63: Weel | BC63: Mark | BD63: Winterbottom | BI63: Mark | BJ63: Winterbottom | BK63: Marcus | BL63: Zukanovic
A64: Jack | B64: Nougher | E64: Bruce | F64: Maher | G64: Lindsay | H64: Little | I64: Spencer | J64: Martin | K64: Timo | L64: Mäkinen | M64: Ray | N64: Marquet | O64: Paul | P64: Mander | Q64: Ron | R64: Marks | S64: Michael | T64: Mortimer | U64: John | V64: Mann | W64: Graham | X64: Lusty | Y64: Charlie | Z64: O'Brien | AA64: Stuart | AB64: McColl | AC64: David | AD64: McMillan | AE64: Troy | AF64: Nicholson | AG64: Bernie | AH64: Stack | AI64: Bill | AJ64: Sieders | AK64: Steven | AL64: Richards | AM64: Ian | AN64: Palmer | AO64: Richard | AP64: Mork | AQ64: Andrew | AR64: Miedecke | AS64: Greg | AT64: Ritter | AU64: Ron | AV64: Searle | AW64: Ron | AX64: Searle | AY64: Jamie | AZ64: Whincup | BA64: Jamie | BB64: Whincup | BC64: Luke | BD64: Youlden | BI64: Dale | BJ64: Wood
A65: Ken (Rex) | B65: Orman | E65: Lionel | F65: Marsh | G65: Greg | H65: Mackie | I65: Mike | J65: Martin | K65: Paul | L65: Mander | M65: Lew | N65: Marshall | O65: Lakis | P65: Manticas | Q65: Ray | R65: Marquet | S65: Tony | T65: Mulvihill | U65: Ken | V65: Mathews | W65: John | X65: Lusty | Y65: Bill | Z65: O'Brien | AA65: Tomas | AB65: Mezera | AC65: Gregg | AD65: McShane | AE65: Charlie | AF65: O'Brien | AG65: Bruce | AH65: Stewart | AI65: Mark | AJ65: Skaife | AK65: Jim | AL65: Richards | AM65: David | AN65: Parsons | AO65: Paul | AP65: Morris | AQ65: Ian | AR65: Moncrieff | AS65: Paul | AT65: Romano | AU65: Glenn | AV65: Seton | AW65: Glenn | AX65: Seton | AY65: Matthew | AZ65: White | BA65: Damien | BB65: White | BI65: Luke | BJ65: Youlden
A66: Les | B66: Park | E66: Stan | F66: Martin | G66: Peter | H66: Manton | I66: Brian | J66: McGrath | K66: Peter | L66: Manton | M66: Mike | N66: Martin | O66: Spencer | P66: Martin | Q66: Spencer | R66: Martin | S66: Geoff | T66: Munday | U66: Joe | V66: McAndrew | W66: Andrew | X66: McDowell | Y66: Rohan | Z66: Onslow | AA66: Andrew | AB66: Miedecke | AC66: Tomas | AD66: Mezera | AE66: Anders | AF66: Olofsson | AG66: Scotty | AH66: Taylor | AI66: Chris | AJ66: Smerdon | AK66: Paul | AL66: Romano | AM66: David | AN66: Parsons | AO66: Greg | AP66: Murphy | AQ66: Richard | AR66: Mork | AS66: Rod | AT66: Salmon | AU66: Micheal | AV66: Simpson | AW66: Allan | AX66: Simonsen | AY66: Simon | AZ66: Wills | BA66: Matthew | BB66: White
A67: Eddie | B67: Perkins | E67: Frank | F67: McEnroe | G67: Bill | H67: March | I67: Neil | J67: McKay | K67: John | L67: Marchiori | M67: Frank | N67: Matich | O67: Bruce | P67: McIntyre | Q67: Trevor | R67: Mason | S67: Akihiko | T67: Nakaya | U67: Glenn | V67: McIntyre | W67: Glenn | X67: McIntyre | Y67: Wayne | Z67: Park | AA67: Graham | AB67: Moore | AC67: Andrew | AD67: Miedecke | AE67: Ian | AF67: Palmer | AG67: Stephen | AH67: Voight | AI67: Scotty | AJ67: Taylor | AK67: Mal | AL67: Rose | AM67: Darren | AN67: Pate | AO67: Rod | AP67: Nash | AQ67: Paul | AR67: Morris | AS67: Phillip | AT67: Scifleet | AU67: Mark | AV67: Skaife | AW67: Mark | AX67: Skaife | AY67: Max | AZ67: Wilson | BA67: Max | BB67: Wilson
A68: G. | B68: Petty | E68: Jim | F68: McKeown | G68: John | H68: Marchiori | I68: C. | J68: McLean | K68: Spencer | L68: Martin | M68: Bruce | N68: McPhee | O68: David | P68: McKay | Q68: Neil | R68: Mason | S68: Klaus | T68: Niedzwiedz | U68: Peter | V68: McKay | W68: Peter | X68: McKay | Y68: David | Z68: Parsons | AA68: Paul | AB68: Morris | AC68: Gavin | AD68: Monaghan | AE68: David | AF68: Parsons | AG68: Kevin | AH68: Waldock | AI68: John | AJ68: Trimbole | AK68: Wayne | AL68: Russell | AM68: Larry | AN68: Perkins | AO68: Mark | AP68: Noske | AQ68: Yvan | AR68: Muller | AS68: Glenn | AT68: Seton | AU68: Paul | AV68: Stokell | AW68: Paul | AX68: Stokell | AY68: Kurt | AZ68: Wimmer | BA68: Mark | BB68: Winterbottom
A69: Ron | B69: Phillips | E69: Lou | F69: Molina | G69: Trevor | H69: Marden | I69: Lyndon | J69: McLeod | K69: Brian | L69: McGrath | M69: Trevor | N69: Meehan | O69: Trevor | P69: Meehan | Q69: Bruce | R69: McIntyre | S69: Tony | T69: Noske | U69: Warren | V69: McKellar | W69: Mark | X69: McLaughlin | Y69: Bob | Z69: Pearson | AA69: Stuart | AB69: Murphy | AC69: Paul | AD69: Morris | AE69: Win | AF69: Percy | AI69: Kevin | AJ69: Waldock | AK69: Neil | AL69: Schembri | AM69: Brett | AN69: Peters | AO69: Danny | AP69: Osborne | AQ69: Christian | AR69: Murchison | AS69: Micheal | AT69: Simpson | AU69: Garth | AV69: Tander | AW69: Garth | AX69: Tander | AY69: Mark | AZ69: Winterbottom | BA69: Luke | BB69: Youlden
A70: Bill | B70: Pitt | E70: Pam | F70: Murison | G70: Ron | H70: Marshall | I70: Bruce | J70: McPhee | K70: Neil | L70: McKay | M70: Ray | N70: Morris | O70: John | P70: Millyard | Q70: Jim | R70: McKeown | S70: Bill | T70: O'Brien | U70: Tomas | V70: Mezera | W70: Tomas | X70: Mezera | Y70: Win | Z70: Percy | AA70: Nick | AB70: Newton | AC70: Tony | AD70: Mulvihill | AE70: Larry | AF70: Perkins | AI70: Gary | AJ70: Waldon | AK70: Tony | AL70: Scott | AM70: Mark | AN70: Poole | AO70: Steve | AP70: Owen | AQ70: Greg | AR70: Murphy | AS70: Mark | AT70: Skaife | AU70: Anthony | AV70: Tratt | AW70: David | AX70: Thexton | AY70: Alex | AZ70: Yoong
A71: Brian | B71: Pyers | E71: W. | F71: Murison | G71: John | H71: Martin | I71: Chris | J71: McSorley | K71: Bill | L71: McLachlan | M71: Allan | N71: Mottram | O71: Allan | P71: Mottram | Q71: Bruce | R71: McPhee | S71: Mike | T71: Oliver | U71: Andrew | V71: Miedecke | W71: Andrew | X71: Miedecke | Y71: Larry | Z71: Perkins | AA71: Klaus | AB71: Niedzwiedz | AC71: Bill | AD71: O'Brien | AE71: Brett | AF71: Peters | AI71: Kevin | AJ71: Weeks | AK71: Bill | AL71: Seiders | AM71: Nathan | AN71: Pretty | AO71: David | AP71: Parsons | AQ71: Rod | AR71: Nash | AS71: Ashley | AT71: Stichbury | AU71: Wayne | AV71: Wakefield | AW71: Anthony | AX71: Tratt | AY71: Luke | AZ71: Youlden
A72: John | B72: Reaburn | E72: Wes | F72: Nalder | G72: Spencer | H72: Martin | I72: Brian | J72: Milton | K72: Bruce | L72: McPhee | M72: Barry | N72: Mulholland | O72: George | P72: Murray | Q72: Mel | R72: Mollison | S72: Anders | T72: Olofsson | U72: Graham | V72: Moore | W72: Graham | X72: Moore | Y72: Brett | Z72: Peters | AA72: Bill | AB72: O'Brien | AC72: Charlie | AD72: O'Brien | AE72: Michael | AF72: Preston | AI72: Garry | AJ72: Willmington | AK72: Glenn | AL72: Seton | AM72: Melinda | AN72: Price | AO72: David | AP72: Parsons | AQ72: Matt | AR72: Neal | AS72: Garth | AT72: Tander | AU72: Paul | AV72: Weel | AW72: Stephen | AX72: Voight
A73: George | B73: Reynolds | E73: Les | F73: Park | G73: Mike | H73: Martin | I73: Peter | J73: Mitchell[6] | K73: Trevor | L73: Meehan | M73: Jack | N73: Murray | O73: Jack | P73: Murray | Q73: Bob | R73: Morris | S73: Wayne | T73: Park | U73: Tony | V73: Mulvihill | W73: Tony | X73: Mulvihill | Y73: Drew | Z73: Price | AA73: Charlie | AB73: O'Brien | AC73: Anders | AD73: Olofsson | AE73: Melinda | AF73: Price | AK73: Rick | AL73: Shaw | AM73: Gary | AN73: Quartly | AO73: Darren | AP73: Pate | AQ73: Steve | AR73: Owen | AS73: Anthony | AT73: Tratt | AU73: Jamie | AV73: Whincup | AW73: Kerry | AX73: Wade
A74: John | B74: Roxburgh | E74: Frank | F74: Porter | G74: Frank | H74: Matich | I74: Allan | J74: Mottram | K74: Graham | L74: Moore | M74: Jack | N74: Nougher | O74: Kevin | P74: Nipperess | Q74: Ray | R74: Morris | S74: David | T74: Parsons | U74: Klaus | V74: Niedzwiedz | W74: Klaus | X74: Niedzwiedz | Y74: Paul | Z74: Radisich | AA74: Anders | AB74: Olofsson | AC74: David | AD74: Parsons | AE74: Paul | AF74: Radisich | AK74: Terry | AL74: Shiel | AM74: Steve | AN74: Reed | AO74: Larry | AP74: Perkins | AQ74: David'T' | AR74: Parsons | AS74: Wayne | AT74: Wakefield | AU74: Mathew | AV74: White | AW74: Wayne | AX74: Wakefield
A75: Geoff | B75: Russell | E75: George | F75: Poulton | G75: Phil | H75: McCumisky | I75: Brian | J75: Muir | K75: Ray | L75: Morris | M75: David | N75: O'Keefe | O75: Jack | P75: Nougher | Q75: Brian | R75: Muir | S75: Win | T75: Percy | U75: Tony | V75: Noske | W75: Bill | X75: O'Brien | Y75: Steve | Z75: Reed | AA75: Rohan | AB75: Onslow | AC75: Darren | AD75: Pate | AE75: Steve | AF75: Reed | AK75: Mark | AL75: Skaife | AM75: Steven | AN75: Richards | AO75: Brett | AP75: Peters | AQ75: David'S' | AR75: Parsons | AS75: Paul | AT75: Weel | AU75: Simon | AV75: Wills | AW75: Paul | AX75: Weel
A76: Ern | B76: Seeliger | E76: R. | F76: Poulton | G76: David | H76: McKay | I76: Barry | J76: Mulholland | K76: Allan | L76: Mottram | M76: Graham | N76: Porter | O76: David | P76: O'Keefe | Q76: Bob | R76: Muir | S76: Larry | T76: Perkins | U76: Bill | V76: O'Brien | W76: Charlie | X76: O'Brien | Y76: Jim | Z76: Richards | AA76: Wayne | AB76: Park | AC76: Bob | AD76: Pearson | AE76: Andrew | AF76: Reid | AK76: Chris | AL76: Smerdon | AM76: Jim | AN76: Richards | AO76: Mark | AP76: Poole | AQ76: Larry | AR76: Perkins | AS76: Mathew | AT76: White | AU76: Max | AV76: Wilson | AW76: Jamie | AX76: Whincup
A77: Lou | B77: Sinclair | E77: John | F77: Reaburn | G77: Jim | H77: McKeown | I77: George | J77: Murray | K77: Don | L77: Mudd | M77: John | N77: Prisk | O77: Hideo | P77: Oishi | Q77: Barry | R77: Mulholland | S77: Drew | T77: Price | U77: Charlie | V77: O'Brien | W77: Rohan | X77: Onslow | Y77: Dennis | Z77: Rogers | AA77: David | AB77: Parsons | AC77: Win | AD77: Percy | AE77: Jim | AF77: Richards | AK77: John | AL77: Smith | AM77: Paul | AN77: Romano | AO77: Nathan | AP77: Pretty | AQ77: Brett | AR77: Peters | AS77: Simon | AT77: Wills | AU77: Luke | AV77: Youlden | AW77: Matthew | AX77: White
A78: R. | B78: Slaney | E78: George | F78: Reynolds | G78: Bruce | H78: McPhee | I78: Mike | J78: Nedelko | K78: Barry | L78: Mulholland | M78: Barry | N78: Quayle | O78: Steve | P78: Parkes | Q78: Jack | R78: Mullins | S78: Paul | T78: Radisich | U78: Anders | V78: Olofsson | W78: Wayne | X78: Park | Y78: Brian | Z78: Sala | AA78: Win | AB78: Percy | AC78: Larry | AD78: Perkins | AE78: Brett | AF78: Riley | AK78: Malcolm | AL78: Stenniken | AM78: Mal | AN78: Rose | AO78: Melinda | AP78: Price | AQ78: Jason | AR78: Plato | AS78: Terry | AT78: Wyhoon | AW78: Simon | AX78: Wills
A79: Jim | B79: Smith | E79: Tony | F79: Reynolds | G79: Frederick George "Fearless Fred" | H79: Morgan | I79: Bert | J79: Needham | K79: Jack | L79: Murray | M79: Rick | N79: Radford | O79: Stan | P79: Pomroy | Q79: David | R79: O'Keefe | S79: David | T79: Ratcliff | U79: Rohan | V79: Onslow | W79: David | X79: Parsons | Y79: David | Z79: Sala | AA79: Larry | AB79: Perkins | AC79: Brett | AD79: Peters | AE79: Dennis | AF79: Rogers | AK79: Paul | AL79: Stokell | AM79: D'arcy | AN79: Russell | AO79: Gary | AP79: Quartly | AQ79: Miles | AR79: Pope | AS79: Luke | AT79: Youlden | AW79: Max | AX79: Wilson
A80: George | B80: Spanos | E80: Bill | F80: Roberts | G80: Brian | H80: Muir | I80: Bill | J80: Orr | K80: Bill | L80: Orr | M80: Brian | N80: Reed | O80: John | P80: Prisk | Q80: Arthur | R80: Olsen | S80: Steve | T80: Reed | U80: Wayne | V80: Park | W80: Bob | X80: Pearson | Y80: Edgar | Z80: Salwegter | AA80: Brett | AB80: Peters | AC80: Mike | AD80: Preston | AE80: Warwick | AF80: Rooklyn | AK80: Scotty | AL80: Taylor | AM80: Neil | AN80: Schembri | AO80: Paul | AP80: Radisich | AQ80: Nathan | AR80: Pretty | AW80: Mark | AX80: Winterbottom
A81: Doug | B81: Stewart | E81: Tom | F81: Roddy | G81: Jack | H81: Murray | I81: Les | J81: Park | K81: Fred | L81: Otten | M81: George | N81: Reynolds | O81: Rick | P81: Radford | Q81: Jim | R81: Palmer | S81: Jim | T81: Richards | U81: Win | V81: Percy | W81: Win | X81: Percy | Y81: Kyane | Z81: Scott | AA81: Malcom | AB81: Rea | AC81: Paul | AD81: Radisich | AE81: Wayne | AF81: Russell | AK81: Anthony | AL81: Tratt | AM81: Tony | AN81: Scott | AO81: Steve | AP81: Reed | AQ81: Melinda | AR81: Price | AW81: Luke | AX81: Youlden
A82: Fred | B82: Sutherland | E82: John | F82: Roxburgh | G82: George | H82: Murray | I82: Keith | J82: Pascall | K82: Stan | L82: Pomroy | M82: Tony | N82: Robards | O82: George | P82: Reynolds | Q82: Sid/Sib | R82: Petralia | S82: Brett | T82: Riley | U82: Larry | V82: Perkins | W82: Larry | X82: Perkins | Y82: Tony | Z82: Scott | AA82: Steve | AB82: Reed | AC82: Steve | AD82: Reed | AE82: Neil | AF82: Schembri | AK82: John | AL82: Trimbole | AM82: Glenn | AN82: Seton | AO82: Tony | AP82: Ricciardello | AQ82: Gary | AR82: Quartly
A83: Leo | B83: Taylor | E83: Geoff | F83: Russell | G83: Mike | H83: Nedelko | I83: Stan | J83: Pomroy | K83: John | L83: Prisk | M83: John | N83: Roxburgh | O83: Jane | P83: Richardson | Q83: Stan | R83: Pomroy | S83: Dennis | T83: Rogers | U83: Frank | V83: Porter | W83: Mark | X83: Poole | Y83: Ron | Z83: Searle | AA83: Manuel | AB83: Reuter | AC83: Jim | AD83: Richards | AE83: Tony | AF83: Scott | AK83: Brian | AL83: Walden | AM83: Bill | AN83: Sieders | AO83: Steven | AP83: Richards | AQ83: Paul | AR83: Radisich
A84: Tony | B84: Thieler | E84: Brian | F84: Sampson | G84: Bert | H84: Needham | I84: John | J84: Prisk | K84: John | L84: Reaburn | M84: Brian | N84: Sampson | O84: Bob | P84: Romano | Q84: John | R84: Prisk | S84: Garry | T84: Rogers | U84: Drew | V84: Price | W84: Mike | X84: Preston | Y84: Glenn | Z84: Seton | AA84: Jim | AB84: Richards | AC84: Dennis | AD84: Rogers | AE84: Glenn | AF84: Seton | AK84: Kevin | AL84: Waldock | AM84: Mark | AN84: Skaife | AO84: Jim | AP84: Richards | AQ84: Steve | AR84: Reed
A85: Barry | B85: Topen | E85: Charlie | F85: Smith | G85: Kevin | H85: Nicholson | I85: John | J85: Reaburn | K85: Brian | L85: Reed | M85: Mike | N85: Savva | O85: John | P85: Roxburgh | Q85: Rick | R85: Radford | S85: Brian | T85: Sampson | U85: Paul | V85: Radisich | W85: Drew | X85: Price | Y85: Keith | Z85: Sharp | AA85: Garry | AB85: Rogers | AC85: Garry | AD85: Rogers | AE85: Richard | AF85: Shaw | AK85: Bruce | AL85: Williams | AM85: Chris | AN85: Smerdon | AO85: Greg | AP85: Ritter | AQ85: Steven | AR85: Richards
A86: Bruce | B86: Walton | E86: Jim | F86: Smith | G86: Jim | H86: O'Shaunnessy | I86: Brian | J86: Reed | K86: George | L86: Reynolds | M86: Mike | N86: Schneider | O86: Brian | P86: Sampson | Q86: Brian | R86: Reed | S86: Gary | T86: Scott | U86: Steve | V86: Reed | W86: David | X86: Pullen | Y86: Terry | Z86: Shiel | AA86: Dennis | AB86: Rogers | AC86: Glenn | AD86: Seton | AE86: Bill | AF86: Sieders | AK86: Steve | AL86: Williams | AM86: Robert | AN86: Smith | AO86: Paul | AP86: Romano | AQ86: Jason | AR86: Richards
A87: Des | B87: West | E87: Fred | F87: Sutherland | G87: Les | H87: Park | I87: George | J87: Reynolds | K87: Tony | L87: Robards | M87: Barry | N87: Seton | O87: Mike | P87: Savva | Q87: George | R87: Reynolds | S87: Kayne | T87: Scott | U87: Jim | V87: Richards | W87: Paul | X87: Radisich | Y87: Mark | Z87: Skaife | AA87: Bryan | AB87: Sala | AC87: Mark | AD87: Skaife | AE87: Mark | AF87: Skaife | AK87: Garry | AL87: Willmington | AM87: Ashley | AN87: Stichbury | AO87: Tim | AP87: Rowse | AQ87: Jim | AR87: Richards
A88: G. | B88: White | E88: Tony | F88: Theiler | G88: John | H88: Reaburn | I88: Tony | J88: Reynolds | K88: Keith | L88: Russell | M88: Gary | N88: Shoesmith | O88: Mike | P88: Schneider | Q88: Tony | R88: Roberts | S88: Brian | T88: Selby | U88: Llynden | V88: Riethmuller | W88: David | X88: Ratcliff | Y88: John | Z88: Smith | AA88: David | AB88: Sala | AC88: John | AD88: Smith | AE88: Chris | AF88: Smerdon | AM88: Paul | AN88: Stokell | AO88: Darcy | AP88: Russell | AQ88: Greg | AR88: Ritter
A89: Doug | B89: Whiteford | E89: Rocky | F89: Tresise | G89: Tony | H89: Reynolds | I89: Alwyn | J89: Rose | K89: Geoff | L89: Russell | M89: Bill | N89: Slattery | O89: Glyn | P89: Scott | Q89: John | R89: Roxburgh | S89: Glenn | T89: Seton | U89: Brett | V89: Riley | W89: Steve | X89: Reed | Y89: Ian | Z89: Spurle | AA89: Glenn | AB89: Seton | AC89: Steve | AD89: Soper | AE89: Malcolm | AF89: Stenniken | AM89: Garth | AN89: Tander | AO89: Rod | AP89: Salmon | AQ89: Paul | AR89: Romano
A90: Arthur | B90: Wylie | E90: P. | F90: Trueman | G90: George | H90: Reynolds | I90: John | J90: Roxburgh | K90: Ralph | L90: Sach | M90: Charlie | N90: Smith | O90: David | P90: Seldon | Q90: Brian | R90: Sampson | S90: Terry | T90: Shiel | U90: Dennis | V90: Rogers | W90: Jim | X90: Richards | Y90: Bruce | Z90: Stewart | AA90: Terry | AB90: Shiel | AC90: Bruce | AD90: Stewart | AE90: Alan Scotty | AF90: Taylor | AM90: Scotty | AN90: Taylor | AO90: Neil | AP90: Schembri | AQ90: Mal | AR90: Rose
A91: Ken | B91: Wylie | E91: Cliff | F91: van Praag | G91: Bill | H91: Reynolds | I91: Keith | J91: Russell | K91: Bob | L91: Salter | M91: Ken | N91: Stacey | O91: Barry | P91: Seton | Q91: Mike | R91: Savva | S91: Christer | T91: Simonsen | U91: Garry | V91: Rogers | W91: Brett | X91: Riley | Y91: Darren | Z91: Stewart | AA91: Mark | AB91: Skaife | AC91: Brad | AD91: Stratton | AE91: John | AF91: Trimbole | AM91: Anthony | AN91: Tratt | AO91: Tony | AP91: Scott | AQ91: Rob | AR91: Russell
A92: Gavin | B92: Youl | E92: A. | F92: Waite | G92: Alwyn | H92: Rose | I92: Ralph | J92: Sach | K92: Brian | L92: Sampson | M92: Bill | N92: Stanley | O92: Barry | P92: Sharp | Q92: Ray | R92: Scanlan | S92: Mark | T92: Skaife | U92: Andy | V92: Rouse | W92: Dennis | X92: Rogers | Y92: Brad | Z92: Stratton | AA92: John | AB92: Smith | AC92: John | AD92: Trimbole | AE92: Kevin | AF92: Waldock | AM92: G. | AN92: Waldon | AO92: Glenn | AP92: Seton | AQ92: Rod | AR92: Salmon
A93: John | B93: Youl | E93: M. | F93: Watson | G93: Geoff | H93: Russell | I93: Bob | J93: Salter | K93: Glyn | L93: Scott | M93: Max | N93: Stewart | O93: Bob | P93: Skelton | Q93: Glyn | R93: Scott | S93: John | T93: Smith | U93: Brian | V93: Sampson | W93: Garry | X93: Rogers | Y93: Gregg | Z93: Taylor | AA93: Brad | AB93: Stratton | AC93: Des | AD93: Wall | AE93: Garry | AF93: Waldon | AM93: T | AN93: Wanless | AO93: Tim | AP93: Shaw | AQ93: Neil | AR93: Schembri
E94: Ian | F94: Wells | G94: Graham | H94: Ryan | I94: John | J94: Schroder | K94: Barry | L94: Seton | M94: Laurie | N94: Stewart | O94: John | P94: Smailes | Q94: David | R94: Seldon | S94: Steve | T94: Soper | U94: John | V94: Sax | W94: Andy | X94: Rouse | Y94: Bob | Z94: Tindal | AA94: Ken | AB94: Talbert | AC94: Tom | AD94: Watkinson | AE94: Phil | AF94: Ward | AM94: Paul | AN94: Weel | AO94: Ric | AP94: Shaw | AQ94: Phillip | AR94: Scifleet
E95: Peter | F95: White | G95: Ralph | H95: Sach | I95: Barry | J95: Seton | K95: Gary | L95: Shoesmith | M95: Doug | N95: Stewart | O95: Jim | P95: Smith | Q95: Barry | R95: Seton | S95: John | T95: Sorensen | U95: Gary | V95: Scott | W95: Garry | X95: Rush | Y95: Peter | Z95: Verheyen | AA95: Ken | AB95: Talbot | AC95: Garry | AD95: Willmington | AE95: Don | AF95: Watson1 | AM95: Garry | AN95: Willmington | AO95: Bill | AP95: Sieders | AQ95: Glenn | AR95: Seton
E96: Doug | F96: Whiteford | G96: Barry | H96: Seton | I96: Tony | J96: Simmons | K96: Tony | L96: Simmons | M96: Fred | N96: Sutherland | O96: Don | P96: Smith | Q96: John | R96: Smailes | S96: Bruce | T96: Stewart | U96: Glenn | V96: Seton | W96: David | X96: Sala | Y96: John | Z96: Vernon | AA96: Bob | AB96: Tindal | AC96: Richard | AD96: Wilson | AE96: Steve | AF96: Williams | AM96: Simon | AN96: Wills | AO96: Mark | AP96: Skaife | AQ96: Bill | AR96: Sieders
E97: Bill | F97: Wilson | G97: Charlie | H97: Smith | I97: Bob | J97: Skelton | K97: Bill | L97: Slattery | M97: John | N97: T. | O97: John T. | P97: Smith | Q97: Charlie | R97: Smith | S97: Bob | T97: Tindal | U97: Terry | V97: Shiel | W97: Brian | X97: Sampson | Y97: Richard | Z97: Vorst | AA97: John | AB97: Trimble | AC97: Joachim | AD97: Winkelhock | AE97: Garry | AF97: Willmington | AM97: Rod | AN97: Wilson | AO97: Chris | AP97: Smerdon | AQ97: Luke | AR97: Sieders
G98: Ron | H98: Smith | I98: Charlie | J98: Smith | K98: Don | L98: Smith | M98: Kunimitsu | N98: Takahashi | O98: Charlie | P98: Smith | Q98: Don | R98: Smith | S98: Ian | T98: Tulloch | U98: Mark | V98: Skaife | W98: Ron | X98: Searle | Y98: Kevin | Z98: Waldock | AA98: John | AB98: Trimbole | AC98: Brett | AD98: Youlden | AE98: Richard | AF98: Wilson | AO98: Garth | AP98: Tander | AQ98: Tim | AR98: Sipp
G99: Bruce | H99: Smith | I99: Bill | J99: Stanley | K99: Charlie | L99: Smith | M99: Herb | N99: Taylor | O99: Bob | P99: Sorrenson | Q99: Dick | R99: Sorenson | S99: Tom | T99: Walkinshaw | U99: Tim | V99: Slako | W99: David | X99: Sears | Y99: Garry | Z99: Waldron | AA99: Peter | AB99: Verheyen | AE99: Brett | AF99: Youlden | AO99: Scotty | AP99: Taylor | AQ99: Mark | AR99: Skaife
G100: Bill | H100: Stanley | I100: Max | J100: Stewart | K100: Bill | L100: Stanley | M100: Arthur | N100: Treloar | O100: Ken | P100: Stacey | Q100: Ken | R100: Stacey | S100: Phil | T100: Ward | U100: Lester | V100: Smerdon | W100: Glenn | X100: Seton | Y100: John | Z100: White | AA100: Kevin | AB100: Waldock | AO100: Bob | AP100: Thorn | AQ100: Paul | AR100: Stokell
G101: Laurie | H101: Stewart | I101: Laurie | J101: Stewart | K101: Max | L101: Stewart | M101: Max | N101: Volkers | O101: Max | P101: Stahl | Q101: Max | R101: Stahl | S101: Garry | T101: Willmington | U101: Clive | V101: Smith | W101: Terry | X101: Shiel | Y101: Garry | Z101: Willmington | AA101: Des | AB101: Wall | AO101: Anthony | AP101: Tratt | AQ101: Garth | AR101: Tander
G102: Doug | H102: Stewart | I102: Fred | J102: Sutherland | K102: Bruce | L102: Stewart | M102: Warren | N102: Weldon | O102: Bill | P102: Stanley | Q102: Bill | R102: Stanley | U102: John | V102: Smith | W102: Mark | X102: Skaife | Y102: Brad | Z102: Wright | AA102: Tom | AB102: Watkinson | AO102: John | AP102: Trimbole | AQ102: Anthony | AR102: Tratt
G103: Fred | H103: Sutherland | I103: Herb | J103: Taylor | K103: Laurie | L103: Stewart | M103: Des | N103: West | O103: Max | P103: Stewart | Q103: Laurie | R103: Stewart | U103: Damon | V103: Smith | W103: Lester | X103: Smerdon | AA103: Don | AB103: Watson | AO103: Wayne | AP103: Wakefield | AQ103: Stephen | AR103: Voight
G104: Herb | H104: Taylor | I104: Barry | J104: Thiele | K104: Fred | L104: Sutherland | M104: Doug | N104: Whiteford | O104: Laurie | P104: Stewart | Q104: Bruce | R104: Stewart | U104: Joe | V104: Sommariva | W104: John | X104: Smith | AA104: Kevin | AB104: Weeks | AO104: Dean | AP104: Wanless | AQ104: Wayne | AR104: Wakefield
G105: Ron | H105: Thorp | I105: Bryan | J105: Thomson | K105: P. | L105: Taylor | M105: Peter | N105: Williamson | O105: Fred | P105: Sutherland | Q105: Jim | R105: Sullivan | U105: Bruce | V105: Stewart | W105: Heather | X105: Spurle | AA105: Garry | AB105: Willmington | AO105: Todd | AP105: Wanless | AQ105: Adam | AR105: Wallis
G106: Rocky | H106: Tresise | I106: Rocky | J106: Tresise | K106: Herb | L106: Taylor | M106: Bruce | N106: Wright | O106: Kunimitsu | P106: Takahashi | Q106: Ym | R106: Sunago | U106: Alan"Scotty" | V106: Taylor | W106: Bernie | X106: Stack | AA106: Richard | AB106: Wilson | AO106: Paul | AP106: Weel | AQ106: Paul | AR106: Weel
G107: Jerry | H107: Trevor-Jones | I107: Jerry | J107: Trevor-Jones | K107: Evan | L107: Thomas | M107: Bob | N107: Young | O107: Barry | P107: Tapsall | Q107: Kunimitsu | R107: Takahashi | U107: Bryan | V107: Thomson | W107: Bruce | X107: Stewart | AA107: Brad | AB107: Wright | AO107: Damien | AP107: White | AQ107: Matthew | AR107: White
G108: Max | H108: Volkers | I108: David | J108: Walker | K108: Arthur | L108: Treloar | O108: Herb | P108: Taylor | Q108: Herb | R108: Taylor | U108: Bob | V108: Tindal | W108: Paul | X108: Stokell | AO108: Matthew | AP108: White | AQ108: Damien | AR108: White
G109: David | H109: Walker | I109: Warren | J109: Weldon | K109: Max | L109: Volkers | O109: Jeff | P109: Thompson | Q109: Hans | R109: Tholstrup | U109: Paul | V109: Trevethan | W109: Bryan | X109: Thomson | AO109: Mark | AP109: Williams | AQ109: Steve | AR109: Williams
G110: Les | H110: Weiley | I110: Phil | J110: West | K110: David | L110: Walker | O110: Dick | P110: Thurston | Q110: Dick | R110: Thurston | U110: Craig | V110: Turner | W110: Paul | X110: Trevethan | AO110: Garry | AP110: Willmington | AQ110: Garry | AR110: Willmington
G111: Warren | H111: Weldon | I111: John | J111: White | K111: Graham | L111: Ward | O111: David | P111: Toshack | Q111: Bill | R111: Tuckey | U111: Marty | V111: Turpin | W111: Mike | X111: Twigden | AO111: Simon | AP111: Wills | AQ111: Simon | AR111: Wills
G112: Des | H112: West | I112: Lionel | J112: Williams | K112: Colin | L112: Wear | O112: Arthur | P112: Treloar | Q112: Peter | R112: Ulbrich | U112: Lou | V112: Vandermeer | W112: Peter | X112: Verheyen | AQ112: Terry | AR112: Wyhoon
G113: Graham | H113: White | I113: Peter | J113: Williamson | K113: Warren | L113: Weldon | O113: Bill | P113: Tuckey | Q113: Max | R113: Volkers | U113: Richard | V113: Vorst | W113: Richard | X113: Vorst | AQ113: Luke | AR113: Youlden
G114: Jim | H114: White | I114: Bruce | J114: Wilson | K114: Des | L114: West | O114: Warren | P114: Weldon | Q114: Bob | R114: Watson | U114: Matt | V114: Wacker | W114: Matt | X114: Wacker
G115: Ken | H115: Wilkinson | I115: Kennedy | K115: Ken | L115: Wiggins | O115: Des | P115: West | Q115: Warren | R115: Weldon | U115: Kevin | V115: Waldock | W115: Kevin | X115: Waldock
G116: Jim | H116: Wright | I116: Budda | K116: Lionel | L116: Williams | O116: Geoff | P116: Westbury | Q116: Des | R116: West | U116: Des | V116: Wall | W116: Phil | X116: Ward
G117: Adrian | H117: Yannucelli | I117: Stewart[2] | K117: Bob | L117: Young | O117: Doug | P117: Whiteford | Q117: Phil | R117: West | U117: Tom | V117: Watkinson | W117: Garry | X117: Willmington
I118: Smith[2] | O118: Midge | P118: Whiteman | Q118: Doug | R118: Whiteford | U118: Steve | V118: Williams
I119: unknown[2] | O119: Bob | P119: Wilkinson | Q119: Midge | R119: Whiteman | U119: Garry | V119: Willmington
O120: Peter | P120: Williamson | Q120: Bob | R120: Wilkinson
O121: Bob | P121: Young | Q121: Roger | R121: Withers
S151: =COUNTA(S2:S150) | T151: drivers in 1988 | W151: =COUNTA(W2:W150) | X151: drivers in 1990
AM152: =COUNTA(AM2:AM151) | AN152: drivers in 1998
U153: =COUNTA(U2:U152) | V153: drivers in 1989 | AA153: =COUNTA(AA2:AA152) | AB153: drivers in 1992
AE154: =COUNTA(AE2:AE153) | AF154: drivers in 1994 | BG154: =COUNTA(BG2:BG153) | BH154: drivers in 2008
A155: =COUNTA(A2:A154) | B155: drivers in 1960 | C155: =COUNTA(C2:C154) | D155: drivers in 1961 | E155: =COUNTA(E2:E154) | F155: drivers in 1962 | G155: =COUNTA(G2:G154) | H155: drivers in 1963 | I155: =COUNTA(I2:I154) | J155: drivers in 1964 | K155: =COUNTA(K2:K154) | L155: drivers in 1965 | M155: =COUNTA(M2:M154) | N155: drivers in 1966 | O155: =COUNTA(O2:O154) | P155: drivers in 1967 | Q155: =COUNTA(Q2:Q154) | R155: drivers in 1968 | Y155: =COUNTA(Y2:Y124) | Z155: drivers in 1991 | AC155: =COUNTA(AC2:AC154) | AD155: drivers in 1993 | AG155: =COUNTA(AG2:AG154) | AH155: drivers in 1995 | AI155: =COUNTA(AI2:AI154) | AJ155: drivers in 1996 | AK155: =COUNTA(AK2:AK154) | AL155: drivers in 1997 | AO155: =COUNTA(AO2:AO154) | AP155: drivers in 1999 | AQ155: =COUNTA(AQ2:AQ154) | AR155: drivers in 2000 | AS155: =COUNTA(AS2:AS154) | AT155: drivers in 2001 | AU155: =COUNTA(AU2:AU154) | AV155: drivers in 2002 | AW155: =COUNTA(AW2:AW154) | AX155: drivers in 2003 | AY155: =COUNTA(AY2:AY154) | AZ155: drivers in 2004 | BA155: =COUNTA(BA2:BA154) | BB155: drivers in 2005 | BC155: =COUNTA(BC2:BC154) | BD155: drivers in 2006 | BE155: =COUNTA(BE2:BE154) | BF155: drivers in 2007 | BI155: =COUNTA(BI2:BI154) | BJ155: drivers in 2009 | BK155: =COUNTA(BK2:BK154) | BL155: drivers in 2010 | BM155: =COUNTA(BM2:BM154) | BN155: drivers in 2011 | BO155: =COUNTA(BO2:BO154) | BP155: drivers in 2012 | BQ155: =COUNTA(BQ2:BQ154) | BR155: drivers in 2013 | BS155: =COUNTA(BS2:BS154) | BT155: drivers in 2014 | BU155: =COUNTA(BU2:BU154) | BV155: drivers in 2015 | BW155: =COUNTA(BW2:BW154) | BX155: drivers in 2016 | BY155: =COUNTA(BY2:BY154) | BZ155: drivers in 2017 | CA155: =COUNTA(CA2:CA154) | CB155: drivers in 2018 | CC155: =COUNTA(CC2:CC154) | CD155: drivers in 2019 | CE155: =COUNTA(CE2:CE154) | CF155: drivers in 2020 | CG155: =COUNTA(CG2:CG154) | CH155: drivers in 2021 | CI155: =COUNTA(CI2:CI154) | CJ155: drivers in 2022 | CK155: =COUNTA(CK2:CK154) | CL155: drivers in 2023 | CM155: =COUNTA(CM2:CM154) | CN155: drivers in 2024 | CO155: =COUNTA(CO2:CO154) | CP155: drivers in 2025
A158: Year | B158: Driver Count
A159: 1960 | B159: 92
A160: 1961 | B160: 62
A161: 1962 | B161: 96
A162: 1963 | B162: 116
A163: 1964 | B163: 118
A164: 1965 | B164: 116
A165: 1966 | B165: 106
A166: 1967 | B166: 120
...

Sheet Yearly Race Winners
A2: Year | B2: Event Name | D2: Driver(s) | F2: Driver(s) | H2: Driver(s) | J2: Car | O2: Race average speed
E3: Country | G3: Country | K3: Laps | M3: Elapsed time
A4: Phillip Island (500 Miles)
A5: 1960 | B5: Armstrong 500 | C5: 1 | D5: John Roxburgh | E5: AUS | F5: Frank Coad | G5: AUS | J5: Vauxhall Cresta | K5: 167 | M5: 8h 20m 45.0s | O5: 96.42 km/h | Q5: 59.91 mph
A6: 1961 | B6: Armstrong 500 | C6: 1 | D6: Bob Jane | E6: AUS | F6: Harry Firth | G6: AUS | J6: Mercedes-Benz 220SE | K6: 167 | M6: 8h 0m 31.0s | O6: 100.48 km/h | Q6: 62.43 mph
A7: 1962 | B7: Armstrong 500 | C7: 1 | D7: Harry Firth | E7: AUS | F7: Bob Jane | G7: AUS | J7: Ford XL Falcon | K7: 167 | M7: 8h 15m 16.0s | O7: 97.48 km/h | Q7: 60.57 mph
A8: Mount Panorama (500 Miles)
A9: 1963 | B9: Armstrong 500 | C9: 1 | D9: Harry Firth | E9: AUS | F9: Bob Jane | G9: AUS | J9: Ford Cortina Mk.I GT | K9: 130 | M9: 7h 47m 14.0s | O9: 103.33 km/h | Q9: 64.21 mph
A10: 1964 | B10: Armstrong 500 | C10: 1 | D10: Bob Jane | E10: AUS | F10: George Reynolds | G10: AUS | J10: Ford Cortina Mk.I GT | K10: 130 | M10: — | O10: — | Q10: —
A11: 1965 | B11: Armstrong 500 | D11: Barry Seton | E11: AUS | F11: Midge Bosworth | G11: AUS | J11: Ford Cortina Mk.I GT500 | K11: 130 | M11: 7h 16m 45.1s | O11: 110.54 km/h | Q11: 68.69 mph
A12: 1966 | B12: Gallaher 500 | D12: Rauno Aaltonen | E12: FIN | F12: Bob Holden | G12: AUS | J12: Morris Cooper S | K12: 130 | M12: 7h 11m 29.1s | O12: 111.89 km/h | Q12: 69.53 mph
A13: 1967 | B13: Gallaher 500 | D13: Harry Firth | E13: AUS | F13: Fred Gibson | G13: AUS | J13: Ford XR Falcon GT | K13: 130 | M13: 6h 55m 8.0s | O13: 116.30 km/h | Q13: 72.27 mph
A14: 1968 | B14: Hardie-Ferodo 500 | D14: Bruce McPhee | E14: AUS | F14: Barry Mulholland | G14: AUS | J14: Holden HK Monaro GTS327 | K14: 130 | M14: 6h 44m 7.0s | O14: 119.47 km/h | Q14: 74.24 mph
A15: 1969 | B15: Hardie-Ferodo 500 | D15: Colin Bond | E15: AUS | F15: Tony Roberts | G15: AUS | J15: Holden HT Monaro GTS350 | K15: 130 | M15: 6h 32m 25s | O15: 123.16 km/h | Q15: 76.53 mph
A16: 1970 | B16: Hardie-Ferodo 500 | D16: Allan Moffat | E16: CAN | J16: Ford XW Falcon GTHO Phase II | K16: 130 | M16: 6h 33m 47.0s | O16: 122.61 km/h | Q16: 76.18 mph
A17: 1971 | B17: Hardie-Ferodo 500 | D17: Allan Moffat | E17: CAN | J17: Ford XY Falcon GTHO Phase III | K17: 130 | M17: 6h 9m 49.5s | O17: 130.55 km/h | Q17: 81.12 mph
A18: 1972 | B18: Hardie-Ferodo 500 | D18: Peter Brock | E18: AUS | J18: Holden LJ Torana GTR XU-1 | K18: 130 | M18: 6h 1m 53.0s | O18: 133.41 km/h | Q18: 82.90 mph
A19: Mount Panorama (1,000 Kilometres)
A20: 1973 | B20: Hardie-Ferodo 1000 | D20: Allan Moffat | E20: CAN | F20: Ian Geoghegan | G20: AUS | J20: Ford XA Falcon GT Hardtop | K20: 163 | M20: 7h 20m 6.8s | O20: 136.33 km/h | Q20: 84.71 mph
A21: 1974 | B21: Hardie-Ferodo 1000 | D21: John Goss | E21: AUS | F21: Kevin Bartlett | G21: AUS | J21: Ford XA Falcon GT Hardtop | K21: 163 | M21: 7h 51m 43.0s | O21: 127.19 km/h | Q21: 79.04 mph
A22: 1975 | B22: Hardie-Ferodo 1000 | D22: Peter Brock | E22: AUS | F22: Brian Sampson | G22: AUS | J22: Holden LH Torana SL/R 5000 L34 | K22: 163 | M22: 7h 10m 11.3s | O22: 139.47 km/h | Q22: 86.66 mph
A23: 1976 | B23: Hardie-Ferodo 1000 | D23: Bob Morris | E23: AUS | F23: John Fitzpatrick | G23: GBR | J23: Holden LH Torana SL/R 5000 L34 | K23: 163 | M23: 7h 7m 12.0s | O23: 140.45 km/h | Q23: 87.27 mph
A24: 1977 | B24: Hardie-Ferodo 1000 | D24: Allan Moffat | E24: CAN | F24: Jacky Ickx | G24: BEL | J24: Ford XC Falcon GS500 Hardtop | K24: 163 | M24: 6h 59m 7.8s | O24: 143.15 km/h | Q24: 88.95 mph
A25: 1978 | B25: Hardie-Ferodo 1000 | D25: Peter Brock | E25: AUS | F25: Jim Richards | G25: NZL | J25: Holden LX Torana A9X SS Hatchback | K25: 163 | M25: 6h 45m 53.9s | O25: 147.82 km/h | Q25: 91.85 mph
A26: 1979 | B26: Hardie-Ferodo 1000 | D26: Peter Brock | E26: AUS | F26: Jim Richards | G26: NZL | J26: Holden LX Torana A9X SS Hatchback | K26: 163 | M26: 6h 38m 15.8s | O26: 150.65 km/h | Q26: 93.61 mph
A27: 1980 | B27: Hardie-Ferodo 1000 | D27: Peter Brock | E27: AUS | F27: Jim Richards | G27: NZL | J27: Holden VC Commodore | K27: 163 | M27: 6h 47m 52.7s | O27: 147.10 km/h | Q27: 91.41 mph
A28: 1981 | B28: James Hardie 1000 | D28: Dick Johnson | E28: AUS | F28: John French | G28: AUS | J28: Ford XD Falcon | K28: 120 | L28: 2 | M28: 4h 53m 52.7s | O28: 150.31 km/h | Q28: 93.40 mph
A29: 1982 | B29: James Hardie 1000 | D29: Peter Brock | E29: AUS | F29: Larry Perkins | G29: AUS | J29: Holden VH Commodore SS | K29: 163 | M29: 6h 32m 3.2s | O29: 153.04 km/h | Q29: 95.09 mph
A30: 1983 | B30: James Hardie 1000 | D30: Peter Brock | E30: AUS | F30: John Harvey | G30: AUS | H30: Larry Perkins | I30: AUS | J30: Holden VH Commodore SS | K30: 163 | M30: 6h 28m 31.6s | O30: 154.43 km/h | Q30: 95.96 mph
A31: 1984 | B31: James Hardie 1000 | D31: Peter Brock | E31: AUS | F31: Larry Perkins | G31: AUS | J31: Holden VK Commodore | K31: 163 | M31: 6h 23m 13.06s | O31: 156.57 km/h | Q31: 97.29 mph
A32: 1985 | B32: James Hardie 1000 | D32: John Goss | E32: AUS | F32: Armin Hahne | G32: DEU | J32: Jaguar XJ-S | K32: 163 | M32: 6h 41m 30.19s | O32: 149.44 km/h | Q32: 92.86 mph
A33: 1986 | B33: James Hardie 1000 | D33: Allan Grice | E33: AUS | F33: Graeme Bailey | G33: AUS | J33: Holden VK Commodore SS Group A | K33: 163 | M33: 6h 30m 35.68s | O33: 153.61 km/h | Q33: 95.45 mph
A34: 1987 | B34: James Hardie 1000 | D34: Peter Brock | E34: AUS | F34: David Parsons | G34: AUS | H34: Peter McLeod | I34: AUS | J34: Holden VL Commodore SS Group A | K34: 158 | L34: 3 | M34: 7h 1m 8.4s | O34: 139.82 km/h | P34: 8 | Q34: 86.88 mph
A35: 1988 | B35: Tooheys 1000 | D35: Tony Longhurst | E35: AUS | F35: Tomas Mezera | G35: AUS | J35: Ford Sierra RS500 | K35: 161 | M35: 7h 2m 10.28s | O35: 142.12 km/h | Q35: 88.31 mph
A36: 1989 | B36: Tooheys 1000 | D36: Dick Johnson | E36: AUS | F36: John Bowe | G36: AUS | J36: Ford Sierra RS500 | K36: 161 | M36: 6h 30m 53.44s | O36: 153.50 km/h | Q36: 95.38 mph
A37: 1990 | B37: Tooheys 1000 | D37: Win Percy | E37: GBR | F37: Allan Grice | G37: AUS | J37: Holden VL Commodore SS Group A SV | K37: 161 | M37: 6h 40m 52.64s | O37: 149.67 km/h | Q37: 93.00 mph
A38: 1991 | B38: Tooheys 1000 | D38: Jim Richards | E38: NZL | F38: Mark Skaife | G38: AUS | J38: Nissan Skyline BNR32 GT-R | K38: 161 | M38: 6h 19m 14.80s | O38: 158.21 km/h | Q38: 98.31 mph
A39: 1992 | B39: Tooheys 1000 | D39: Mark Skaife | E39: AUS | F39: Jim Richards | G39: NZL | J39: Nissan Skyline BNR32 GT-R | K39: 143 | L39: 2 | M39: 6h 27m 16.22s | O39: 137.61 km/h | Q39: 85.51 mph
A40: 1993 | B40: Tooheys 1000 | D40: Larry Perkins | E40: AUS | F40: Gregg Hansford | G40: AUS | J40: Holden VP Commodore | K40: 161 | M40: 6h 29m 6.69s | O40: 154.19 km/h | Q40: 95.81 mph
A41: 1994 | B41: Tooheys 1000 | D41: Dick Johnson | E41: AUS | F41: John Bowe | G41: AUS | J41: Ford EB Falcon | K41: 161 | M41: 7h 3m 45.8425s | O41: 141.5882 km/h | Q41: 87.9788 mph
A42: 1995 | B42: Tooheys 1000 | D42: Larry Perkins | E42: AUS | F42: Russell Ingall | G42: AUS | J42: Holden VR Commodore | K42: 161 | M42: 6h 20m 32.4766s | O42: 157.6701 km/h | Q42: 97.9717 mph
A43: 1996 | B43: AMP Bathurst 1000 | D43: Craig Lowndes | E43: AUS | F43: Greg Murphy | G43: NZL | J43: Holden VR Commodore | K43: 161 | M43: 7h 9m 28.3584s | O43: 139.7062 km/h | Q43: 86.8094 mph
A44: 1997 | B44: AMP Bathurst 1000 | D44: Geoff Brabham | E44: AUS | F44: David Brabham | G44: AUS | J44: BMW 320i | K44: 161 | L44: 4 | M44: 6h 41m 25.4072s | O44: 149.4681 km/h | Q44: 92.8752 mph
A45: 1997 | B45: Primus 1000 Classic | C45: 5 | D45: Larry Perkins | E45: AUS | F45: Russell Ingall | G45: AUS | J45: Holden VS Commodore | K45: 161 | M45: 6h 21m 55.5483s | O45: 157.0986 km/h | Q45: 97.6165 mph
A46: 1998 | B46: AMP Bathurst 1000 | D46: Rickard Rydell | E46: SWE | F46: Jim Richards | G46: NZL | J46: Volvo S40 | K46: 161 | M46: 6h 54m 23.4756s | O46: 144.7907 km/h | Q46: 89.9688 mph
A47: 1998 | B47: FAI 1000 | C47: 5 | D47: Jason Bright | E47: AUS | F47: Steven Richards | G47: NZL | J47: Ford EL Falcon | K47: 161 | M47: 6h 42m 23.9039s | O47: 149.1060 km/h | Q47: 92.6501 mph
A48: 1999 | B48: FAI 1000 | D48: Steven Richards | E48: NZL | F48: Greg Murphy | G48: NZL | J48: Holden VT Commodore | K48: 161 | M48: 6h 51m 48.8354s | O48: 145.6969 km/h | Q48: 90.5318 mph
A49: 2000 | B49: FAI 1000 | D49: Garth Tander | E49: AUS | F49: Jason Bargwanna | G49: AUS | J49: Holden VT Commodore | K49: 161 | M49: 7h 23m 30.2348s | O49: 135.3259 km/h | Q49: 84.0876 mph
A50: 2001 | B50: V8 Supercar 1000 | D50: Mark Skaife | E50: AUS | F50: Tony Longhurst | G50: AUS | J50: Holden VX Commodore | K50: 161 | M50: 6h 50m 33.1789s | O50: 146.1872 km/h | Q50: 90.8365 mph
A51: 2002 | B51: Bob Jane T-Marts 1000 | D51: Mark Skaife | E51: AUS | F51: Jim Richards | G51: NZL | J51: Holden VX Commodore | K51: 161 | M51: 6h 58m 41.0260s | O51: 143.3482 km/h | Q51: 89.0724 mph
A52: 2003 | B52: Bob Jane T-Marts 1000 | D52: Greg Murphy | E52: NZL | F52: Rick Kelly | G52: AUS | J52: Holden VY Commodore | K52: 161 | M52: 6h 32m 55.4044s | O52: 152.7463 km/h | Q52: 94.9121 mph
A53: 2004 | B53: Bob Jane T-Marts 1000 | D53: Greg Murphy | E53: NZL | F53: Rick Kelly | G53: AUS | J53: Holden VY Commodore | K53: 161 | M53: 6h 29m 36.2055s | O53: 154.0479 km/h | Q53: 95.7209 mph
A54: 2005 | B54: Supercheap Auto 1000 | D54: Mark Skaife | E54: AUS | F54: Todd Kelly | G54: AUS | J54: Holden VZ Commodore | K54: 161 | M54: 6h 37m 17.0012s | O54: 151.0700 km/h | Q54: 93.8705 mph
A55: 2006 | B55: Supercheap Auto Bathurst 1000 | D55: Craig Lowndes | E55: AUS | F55: Jamie Whincup | G55: AUS | J55: Ford BA Falcon | K55: 161 | M55: 6h 59m 53.5852s | O55: 142.9354 km/h | Q55: 88.8159 mph
A56: 2007 | B56: Supercheap Auto Bathurst 1000 | D56: Craig Lowndes | E56: AUS | F56: Jamie Whincup | G56: AUS | J56: Ford BF Falcon | K56: 161 | M56: 6h 29m 10.1985s | O56: 154.2195 km/h | Q56: 95.8275 mph
A57: 2008 | B57: Supercheap Auto Bathurst 1000 | D57: Craig Lowndes | E57: AUS | F57: Jamie Whincup | G57: AUS | J57: Ford BF Falcon | K57: 161 | M57: 6h 26m 00.4291s | O57: 155.4831 km/h | Q57: 96.6127 mph
A58: 2009 | B58: Supercheap Auto Bathurst 1000 | D58: Will Davison | E58: AUS | F58: Garth Tander | G58: AUS | J58: Holden VE Commodore | K58: 161 | M58: 6h 40m 02.4884s | O58: 150.0284 km/h | Q58: 93.2233 mph
A59: 2010 | B59: Supercheap Auto Bathurst 1000 | D59: Craig Lowndes | E59: AUS | F59: Mark Skaife | G59: AUS | J59: Holden VE Commodore | K59: 161 | M59: 6h 12m 51.4153s | O59: 160.9668 km/h | Q59: 100.0201 mph
... A62: 2013 | B62: Supercheap Auto Bathurst 1000 | D62: Mark Winterbottom | E62: AUS | F62: Steven Richards | G62: NZL | J62: Ford FG Falcon | K62: 161 | M62: 6h 11m 27.9315s | O62: 161.5697 km/h | Q62: 100.3948 mph
A63: 2014 | B63: Supercheap Auto Bathurst 1000 | D63: Chaz Mostert | E63: AUS | F63: Paul Morris | G63: AUS | J63: Ford FG Falcon | K63: 161 | M63: 7h 58m 53.2052s | N63: 6 | O63: 125.3273 km/h | Q63: 77.8914 mph
A64: 2015 | B64: Supercheap Auto Bathurst 1000 | D64: Craig Lowndes | E64: AUS | F64: Steven Richards | G64: NZL | J64: Holden VF Commodore | K64: 161 | M64: 6h 16m 07.7064s | O64: 159.5667 km/h | Q64: 99.1714 mph
A65: 2016 | B65: Supercheap Auto Bathurst 1000 | D65: Will Davison | E65: AUS | F65: Jonathon Webb | G65: AUS | I65: 7 | J65: Holden VF Commodore | K65: 161 | M65: 6h 19m 25.3237s | O65: 158.1816 km/h | Q65: 98.3105 mph
A66: 2017 | B66: Supercheap Auto Bathurst 1000 | D66: David Reynolds | E66: AUS | F66: Luke Youlden | G66: AUS | J66: Holden VF Commodore | K66: 161 | M66: 7h 11m 45.5456s | O66: 139.0071 km/h | Q66: 86.3844 mph
A67: 2018 | B67: Supercheap Auto Bathurst 1000 | D67: Craig Lowndes | E67: AUS | F67: Steven Richards | G67: NZL | J67: Holden ZB Commodore | K67: 161 | M67: 6h 01m 44.8637s | O67: 165.9100 km/h | Q67: 103.0917 mph | R67: 9
A68: 2019 | B68: Supercheap Auto Bathurst 1000 | D68: Scott McLaughlin | E68: NZL | F68: Alexandre Prémat | G68: FRA | J68: Ford Mustang GT | K68: 161 | M68: 6h 27m 51.5260s | O68: 154.7408 km/h | Q68: 96.1515 mph
A69: 2020 | B69: Supercheap Auto Bathurst 1000 | D69: Shane van Gisbergen | E69: NZL | F69: Garth Tander | G69: AUS | J69: Holden ZB Commodore | K69: 161 | M69: 6h 10m 56.1143s | O69: 161.8006 km/h | Q69: 100.5385 mph
A70: 2021 | B70: Repco Bathurst 1000 | D70: Chaz Mostert | E70: AUS | F70: Lee Holdsworth | G70: AUS | J70: Holden ZB Commodore | K70: 161 | M70: 6h 15m 06.1952s | O70: 160.0028 km/h | Q70: 99.4211 mph
A71: 2022 | B71: Repco Bathurst 1000 | D71: Shane van Gisbergen | E71: NZL | F71: Garth Tander | G71: AUS | J71: Holden ZB Commodore | K71: 161 | M71: 6h 41m 53.7220s | O71: 149.3363 km/h | Q71: 92.7933 mph
A72: 2023 | B72: Repco Bathurst 1000 | D72: Shane van Gisbergen | E72: NZL | F72: Richie Stanaway | G72: NZL | J72: Chevrolet Camaro ZL1-1LE | K72: 161 | M72: 6h 7m 07.4957s | O72: 163.4800 km/h | Q72: 101.5818 mph
A73: 2024 | B73: Repco Bathurst 1000 | D73: Brodie Kostecki | E73: AUS | F73: Todd Hazelwood | G73: AUS | J73: Chevrolet Camaro ZL1-1LE | K73: 161 | M73: 5h 58m 3.0649s | N73: 9 | O73: 167.6230 km/h | Q73: 104.1561 mph
A74: 2025 | B74: Repco Bathurst 1000 | D74: Matthew Payne | E74: NZL | F74: Garth Tander | G74: AUS | J74: Ford Mustang S650 | K74: 161 | M74: 6h 52m 14.9378s | O74: 145.5858 km/h | Q74: 90.4628 mph
A76: ^1 – Outright race winner was not officially recognised until 1965. Prior to that official results reflected four or five class races occurring simultaneously rather than a single race. The first car across the finish line has been retrospectively referred to as outright race winner since then.
A77: ^2 – Race was stopped before full race distance.
A78: ^3 – The first and second position finishers were disqualified post race.
A79: ^4 – The first position finisher was disqualified post race.
A80: ^5 – Denotes Australia 1000 races for V8 Supercars category.
A81: ^6 – Race was stopped for over an hour due to the track surface breaking up and requiring repair. Stoppage time is included in final race time.
A82: ^7 – The first position finisher was assessed a post-race time penalty for violating driving standards.
A83: ^8 – This is the first year with the newly added Chase in Conrod Straight.
A84: ^9 – Race record for time elapsed & average speed.

Sheet Years Racing The Great Race
B1: 60 | C1: 61 | D1: 62 | E1: 63 | F1: 64 | G1: 65 | H1: 66 | I1: 67 | J1: 68 | K1: 69 | L1: 70 | M1: 71 | N1: 72 | O1: 73 | P1: 74 | Q1: 75 | R1: 76 | S1: 77 | T1: 78 | U1: 79 | V1: 80 | W1: 81 | X1: 82 | Y1: 83 | Z1: 84 | AA1: 85 | AB1: 86 | AC1: 87 | AD1: 88 | AE1: 89 | AF1: 90 | AG1: 91 | AH1: 92 | AI1: 93 | AJ1: 94 | AK1: 95 | AL1: 96 | AM1: 97 | AN1: 97 ST | AO1: 98 | AP1: 98 ST | AQ1: 99 | AR1: 99 ST | AS1: 00 | AT1: 01 | AU1: 02 | AV1: 03 | AW1: 04 | AX1: 05 | AY1: 06 | AZ1: 07 | BA1: 08 | BB1: 09 | BC1: 10 | BD1: 11 | BE1: 12 | BF1: 13 | BG1: 14 | BH1: 15 | BI1: 16 | BJ1: 17 | BK1: 18 | BL1: 19 | BM1: 20 | BN1: 21 | BO1: 22 | BP1: 23 | BQ1: 24 | BR1: 25 | BS1: 26 | BT1: Total | BV1: Surname | BW1: First
A2: Rauno Aaltonen | H2: 1 | AG2: 1 | BT2: =COUNTIF(B2:BS2,1) | BV2: =TRIM(RIGHT(A2, LEN(A2) - FIND("@", SUBSTITUTE(A2, " ", "@", LEN(A2)-LEN(SUBSTITUTE(A2," ","")))))) | BW2: =TRIM(LEFT(A2,FIND(" ",A2&" ")-1)) | BX2: =+IF(BV2=BV1,"Same","Diff") | BY2: =IF(BX2="Same",IF(BW2=BW1,"same","Diff"))
A3: Ern Abbott | B3: 1 | E3: 1 | G3: 1 | H3: 1 | BT3: =COUNTIF(B3:BS3,1) | BV3: =TRIM(RIGHT(A3, LEN(A3) - FIND("@", SUBSTITUTE(A3, " ", "@", LEN(A3)-LEN(SUBSTITUTE(A3," ","")))))) | BW3: =TRIM(LEFT(A3,FIND(" ",A3&" ")-1)) | BX3: =+IF(BV3=BV2,"Same","Diff") | BY3: =IF(BX3="Same",IF(BW3=BW2,"same","Diff"))
A4: Arthur Abrahams | AG4: 1 | BT4: =COUNTIF(B4:BS4,1) | BV4: =TRIM(RIGHT(A4, LEN(A4) - FIND("@", SUBSTITUTE(A4, " ", "@", LEN(A4)-LEN(SUBSTITUTE(A4," ","")))))) | BW4: =TRIM(LEFT(A4,FIND(" ",A4&" ")-1)) | BX4: =+IF(BV4=BV3,"Same","Diff") | BY4: =IF(BX4="Same",IF(BW4=BW3,"same","Diff"))
A5: Graeme Adams | P5: 1 | Q5: 1 | BT5: =COUNTIF(B5:BS5,1) | BV5: =TRIM(RIGHT(A5, LEN(A5) - FIND("@", SUBSTITUTE(A5, " ", "@", LEN(A5)-LEN(SUBSTITUTE(A5," ","")))))) | BW5: =TRIM(LEFT(A5,FIND(" ",A5&" ")-1)) | BX5: =+IF(BV5=BV4,"Same","Diff") | BY5: =IF(BX5="Same",IF(BW5=BW4,"same","Diff"))
A6: Lindsay Adcock | I6: 1 | J6: 1 | BT6: =COUNTIF(B6:BS6,1) | BV6: =TRIM(RIGHT(A6, LEN(A6) - FIND("@", SUBSTITUTE(A6, " ", "@", LEN(A6)-LEN(SUBSTITUTE(A6," ","")))))) | BW6: =TRIM(LEFT(A6,FIND(" ",A6&" ")-1)) | BX6: =+IF(BV6=BV5,"Same","Diff") | BY6: =IF(BX6="Same",IF(BW6=BW5,"same","Diff"))
A7: Michael Adcock | AE7: 1 | BT7: =COUNTIF(B7:BS7,1) | BV7: =TRIM(RIGHT(A7, LEN(A7) - FIND("@", SUBSTITUTE(A7, " ", "@", LEN(A7)-LEN(SUBSTITUTE(A7," ","")))))) | BW7: =TRIM(LEFT(A7,FIND(" ",A7&" ")-1)) | BX7: =+IF(BV7=BV6,"Same","Diff") | BY7: =IF(BX7="Same",IF(BW7=BW6,"same","Diff"))
A8: Arnold Ahrenfeld | F8: 1 | G8: 1 | BT8: =COUNTIF(B8:BS8,1) | BV8: =TRIM(RIGHT(A8, LEN(A8) - FIND("@", SUBSTITUTE(A8, " ", "@", LEN(A8)-LEN(SUBSTITUTE(A8," ","")))))) | BW8: =TRIM(LEFT(A8,FIND(" ",A8&" ")-1)) | BX8: =+IF(BV8=BV7,"Same","Diff") | BY8: =IF(BX8="Same",IF(BW8=BW7,"same","Diff"))
A9: John Ainsley | Q9: 1 | R9: 1 | BT9: =COUNTIF(B9:BS9,1) | BV9: =TRIM(RIGHT(A9, LEN(A9) - FIND("@", SUBSTITUTE(A9, " ", "@", LEN(A9)-LEN(SUBSTITUTE(A9," ","")))))) | BW9: =TRIM(LEFT(A9,FIND(" ",A9&" ")-1)) | BX9: =+IF(BV9=BV8,"Same","Diff") | BY9: =IF(BX9="Same",IF(BW9=BW8,"same","Diff"))
A10: John Alexander | E10: 1 | BT10: =COUNTIF(B10:BS10,1) | BV10: =TRIM(RIGHT(A10, LEN(A10) - FIND("@", SUBSTITUTE(A10, " ", "@", LEN(A10)-LEN(SUBSTITUTE(A10," ","")))))) | BW10: =TRIM(LEFT(A10,FIND(" ",A10&" ")-1)) | BX10: =+IF(BV10=BV9,"Same","Diff") | BY10: =IF(BX10="Same",IF(BW10=BW9,"same","Diff"))
A11: Phil Alexander | W11: 1 | X11: 1 | Y11: 1 | Z11: 1 | BT11: =COUNTIF(B11:BS11,1) | BV11: =TRIM(RIGHT(A11, LEN(A11) - FIND("@", SUBSTITUTE(A11, " ", "@", LEN(A11)-LEN(SUBSTITUTE(A11," ","")))))) | BW11: =TRIM(LEFT(A11,FIND(" ",A11&" ")-1)) | BX11: =+IF(BV11=BV10,"Same","Diff") | BY11: =IF(BX11="Same",IF(BW11=BW10,"same","Diff"))
A12: Don Algie | D12: 1 | BT12: =COUNTIF(B12:BS12,1) | BV12: =TRIM(RIGHT(A12, LEN(A12) - FIND("@", SUBSTITUTE(A12, " ", "@", LEN(A12)-LEN(SUBSTITUTE(A12," ","")))))) | BW12: =TRIM(LEFT(A12,FIND(" ",A12&" ")-1)) | BX12: =+IF(BV12=BV11,"Same","Diff") | BY12: =IF(BX12="Same",IF(BW12=BW11,"same","Diff"))
A13: Jeff Allam | Z13: 1 | AA13: 1 | AD13: 1 | AE13: 1 | AF13: 1 | AI13: 1 | AJ13: 1 | BT13: =COUNTIF(B13:BS13,1) | BV13: =TRIM(RIGHT(A13, LEN(A13) - FIND("@", SUBSTITUTE(A13, " ", "@", LEN(A13)-LEN(SUBSTITUTE(A13," ","")))))) | BW13: =TRIM(LEFT(A13,FIND(" ",A13&" ")-1)) | BX13: =+IF(BV13=BV12,"Same","Diff") | BY13: =IF(BX13="Same",IF(BW13=BW12,"same","Diff"))
A14: Barry Allen | Q14: 1 | BT14: =COUNTIF(B14:BS14,1) | BV14: =TRIM(RIGHT(A14, LEN(A14) - FIND("@", SUBSTITUTE(A14, " ", "@", LEN(A14)-LEN(SUBSTITUTE(A14," ","")))))) | BW14: =TRIM(LEFT(A14,FIND(" ",A14&" ")-1)) | BX14: =+IF(BV14=BV13,"Same","Diff") | BY14: =IF(BX14="Same",IF(BW14=BW13,"same","Diff"))
A15: Kai Allen | BP15: 1 | BQ15: 1 | BR15: 1 | BS15: 1 | BT15: =COUNTIF(B15:BS15,1) | BV15: =TRIM(RIGHT(A15, LEN(A15) - FIND("@", SUBSTITUTE(A15, " ", "@", LEN(A15)-LEN(SUBSTITUTE(A15," ","")))))) | BW15: =TRIM(LEFT(A15,FIND(" ",A15&" ")-1)) | BX15: =+IF(BV15=BV14,"Same","Diff") | BY15: =IF(BX15="Same",IF(BW15=BW14,"same","Diff"))
A16: Terry Allen | D16: 1 | BT16: =COUNTIF(B16:BS16,1) | BV16: =TRIM(RIGHT(A16, LEN(A16) - FIND("@", SUBSTITUTE(A16, " ", "@", LEN(A16)-LEN(SUBSTITUTE(A16," ","")))))) | BW16: =TRIM(LEFT(A16,FIND(" ",A16&" ")-1)) | BX16: =+IF(BV16=BV15,"Same","Diff") | BY16: =IF(BX16="Same",IF(BW16=BW15,"same","Diff"))
A17: Tony Allen | E17: 1 | F17: 1 | N17: 1 | O17: 1 | P17: 1 | BT17: =COUNTIF(B17:BS17,1) | BV17: =TRIM(RIGHT(A17, LEN(A17) - FIND("@", SUBSTITUTE(A17, " ", "@", LEN(A17)-LEN(SUBSTITUTE(A17," ","")))))) | BW17: =TRIM(LEFT(A17,FIND(" ",A17&" ")-1)) | BX17: =+IF(BV17=BV16,"Same","Diff") | BY17: =IF(BX17="Same",IF(BW17=BW16,"same","Diff"))
A18: Marcos Ambrose | AT18: 1 | AU18: 1 | AV18: 1 | AW18: 1 | AX18: 1 | BH18: 1 | BT18: =COUNTIF(B18:BS18,1) | BV18: =TRIM(RIGHT(A18, LEN(A18) - FIND("@", SUBSTITUTE(A18, " ", "@", LEN(A18)-LEN(SUBSTITUTE(A18," ","")))))) | BW18: =TRIM(LEFT(A18,FIND(" ",A18&" ")-1)) | BX18: =+IF(BV18=BV17,"Same","Diff") | BY18: =IF(BX18="Same",IF(BW18=BW17,"same","Diff"))
A19: John Amp | B19: 1 | BT19: =COUNTIF(B19:BS19,1) | BV19: =TRIM(RIGHT(A19, LEN(A19) - FIND("@", SUBSTITUTE(A19, " ", "@", LEN(A19)-LEN(SUBSTITUTE(A19," ","")))))) | BW19: =TRIM(LEFT(A19,FIND(" ",A19&" ")-1)) | BX19: =+IF(BV19=BV18,"Same","Diff") | BY19: =IF(BX19="Same",IF(BW19=BW18,"same","Diff"))
A20: Bruce Anderson | AA20: 1 | AB20: 1 | BT20: =COUNTIF(B20:BS20,1) | BV20: =TRIM(RIGHT(A20, LEN(A20) - FIND("@", SUBSTITUTE(A20, " ", "@", LEN(A20)-LEN(SUBSTITUTE(A20," ","")))))) | BW20: =TRIM(LEFT(A20,FIND(" ",A20&" ")-1)) | BX20: =+IF(BV20=BV19,"Same","Diff") | BY20: =IF(BX20="Same",IF(BW20=BW19,"same","Diff"))
A21: David Anderson | B21: 1 | D21: 1 | BT21: =COUNTIF(B21:BS21,1) | BV21: =TRIM(RIGHT(A21, LEN(A21) - FIND("@", SUBSTITUTE(A21, " ", "@", LEN(A21)-LEN(SUBSTITUTE(A21," ","")))))) | BW21: =TRIM(LEFT(A21,FIND(" ",A21&" ")-1)) | BX21: =+IF(BV21=BV20,"Same","Diff") | BY21: =IF(BX21="Same",IF(BW21=BW20,"same","Diff"))
A22: Jack Anderson | D22: 1 | BT22: =COUNTIF(B22:BS22,1) | BV22: =TRIM(RIGHT(A22, LEN(A22) - FIND("@", SUBSTITUTE(A22, " ", "@", LEN(A22)-LEN(SUBSTITUTE(A22," ","")))))) | BW22: =TRIM(LEFT(A22,FIND(" ",A22&" ")-1)) | BX22: =+IF(BV22=BV21,"Same","Diff") | BY22: =IF(BX22="Same",IF(BW22=BW21,"same","Diff"))
A23: Wayne Anderson | AA23: 1 | AB23: 1 | BT23: =COUNTIF(B23:BS23,1) | BV23: =TRIM(RIGHT(A23, LEN(A23) - FIND("@", SUBSTITUTE(A23, " ", "@", LEN(A23)-LEN(SUBSTITUTE(A23," ","")))))) | BW23: =TRIM(LEFT(A23,FIND(" ",A23&" ")-1)) | BX23: =+IF(BV23=BV22,"Same","Diff") | BY23: =IF(BX23="Same",IF(BW23=BW22,"same","Diff"))
A24: John Andretti | AD24: 1 | BT24: =COUNTIF(B24:BS24,1) | BV24: =TRIM(RIGHT(A24, LEN(A24) - FIND("@", SUBSTITUTE(A24, " ", "@", LEN(A24)-LEN(SUBSTITUTE(A24," ","")))))) | BW24: =TRIM(LEFT(A24,FIND(" ",A24&" ")-1)) | BX24: =+IF(BV24=BV23,"Same","Diff") | BY24: =IF(BX24="Same",IF(BW24=BW23,"same","Diff"))
A25: Arthur Andrews | E25: 1 | BT25: =COUNTIF(B25:BS25,1) | BV25: =TRIM(RIGHT(A25, LEN(A25) - FIND("@", SUBSTITUTE(A25, " ", "@", LEN(A25)-LEN(SUBSTITUTE(A25," ","")))))) | BW25: =TRIM(LEFT(A25,FIND(" ",A25&" ")-1)) | BX25: =+IF(BV25=BV24,"Same","Diff") | BY25: =IF(BX25="Same",IF(BW25=BW24,"same","Diff"))
A26: Doug Angus | R26: 1 | BT26: =COUNTIF(B26:BS26,1) | BV26: =TRIM(RIGHT(A26, LEN(A26) - FIND("@", SUBSTITUTE(A26, " ", "@", LEN(A26)-LEN(SUBSTITUTE(A26," ","")))))) | BW26: =TRIM(LEFT(A26,FIND(" ",A26&" ")-1)) | BX26: =+IF(BV26=BV25,"Same","Diff") | BY26: =IF(BX26="Same",IF(BW26=BW25,"same","Diff"))
A27: Barry Arentz | G27: 1 | H27: 1 | J27: 1 | K27: 1 | M27: 1 | BT27: =COUNTIF(B27:BS27,1) | BV27: =TRIM(RIGHT(A27, LEN(A27) - FIND("@", SUBSTITUTE(A27, " ", "@", LEN(A27)-LEN(SUBSTITUTE(A27," ","")))))) | BW27: =TRIM(LEFT(A27,FIND(" ",A27&" ")-1)) | BX27: =+IF(BV27=BV26,"Same","Diff") | BY27: =IF(BX27="Same",IF(BW27=BW26,"same","Diff"))
A28: Greville Arnel | R28: 1 | T28: 1 | Z28: 1 | AA28: 1 | BT28: =COUNTIF(B28:BS28,1) | BV28: =TRIM(RIGHT(A28, LEN(A28) - FIND("@", SUBSTITUTE(A28, " ", "@", LEN(A28)-LEN(SUBSTITUTE(A28," ","")))))) | BW28: =TRIM(LEFT(A28,FIND(" ",A28&" ")-1)) | BX28: =+IF(BV28=BV27,"Same","Diff") | BY28: =IF(BX28="Same",IF(BW28=BW27,"same","Diff"))
A29: Lyndon Arnel | N29: 1 | O29: 1 | P29: 1 | Q29: 1 | R29: 1 | S29: 1 | T29: 1 | Z29: 1 | BT29: =COUNTIF(B29:BS29,1) | BV29: =TRIM(RIGHT(A29, LEN(A29) - FIND("@", SUBSTITUTE(A29, " ", "@", LEN(A29)-LEN(SUBSTITUTE(A29," ","")))))) | BW29: =TRIM(LEFT(A29,FIND(" ",A29&" ")-1)) | BX29: =+IF(BV29=BV28,"Same","Diff") | BY29: =IF(BX29="Same",IF(BW29=BW28,"same","Diff"))
A30: Phillip Arnull | O30: 1 | S30: 1 | T30: 1 | BT30: =COUNTIF(B30:BS30,1) | BV30: =TRIM(RIGHT(A30, LEN(A30) - FIND("@", SUBSTITUTE(A30, " ", "@", LEN(A30)-LEN(SUBSTITUTE(A30," ","")))))) | BW30: =TRIM(LEFT(A30,FIND(" ",A30&" ")-1)) | BX30: =+IF(BV30=BV29,"Same","Diff") | BY30: =IF(BX30="Same",IF(BW30=BW29,"same","Diff"))
A31: Trevor Ashby | AB31: 1 | AC31: 1 | AD31: 1 | AE31: 1 | AF31: 1 | AG31: 1 | AH31: 1 | AI31: 1 | AJ31: 1 | AK31: 1 | AL31: 1 | AM31: 1 | AO31: 1 | AQ31: 1 | AS31: 1 | AT31: 1 | BT31: =COUNTIF(B31:BS31,1) | BV31: =TRIM(RIGHT(A31, LEN(A31) - FIND("@", SUBSTITUTE(A31, " ", "@", LEN(A31)-LEN(SUBSTITUTE(A31," ","")))))) | BW31: =TRIM(LEFT(A31,FIND(" ",A31&" ")-1)) | BX31: =+IF(BV31=BV30,"Same","Diff") | BY31: =IF(BX31="Same",IF(BW31=BW30,"same","Diff"))
A32: Damian Assaillit | BB32: 1 | BC32: 1 | BT32: =COUNTIF(B32:BS32,1) | BV32: =TRIM(RIGHT(A32, LEN(A32) - FIND("@", SUBSTITUTE(A32, " ", "@", LEN(A32)-LEN(SUBSTITUTE(A32," ","")))))) | BW32: =TRIM(LEFT(A32,FIND(" ",A32&" ")-1)) | BX32: =+IF(BV32=BV31,"Same","Diff") | BY32: =IF(BX32="Same",IF(BW32=BW31,"same","Diff"))
A33: Bill Attard | AL33: 1 | AM33: 1 | AO33: 1 | AQ33: 1 | AS33: 1 | BT33: =COUNTIF(B33:BS33,1) | BV33: =TRIM(RIGHT(A33, LEN(A33) - FIND("@", SUBSTITUTE(A33, " ", "@", LEN(A33)-LEN(SUBSTITUTE(A33," ","")))))) | BW33: =TRIM(LEFT(A33,FIND(" ",A33&" ")-1)) | BX33: =+IF(BV33=BV32,"Same","Diff") | BY33: =IF(BX33="Same",IF(BW33=BW32,"same","Diff"))
A34: David Attard | AK34: 1 | AL34: 1 | BT34: =COUNTIF(B34:BS34,1) | BV34: =TRIM(RIGHT(A34, LEN(A34) - FIND("@", SUBSTITUTE(A34, " ", "@", LEN(A34)-LEN(SUBSTITUTE(A34," ","")))))) | BW34: =TRIM(LEFT(A34,FIND(" ",A34&" ")-1)) | BX34: =+IF(BV34=BV33,"Same","Diff") | BY34: =IF(BX34="Same",IF(BW34=BW33,"same","Diff"))
A35: Chick Audsley | O35: 1 | P35: 1 | BT35: =COUNTIF(B35:BS35,1) | BV35: =TRIM(RIGHT(A35, LEN(A35) - FIND("@", SUBSTITUTE(A35, " ", "@", LEN(A35)-LEN(SUBSTITUTE(A35," ","")))))) | BW35: =TRIM(LEFT(A35,FIND(" ",A35&" ")-1)) | BX35: =+IF(BV35=BV34,"Same","Diff") | BY35: =IF(BX35="Same",IF(BW35=BW34,"same","Diff"))
A36: Kym Aunger | L36: 1 | BT36: =COUNTIF(B36:BS36,1) | BV36: =TRIM(RIGHT(A36, LEN(A36) - FIND("@", SUBSTITUTE(A36, " ", "@", LEN(A36)-LEN(SUBSTITUTE(A36," ","")))))) | BW36: =TRIM(LEFT(A36,FIND(" ",A36&" ")-1)) | BX36: =+IF(BV36=BV35,"Same","Diff") | BY36: =IF(BX36="Same",IF(BW36=BW35,"same","Diff"))
A37: Reda Awadallah | AE37: 1 | BT37: =COUNTIF(B37:BS37,1) | BV37: =TRIM(RIGHT(A37, LEN(A37) - FIND("@", SUBSTITUTE(A37, " ", "@", LEN(A37)-LEN(SUBSTITUTE(A37," ","")))))) | BW37: =TRIM(LEFT(A37,FIND(" ",A37&" ")-1)) | BX37: =+IF(BV37=BV36,"Same","Diff") | BY37: =IF(BX37="Same",IF(BW37=BW36,"same","Diff"))
A38: Reda Awadullah | AG38: 1 | BT38: =COUNTIF(B38:BS38,1) | BV38: =TRIM(RIGHT(A38, LEN(A38) - FIND("@", SUBSTITUTE(A38, " ", "@", LEN(A38)-LEN(SUBSTITUTE(A38," ","")))))) | BW38: =TRIM(LEFT(A38,FIND(" ",A38&" ")-1)) | BX38: =+IF(BV38=BV37,"Same","Diff") | BY38: =IF(BX38="Same",IF(BW38=BW37,"same","Diff"))
A39: Lionel Ayers | F39: 1 | H39: 1 | J39: 1 | BT39: =COUNTIF(B39:BS39,1) | BV39: =TRIM(RIGHT(A39, LEN(A39) - FIND("@", SUBSTITUTE(A39, " ", "@", LEN(A39)-LEN(SUBSTITUTE(A39," ","")))))) | BW39: =TRIM(LEFT(A39,FIND(" ",A39&" ")-1)) | BX39: =+IF(BV39=BV38,"Same","Diff") | BY39: =IF(BX39="Same",IF(BW39=BW38,"same","Diff"))
A40: George Ayoub | AJ40: 1 | BT40: =COUNTIF(B40:BS40,1) | BV40: =TRIM(RIGHT(A40, LEN(A40) - FIND("@", SUBSTITUTE(A40, " ", "@", LEN(A40)-LEN(SUBSTITUTE(A40," ","")))))) | BW40: =TRIM(LEFT(A40,FIND(" ",A40&" ")-1)) | BX40: =+IF(BV40=BV39,"Same","Diff") | BY40: =IF(BX40="Same",IF(BW40=BW39,"same","Diff"))
A41: Andrew Bagnall | AB41: 1 | AC41: 1 | AD41: 1 | AE41: 1 | AF41: 1 | BT41: =COUNTIF(B41:BS41,1) | BV41: =TRIM(RIGHT(A41, LEN(A41) - FIND("@", SUBSTITUTE(A41, " ", "@", LEN(A41)-LEN(SUBSTITUTE(A41," ","")))))) | BW41: =TRIM(LEFT(A41,FIND(" ",A41&" ")-1)) | BX41: =+IF(BV41=BV40,"Same","Diff") | BY41: =IF(BX41="Same",IF(BW41=BW40,"same","Diff"))
A42: Kent Baigent | AA42: 1 | AB42: 1 | AC42: 1 | BT42: =COUNTIF(B42:BS42,1) | BV42: =TRIM(RIGHT(A42, LEN(A42) - FIND("@", SUBSTITUTE(A42, " ", "@", LEN(A42)-LEN(SUBSTITUTE(A42," ","")))))) | BW42: =TRIM(LEFT(A42,FIND(" ",A42&" ")-1)) | BX42: =+IF(BV42=BV41,"Same","Diff") | BY42: =IF(BX42="Same",IF(BW42=BW41,"same","Diff"))
A43: Graeme Bailey | U43: 1 | V43: 1 | W43: 1 | X43: 1 | Y43: 1 | Z43: 1 | AA43: 1 | AB43: 1 | BT43: =COUNTIF(B43:BS43,1) | BV43: =TRIM(RIGHT(A43, LEN(A43) - FIND("@", SUBSTITUTE(A43, " ", "@", LEN(A43)-LEN(SUBSTITUTE(A43," ","")))))) | BW43: =TRIM(LEFT(A43,FIND(" ",A43&" ")-1)) | BX43: =+IF(BV43=BV42,"Same","Diff") | BY43: =IF(BX43="Same",IF(BW43=BW42,"same","Diff"))
A44: Lex Bailey | F44: 1 | BT44: =COUNTIF(B44:BS44,1) | BV44: =TRIM(RIGHT(A44, LEN(A44) - FIND("@", SUBSTITUTE(A44, " ", "@", LEN(A44)-LEN(SUBSTITUTE(A44," ","")))))) | BW44: =TRIM(LEFT(A44,FIND(" ",A44&" ")-1)) | BX44: =+IF(BV44=BV43,"Same","Diff") | BY44: =IF(BX44="Same",IF(BW44=BW43,"same","Diff"))
A45: Malcolm Bailey | H45: 1 | BT45: =COUNTIF(B45:BS45,1) | BV45: =TRIM(RIGHT(A45, LEN(A45) - FIND("@", SUBSTITUTE(A45, " ", "@", LEN(A45)-LEN(SUBSTITUTE(A45," ","")))))) | BW45: =TRIM(LEFT(A45,FIND(" ",A45&" ")-1)) | BX45: =+IF(BV45=BV44,"Same","Diff") | BY45: =IF(BX45="Same",IF(BW45=BW44,"same","Diff"))
A46: Murray Bailey | I46: 1 | BT46: =COUNTIF(B46:BS46,1) | BV46: =TRIM(RIGHT(A46, LEN(A46) - FIND("@", SUBSTITUTE(A46, " ", "@", LEN(A46)-LEN(SUBSTITUTE(A46," ","")))))) | BW46: =TRIM(LEFT(A46,FIND(" ",A46&" ")-1)) | BX46: =+IF(BV46=BV45,"Same","Diff") | BY46: =IF(BX46="Same",IF(BW46=BW45,"same","Diff"))
A47: Richard Bailey | R47: 1 | BT47: =COUNTIF(B47:BS47,1) | BV47: =TRIM(RIGHT(A47, LEN(A47) - FIND("@", SUBSTITUTE(A47, " ", "@", LEN(A47)-LEN(SUBSTITUTE(A47," ","")))))) | BW47: =TRIM(LEFT(A47,FIND(" ",A47&" ")-1)) | BX47: =+IF(BV47=BV46,"Same","Diff") | BY47: =IF(BX47="Same",IF(BW47=BW46,"same","Diff"))
A48: Kerry Baily | Y48: 1 | AB48: 1 | AC48: 1 | AD48: 1 | AL48: 1 | BT48: =COUNTIF(B48:BS48,1) | BV48: =TRIM(RIGHT(A48, LEN(A48) - FIND("@", SUBSTITUTE(A48, " ", "@", LEN(A48)-LEN(SUBSTITUTE(A48," ","")))))) | BW48: =TRIM(LEFT(A48,FIND(" ",A48&" ")-1)) | BX48: =+IF(BV48=BV47,"Same","Diff") | BY48: =IF(BX48="Same",IF(BW48=BW47,"same","Diff"))
A49: Craig Baird | AF49: 1 | AJ49: 1 | AM49: 1 | AQ49: 1 | AS49: 1 | AT49: 1 | AU49: 1 | AV49: 1 | AW49: 1 | AX49: 1 | AY49: 1 | AZ49: 1 | BA49: 1 | BB49: 1 | BC49: 1 | BD49: 1 | BE49: 1 | BF49: 1 | BG49: 1 | BI49: 1 | BT49: =COUNTIF(B49:BS49,1) | BV49: =TRIM(RIGHT(A49, LEN(A49) - FIND("@", SUBSTITUTE(A49, " ", "@", LEN(A49)-LEN(SUBSTITUTE(A49," ","")))))) | BW49: =TRIM(LEFT(A49,FIND(" ",A49&" ")-1)) | BX49: =+IF(BV49=BV48,"Same","Diff") | BY49: =IF(BX49="Same",IF(BW49=BW48,"same","Diff"))
A50: Earl Bamber | BK50: 1 | BT50: =COUNTIF(B50:BS50,1) | BV50: =TRIM(RIGHT(A50, LEN(A50) - FIND("@", SUBSTITUTE(A50, " ", "@", LEN(A50)-LEN(SUBSTITUTE(A50," ","")))))) | BW50: =TRIM(LEFT(A50,FIND(" ",A50&" ")-1)) | BX50: =+IF(BV50=BV49,"Same","Diff") | BY50: =IF(BX50="Same",IF(BW50=BW49,"same","Diff"))
A51: Dick Barbour | U51: 1 | V51: 1 | BT51: =COUNTIF(B51:BS51,1) | BV51: =TRIM(RIGHT(A51, LEN(A51) - FIND("@", SUBSTITUTE(A51, " ", "@", LEN(A51)-LEN(SUBSTITUTE(A51," ","")))))) | BW51: =TRIM(LEFT(A51,FIND(" ",A51&" ")-1)) | BX51: =+IF(BV51=BV50,"Same","Diff") | BY51: =IF(BX51="Same",IF(BW51=BW50,"same","Diff"))
A52: Jason Bargwanna | AF52: 1 | AH52: 1 | AM52: 1 | AO52: 1 | AQ52: 1 | AS52: 1 | AT52: 1 | AU52: 1 | AV52: 1 | AW52: 1 | AX52: 1 | AY52: 1 | AZ52: 1 | BA52: 1 | BB52: 1 | BC52: 1 | BD52: 1 | BT52: =COUNTIF(B52:BS52,1) | BV52: =TRIM(RIGHT(A52, LEN(A52) - FIND("@", SUBSTITUTE(A52, " ", "@", LEN(A52)-LEN(SUBSTITUTE(A52," ","")))))) | BW52: =TRIM(LEFT(A52,FIND(" ",A52&" ")-1)) | BX52: =+IF(BV52=BV51,"Same","Diff") | BY52: =IF(BX52="Same",IF(BW52=BW51,"same","Diff"))
A53: Scott Bargwanna | AH53: 1 | BT53: =COUNTIF(B53:BS53,1) | BV53: =TRIM(RIGHT(A53, LEN(A53) - FIND("@", SUBSTITUTE(A53, " ", "@", LEN(A53)-LEN(SUBSTITUTE(A53," ","")))))) | BW53: =TRIM(LEFT(A53,FIND(" ",A53&" ")-1)) | BX53: =+IF(BV53=BV52,"Same","Diff") | BY53: =IF(BX53="Same",IF(BW53=BW52,"same","Diff"))
A54: Ron Barnacle | W54: 1 | AK54: 1 | AL54: 1 | AM54: 1 | AQ54: 1 | BT54: =COUNTIF(B54:BS54,1) | BV54: =TRIM(RIGHT(A54, LEN(A54) - FIND("@", SUBSTITUTE(A54, " ", "@", LEN(A54)-LEN(SUBSTITUTE(A54," ","")))))) | BW54: =TRIM(LEFT(A54,FIND(" ",A54&" ")-1)) | BX54: =+IF(BV54=BV53,"Same","Diff") | BY54: =IF(BX54="Same",IF(BW54=BW53,"same","Diff"))
A55: Jeff Barnes | T55: 1 | AJ55: 1 | BT55: =COUNTIF(B55:BS55,1) | BV55: =TRIM(RIGHT(A55, LEN(A55) - FIND("@", SUBSTITUTE(A55, " ", "@", LEN(A55)-LEN(SUBSTITUTE(A55," ","")))))) | BW55: =TRIM(LEFT(A55,FIND(" ",A55&" ")-1)) | BX55: =+IF(BV55=BV54,"Same","Diff") | BY55: =IF(BX55="Same",IF(BW55=BW54,"same","Diff"))
A56: Phil Barnes | F56: 1 | G56: 1 | M56: 1 | BT56: =COUNTIF(B56:BS56,1) | BV56: =TRIM(RIGHT(A56, LEN(A56) - FIND("@", SUBSTITUTE(A56, " ", "@", LEN(A56)-LEN(SUBSTITUTE(A56," ","")))))) | BW56: =TRIM(LEFT(A56,FIND(" ",A56&" ")-1)) | BX56: =+IF(BV56=BV55,"Same","Diff") | BY56: =IF(BX56="Same",IF(BW56=BW55,"same","Diff"))
A57: Bill Barnett | F57: 1 | G57: 1 | BT57: =COUNTIF(B57:BS57,1) | BV57: =TRIM(RIGHT(A57, LEN(A57) - FIND("@", SUBSTITUTE(A57, " ", "@", LEN(A57)-LEN(SUBSTITUTE(A57," ","")))))) | BW57: =TRIM(LEFT(A57,FIND(" ",A57&" ")-1)) | BX57: =+IF(BV57=BV56,"Same","Diff") | BY57: =IF(BX57="Same",IF(BW57=BW56,"same","Diff"))
A58: Chris Barns | AH58: 1 | BT58: =COUNTIF(B58:BS58,1) | BV58: =TRIM(RIGHT(A58, LEN(A58) - FIND("@", SUBSTITUTE(A58, " ", "@", LEN(A58)-LEN(SUBSTITUTE(A58," ","")))))) | BW58: =TRIM(LEFT(A58,FIND(" ",A58&" ")-1)) | BX58: =+IF(BV58=BV57,"Same","Diff") | BY58: =IF(BX58="Same",IF(BW58=BW57,"same","Diff"))
A59: Alf Barrett | K59: 1 | BT59: =COUNTIF(B59:BS59,1) | BV59: =TRIM(RIGHT(A59, LEN(A59) - FIND("@", SUBSTITUTE(A59, " ", "@", LEN(A59)-LEN(SUBSTITUTE(A59," ","")))))) | BW59: =TRIM(LEFT(A59,FIND(" ",A59&" ")-1)) | BX59: =+IF(BV59=BV58,"Same","Diff") | BY59: =IF(BX59="Same",IF(BW59=BW58,"same","Diff"))
A60: Dave Barrow | AD60: 1 | AF60: 1 | AG60: 1 | BT60: =COUNTIF(B60:BS60,1) | BV60: =TRIM(RIGHT(A60, LEN(A60) - FIND("@", SUBSTITUTE(A60, " ", "@", LEN(A60)-LEN(SUBSTITUTE(A60," ","")))))) | BW60: =TRIM(LEFT(A60,FIND(" ",A60&" ")-1)) | BX60: =+IF(BV60=BV59,"Same","Diff") | BY60: =IF(BX60="Same",IF(BW60=BW59,"same","Diff"))
A61: Kevin Bartlett | E61: 1 | G61: 1 | H61: 1 | I61: 1 | J61: 1 | K61: 1 | M61: 1 | O61: 1 | P61: 1 | Q61: 1 | R61: 1 | S61: 1 | T61: 1 | V61: 1 | W61: 1 | X61: 1 | Y61: 1 | Z61: 1 | AA61: 1 | AB61: 1 | AC61: 1 | AD61: 1 | AE61: 1 | AF61: 1 | BT61: =COUNTIF(B61:BS61,1) | BV61: =TRIM(RIGHT(A61, LEN(A61) - FIND("@", SUBSTITUTE(A61, " ", "@", LEN(A61)-LEN(SUBSTITUTE(A61," ","")))))) | BW61: =TRIM(LEFT(A61,FIND(" ",A61&" ")-1)) | BX61: =+IF(BV61=BV60,"Same","Diff") | BY61: =IF(BX61="Same",IF(BW61=BW60,"same","Diff"))
A62: Tony Basile | J62: 1 | BT62: =COUNTIF(B62:BS62,1) | BV62: =TRIM(RIGHT(A62, LEN(A62) - FIND("@", SUBSTITUTE(A62, " ", "@", LEN(A62)-LEN(SUBSTITUTE(A62," ","")))))) | BW62: =TRIM(LEFT(A62,FIND(" ",A62&" ")-1)) | BX62: =+IF(BV62=BV61,"Same","Diff") | BY62: =IF(BX62="Same",IF(BW62=BW61,"same","Diff"))
A63: John Bassett | Q63: 1 | BT63: =COUNTIF(B63:BS63,1) | BV63: =TRIM(RIGHT(A63, LEN(A63) - FIND("@", SUBSTITUTE(A63, " ", "@", LEN(A63)-LEN(SUBSTITUTE(A63," ","")))))) | BW63: =TRIM(LEFT(A63,FIND(" ",A63&" ")-1)) | BX63: =+IF(BV63=BV62,"Same","Diff") | BY63: =IF(BX63="Same",IF(BW63=BW62,"same","Diff"))
A64: Barry Bassingthwaite | N64: 1 | BT64: =COUNTIF(B64:BS64,1) | BV64: =TRIM(RIGHT(A64, LEN(A64) - FIND("@", SUBSTITUTE(A64, " ", "@", LEN(A64)-LEN(SUBSTITUTE(A64," ","")))))) | BW64: =TRIM(LEFT(A64,FIND(" ",A64&" ")-1)) | BX64: =+IF(BV64=BV63,"Same","Diff") | BY64: =IF(BX64="Same",IF(BW64=BW63,"same","Diff"))
A65: Bryan Bate | AC65: 1 | AD65: 1 | BT65: =COUNTIF(B65:BS65,1) | BV65: =TRIM(RIGHT(A65, LEN(A65) - FIND("@", SUBSTITUTE(A65, " ", "@", LEN(A65)-LEN(SUBSTITUTE(A65," ","")))))) | BW65: =TRIM(LEFT(A65,FIND(" ",A65&" ")-1)) | BX65: =+IF(BV65=BV64,"Same","Diff") | BY65: =IF(BX65="Same",IF(BW65=BW64,"same","Diff"))
A66: Neal Bates | AE66: 1 | AF66: 1 | AG66: 1 | AH66: 1 | AI66: 1 | AO66: 1 | AQ66: 1 | AS66: 1 | AU66: 1 | AV66: 1 | BT66: =COUNTIF(B66:BS66,1) | BV66: =TRIM(RIGHT(A66, LEN(A66) - FIND("@", SUBSTITUTE(A66, " ", "@", LEN(A66)-LEN(SUBSTITUTE(A66," ","")))))) | BW66: =TRIM(LEFT(A66,FIND(" ",A66&" ")-1)) | BX66: =+IF(BV66=BV65,"Same","Diff") | BY66: =IF(BX66="Same",IF(BW66=BW65,"same","Diff"))
A67: Rick Bates | AF67: 1 | AG67: 1 | AH67: 1 | AS67: 1 | AT67: 1 | AU67: 1 | AV67: 1 | BT67: =COUNTIF(B67:BS67,1) | BV67: =TRIM(RIGHT(A67, LEN(A67) - FIND("@", SUBSTITUTE(A67, " ", "@", LEN(A67)-LEN(SUBSTITUTE(A67," ","")))))) | BW67: =TRIM(LEFT(A67,FIND(" ",A67&" ")-1)) | BX67: =+IF(BV67=BV66,"Same","Diff") | BY67: =IF(BX67="Same",IF(BW67=BW66,"same","Diff"))
A68: Zach Bates | BR68: 1 | BS68: 1 | BT68: =COUNTIF(B68:BS68,1) | BV68: =TRIM(RIGHT(A68, LEN(A68) - FIND("@", SUBSTITUTE(A68, " ", "@", LEN(A68)-LEN(SUBSTITUTE(A68," ","")))))) | BW68: =TRIM(LEFT(A68,FIND(" ",A68&" ")-1)) | BX68: =+IF(BV68=BV67,"Same","Diff") | BY68: =IF(BX68="Same",IF(BW68=BW67,"same","Diff"))
A69: Chris Batger | M69: 1 | N69: 1 | O69: 1 | BT69: =COUNTIF(B69:BS69,1) | BV69: =TRIM(RIGHT(A69, LEN(A69) - FIND("@", SUBSTITUTE(A69, " ", "@", LEN(A69)-LEN(SUBSTITUTE(A69," ","")))))) | BW69: =TRIM(LEFT(A69,FIND(" ",A69&" ")-1)) | BX69: =+IF(BV69=BV68,"Same","Diff") | BY69: =IF(BX69="Same",IF(BW69=BW68,"same","Diff"))
A70: G Baxter | AO70: 1 | BT70: =COUNTIF(B70:BS70,1) | BV70: =TRIM(RIGHT(A70, LEN(A70) - FIND("@", SUBSTITUTE(A70, " ", "@", LEN(A70)-LEN(SUBSTITUTE(A70," ","")))))) | BW70: =TRIM(LEFT(A70,FIND(" ",A70&" ")-1)) | BX70: =+IF(BV70=BV69,"Same","Diff") | BY70: =IF(BX70="Same",IF(BW70=BW69,"same","Diff"))
A71: Gary Baxter | AS71: 1 | BT71: =COUNTIF(B71:BS71,1) | BV71: =TRIM(RIGHT(A71, LEN(A71) - FIND("@", SUBSTITUTE(A71, " ", "@", LEN(A71)-LEN(SUBSTITUTE(A71," ","")))))) | BW71: =TRIM(LEFT(A71,FIND(" ",A71&" ")-1)) | BX71: =+IF(BV71=BV70,"Same","Diff") | BY71: =IF(BX71="Same",IF(BW71=BW70,"same","Diff"))
A72: Leopold von Bayern | Z72: 1 | BT72: =COUNTIF(B72:BS72,1) | BV72: =TRIM(RIGHT(A72, LEN(A72) - FIND("@", SUBSTITUTE(A72, " ", "@", LEN(A72)-LEN(SUBSTITUTE(A72," ","")))))) | BW72: =TRIM(LEFT(A72,FIND(" ",A72&" ")-1)) | BX72: =+IF(BV72=BV71,"Same","Diff") | BY72: =IF(BX72="Same",IF(BW72=BW71,"same","Diff"))
A73: Troy Bayliss | BB73: 1 | BT73: =COUNTIF(B73:BS73,1) | BV73: =TRIM(RIGHT(A73, LEN(A73) - FIND("@", SUBSTITUTE(A73, " ", "@", LEN(A73)-LEN(SUBSTITUTE(A73," ","")))))) | BW73: =TRIM(LEFT(A73,FIND(" ",A73&" ")-1)) | BX73: =+IF(BV73=BV72,"Same","Diff") | BY73: =IF(BX73="Same",IF(BW73=BW72,"same","Diff"))
A74: Bob Beasley | G74: 1 | H74: 1 | I74: 1 | J74: 1 | K74: 1 | L74: 1 | M74: 1 | O74: 1 | P74: 1 | BT74: =COUNTIF(B74:BS74,1) | BV74: =TRIM(RIGHT(A74, LEN(A74) - FIND("@", SUBSTITUTE(A74, " ", "@", LEN(A74)-LEN(SUBSTITUTE(A74," ","")))))) | BW74: =TRIM(LEFT(A74,FIND(" ",A74&" ")-1)) | BX74: =+IF(BV74=BV73,"Same","Diff") | BY74: =IF(BX74="Same",IF(BW74=BW73,"same","Diff"))
A75: Daryl Beattie | AU75: 1 | BT75: =COUNTIF(B75:BS75,1) | BV75: =TRIM(RIGHT(A75, LEN(A75) - FIND("@", SUBSTITUTE(A75, " ", "@", LEN(A75)-LEN(SUBSTITUTE(A75," ","")))))) | BW75: =TRIM(LEFT(A75,FIND(" ",A75&" ")-1)) | BX75: =+IF(BV75=BV74,"Same","Diff") | BY75: =IF(BX75="Same",IF(BW75=BW74,"same","Diff"))
A76: Marie-Claude Beaumont | Q76: 1 | R76: 1 | BT76: =COUNTIF(B76:BS76,1) | BV76: =TRIM(RIGHT(A76, LEN(A76) - FIND("@", SUBSTITUTE(A76, " ", "@", LEN(A76)-LEN(SUBSTITUTE(A76," ","")))))) | BW76: =TRIM(LEFT(A76,FIND(" ",A76&" ")-1)) | BX76: =+IF(BV76=BV75,"Same","Diff") | BY76: =IF(BX76="Same",IF(BW76=BW75,"same","Diff"))
A77: Damon Beck | I77: 1 | J77: 1 | K77: 1 | M77: 1 | N77: 1 | AD77: 1 | BT77: =COUNTIF(B77:BS77,1) | BV77: =TRIM(RIGHT(A77, LEN(A77) - FIND("@", SUBSTITUTE(A77, " ", "@", LEN(A77)-LEN(SUBSTITUTE(A77," ","")))))) | BW77: =TRIM(LEFT(A77,FIND(" ",A77&" ")-1)) | BX77: =+IF(BV77=BV76,"Same","Diff") | BY77: =IF(BX77="Same",IF(BW77=BW76,"same","Diff"))
A78: Peter Beck | AH78: 1 | BT78: =COUNTIF(B78:BS78,1) | BV78: =TRIM(RIGHT(A78, LEN(A78) - FIND("@", SUBSTITUTE(A78, " ", "@", LEN(A78)-LEN(SUBSTITUTE(A78," ","")))))) | BW78: =TRIM(LEFT(A78,FIND(" ",A78&" ")-1)) | BX78: =+IF(BV78=BV77,"Same","Diff") | BY78: =IF(BX78="Same",IF(BW78=BW77,"same","Diff"))
A79: Russell Becker | AF79: 1 | BT79: =COUNTIF(B79:BS79,1) | BV79: =TRIM(RIGHT(A79, LEN(A79) - FIND("@", SUBSTITUTE(A79, " ", "@", LEN(A79)-LEN(SUBSTITUTE(A79," ","")))))) | BW79: =TRIM(LEFT(A79,FIND(" ",A79&" ")-1)) | BX79: =+IF(BV79=BV78,"Same","Diff") | BY79: =IF(BX79="Same",IF(BW79=BW78,"same","Diff"))
A80: Norm Beechey | B80: 1 | C80: 1 | D80: 1 | L80: 1 | M80: 1 | BT80: =COUNTIF(B80:BS80,1) | BV80: =TRIM(RIGHT(A80, LEN(A80) - FIND("@", SUBSTITUTE(A80, " ", "@", LEN(A80)-LEN(SUBSTITUTE(A80," ","")))))) | BW80: =TRIM(LEFT(A80,FIND(" ",A80&" ")-1)) | BX80: =+IF(BV80=BV79,"Same","Diff") | BY80: =IF(BX80="Same",IF(BW80=BW79,"same","Diff"))
A81: Shane Beikoff | AO81: 1 | AS81: 1 | BT81: =COUNTIF(B81:BS81,1) | BV81: =TRIM(RIGHT(A81, LEN(A81) - FIND("@", SUBSTITUTE(A81, " ", "@", LEN(A81)-LEN(SUBSTITUTE(A81," ","")))))) | BW81: =TRIM(LEFT(A81,FIND(" ",A81&" ")-1)) | BX81: =+IF(BV81=BV80,"Same","Diff") | BY81: =IF(BX81="Same",IF(BW81=BW80,"same","Diff"))
A82: Derek Bell | S82: 1 | T82: 1 | U82: 1 | V82: 1 | W82: 1 | BT82: =COUNTIF(B82:BS82,1) | BV82: =TRIM(RIGHT(A82, LEN(A82) - FIND("@", SUBSTITUTE(A82, " ", "@", LEN(A82)-LEN(SUBSTITUTE(A82," ","")))))) | BW82: =TRIM(LEFT(A82,FIND(" ",A82&" ")-1)) | BX82: =+IF(BV82=BV81,"Same","Diff") | BY82: =IF(BX82="Same",IF(BW82=BW81,"same","Diff"))
A83: Stephen Bell | AJ83: 1 | AK83: 1 | AL83: 1 | AM83: 1 | AO83: 1 | BT83: =COUNTIF(B83:BS83,1) | BV83: =TRIM(RIGHT(A83, LEN(A83) - FIND("@", SUBSTITUTE(A83, " ", "@", LEN(A83)-LEN(SUBSTITUTE(A83," ","")))))) | BW83: =TRIM(LEFT(A83,FIND(" ",A83&" ")-1)) | BX83: =+IF(BV83=BV82,"Same","Diff") | BY83: =IF(BX83="Same",IF(BW83=BW82,"same","Diff"))
A84: Domenic Beninca | AO84: 1 | BT84: =COUNTIF(B84:BS84,1) | BV84: =TRIM(RIGHT(A84, LEN(A84) - FIND("@", SUBSTITUTE(A84, " ", "@", LEN(A84)-LEN(SUBSTITUTE(A84," ","")))))) | BW84: =TRIM(LEFT(A84,FIND(" ",A84&" ")-1)) | BX84: =+IF(BV84=BV83,"Same","Diff") | BY84: =IF(BX84="Same",IF(BW84=BW83,"same","Diff"))
A85: Sandra Bennett | K85: 1 | L85: 1 | BT85: =COUNTIF(B85:BS85,1) | BV85: =TRIM(RIGHT(A85, LEN(A85) - FIND("@", SUBSTITUTE(A85, " ", "@", LEN(A85)-LEN(SUBSTITUTE(A85," ","")))))) | BW85: =TRIM(LEFT(A85,FIND(" ",A85&" ")-1)) | BX85: =+IF(BV85=BV84,"Same","Diff") | BY85: =IF(BX85="Same",IF(BW85=BW84,"same","Diff"))
A86: Clive Benson-Brown | W86: 1 | X86: 1 | Y86: 1 | BT86: =COUNTIF(B86:BS86,1) | BV86: =TRIM(RIGHT(A86, LEN(A86) - FIND("@", SUBSTITUTE(A86, " ", "@", LEN(A86)-LEN(SUBSTITUTE(A86," ","")))))) | BW86: =TRIM(LEFT(A86,FIND(" ",A86&" ")-1)) | BX86: =+IF(BV86=BV85,"Same","Diff") | BY86: =IF(BX86="Same",IF(BW86=BW85,"same","Diff"))
A87: Paul Bernasconi | Q87: 1 | BT87: =COUNTIF(B87:BS87,1) | BV87: =TRIM(RIGHT(A87, LEN(A87) - FIND("@", SUBSTITUTE(A87, " ", "@", LEN(A87)-LEN(SUBSTITUTE(A87," ","")))))) | BW87: =TRIM(LEFT(A87,FIND(" ",A87&" ")-1)) | BX87: =+IF(BV87=BV86,"Same","Diff") | BY87: =IF(BX87="Same",IF(BW87=BW86,"same","Diff"))
A88: Paul Berthier | T88: 1 | BT88: =COUNTIF(B88:BS88,1) | BV88: =TRIM(RIGHT(A88, LEN(A88) - FIND("@", SUBSTITUTE(A88, " ", "@", LEN(A88)-LEN(SUBSTITUTE(A88," ","")))))) | BW88: =TRIM(LEFT(A88,FIND(" ",A88&" ")-1)) | BX88: =+IF(BV88=BV87,"Same","Diff") | BY88: =IF(BX88="Same",IF(BW88=BW87,"same","Diff"))
A89: David Besnard | AS89: 1 | AT89: 1 | AU89: 1 | AV89: 1 | AW89: 1 | AX89: 1 | AY89: 1 | AZ89: 1 | BA89: 1 | BB89: 1 | BC89: 1 | BD89: 1 | BE89: 1 | BT89: =COUNTIF(B89:BS89,1) | BV89: =TRIM(RIGHT(A89, LEN(A89) - FIND("@", SUBSTITUTE(A89, " ", "@", LEN(A89)-LEN(SUBSTITUTE(A89," ","")))))) | BW89: =TRIM(LEFT(A89,FIND(" ",A89&" ")-1)) | BX89: =+IF(BV89=BV88,"Same","Diff") | BY89: =IF(BX89="Same",IF(BW89=BW88,"same","Diff"))
A90: Zak Best | BN90: 1 | BO90: 1 | BP90: 1 | BR90: 1 | BS90: 1 | BT90: =COUNTIF(B90:BS90,1) | BV90: =TRIM(RIGHT(A90, LEN(A90) - FIND("@", SUBSTITUTE(A90, " ", "@", LEN(A90)-LEN(SUBSTITUTE(A90," ","")))))) | BW90: =TRIM(LEFT(A90,FIND(" ",A90&" ")-1)) | BX90: =+IF(BV90=BV89,"Same","Diff") | BY90: =IF(BX90="Same",IF(BW90=BW89,"same","Diff"))
A91: Frank Biela | AE91: 1 | AF91: 1 | BT91: =COUNTIF(B91:BS91,1) | BV91: =TRIM(RIGHT(A91, LEN(A91) - FIND("@", SUBSTITUTE(A91, " ", "@", LEN(A91)-LEN(SUBSTITUTE(A91," ","")))))) | BW91: =TRIM(LEFT(A91,FIND(" ",A91&" ")-1)) | BX91: =+IF(BV91=BV90,"Same","Diff") | BY91: =IF(BX91="Same",IF(BW91=BW90,"same","Diff"))
A92: John Billington | AC92: 1 | BT92: =COUNTIF(B92:BS92,1) | BV92: =TRIM(RIGHT(A92, LEN(A92) - FIND("@", SUBSTITUTE(A92, " ", "@", LEN(A92)-LEN(SUBSTITUTE(A92," ","")))))) | BW92: =TRIM(LEFT(A92,FIND(" ",A92&" ")-1)) | BX92: =+IF(BV92=BV91,"Same","Diff") | BY92: =IF(BX92="Same",IF(BW92=BW91,"same","Diff"))
A93: Frank Binding | AH93: 1 | AI93: 1 | BT93: =COUNTIF(B93:BS93,1) | BV93: =TRIM(RIGHT(A93, LEN(A93) - FIND("@", SUBSTITUTE(A93, " ", "@", LEN(A93)-LEN(SUBSTITUTE(A93," ","")))))) | BW93: =TRIM(LEFT(A93,FIND(" ",A93&" ")-1)) | BX93: =+IF(BV93=BV92,"Same","Diff") | BY93: =IF(BX93="Same",IF(BW93=BW92,"same","Diff"))
A94: Graeme Blanchard | P94: 1 | BT94: =COUNTIF(B94:BS94,1) | BV94: =TRIM(RIGHT(A94, LEN(A94) - FIND("@", SUBSTITUTE(A94, " ", "@", LEN(A94)-LEN(SUBSTITUTE(A94," ","")))))) | BW94: =TRIM(LEFT(A94,FIND(" ",A94&" ")-1)) | BX94: =+IF(BV94=BV93,"Same","Diff") | BY94: =IF(BX94="Same",IF(BW94=BW93,"same","Diff"))
A95: John Blanchard | AH95: 1 | AI95: 1 | AJ95: 1 | BT95: =COUNTIF(B95:BS95,1) | BV95: =TRIM(RIGHT(A95, LEN(A95) - FIND("@", SUBSTITUTE(A95, " ", "@", LEN(A95)-LEN(SUBSTITUTE(A95," ","")))))) | BW95: =TRIM(LEFT(A95,FIND(" ",A95&" ")-1)) | BX95: =+IF(BV95=BV94,"Same","Diff") | BY95: =IF(BX95="Same",IF(BW95=BW94,"same","Diff"))
A96: Tim Blanchard | BD96: 1 | BE96: 1 | BF96: 1 | BG96: 1 | BH96: 1 | BI96: 1 | BJ96: 1 | BK96: 1 | BL96: 1 | BM96: 1 | BN96: 1 | BO96: 1 | BP96: 1 | BT96: =COUNTIF(B96:BS96,1) | BV96: =TRIM(RIGHT(A96, LEN(A96) - FIND("@", SUBSTITUTE(A96, " ", "@", LEN(A96)-LEN(SUBSTITUTE(A96," ","")))))) | BW96: =TRIM(LEFT(A96,FIND(" ",A96&" ")-1)) | BX96: =+IF(BV96=BV95,"Same","Diff") | BY96: =IF(BX96="Same",IF(BW96=BW95,"same","Diff"))
A97: Jeroen Bleekemolen | BF97: 1 | BT97: =COUNTIF(B97:BS97,1) | BV97: =TRIM(RIGHT(A97, LEN(A97) - FIND("@", SUBSTITUTE(A97, " ", "@", LEN(A97)-LEN(SUBSTITUTE(A97," ","")))))) | BW97: =TRIM(LEFT(A97,FIND(" ",A97&" ")-1)) | BX97: =+IF(BV97=BV96,"Same","Diff") | BY97: =IF(BX97="Same",IF(BW97=BW96,"same","Diff"))
A98: Warren Blomfield | E98: 1 | F98: 1 | BT98: =COUNTIF(B98:BS98,1) | BV98: =TRIM(RIGHT(A98, LEN(A98) - FIND("@", SUBSTITUTE(A98, " ", "@", LEN(A98)-LEN(SUBSTITUTE(A98," ","")))))) | BW98: =TRIM(LEFT(A98,FIND(" ",A98&" ")-1)) | BX98: =+IF(BV98=BV97,"Same","Diff") | BY98: =IF(BX98="Same",IF(BW98=BW97,"same","Diff"))
A99: Alton Boddenberg | F99: 1 | G99: 1 | H99: 1 | J99: 1 | BT99: =COUNTIF(B99:BS99,1) | BV99: =TRIM(RIGHT(A99, LEN(A99) - FIND("@", SUBSTITUTE(A99, " ", "@", LEN(A99)-LEN(SUBSTITUTE(A99," ","")))))) | BW99: =TRIM(LEFT(A99,FIND(" ",A99&" ")-1)) | BX99: =+IF(BV99=BV98,"Same","Diff") | BY99: =IF(BX99="Same",IF(BW99=BW98,"same","Diff"))
A100: Paul Bolton | E100: 1 | F100: 1 | BT100: =COUNTIF(B100:BS100,1) | BV100: =TRIM(RIGHT(A100, LEN(A100) - FIND("@", SUBSTITUTE(A100, " ", "@", LEN(A100)-LEN(SUBSTITUTE(A100," ","")))))) | BW100: =TRIM(LEFT(A100,FIND(" ",A100&" ")-1)) | BX100: =+IF(BV100=BV99,"Same","Diff") | BY100: =IF(BX100="Same",IF(BW100=BW99,"same","Diff"))
...

Sheet Overall Stats 2025 Drivers
B1: Upto Pre Bathurst 2025 | E1: ATCC | P1: ATCC | U1: Bathurst 1000 | AD1: Bathurst 1000 Shootouts | AI1: Super 2 Series
B2: Name | C2: Born | D2: Age | E2: Career Span | F2: Rounds | G2: Race Starts | H2: Race Wins | I2: Race Best Finish | J2: Race Top 10 | K2: Race Finishes | M2: Poles | N2: Podiums | P2: Career Span | Q2: Shootout Starts | R2: Shootout Poles | S2: Shootout Best | T2: Top 3 | U2: Career Span | V2: Race Starts | W2: Race Best Finish | X2: Race Wins | Z2: Race Top 3 | AA2: Race Top 10 | AB2: Race Finishes | AC2: Poles | AD2: Career Span | AE2: Shootout Starts | AF2: Shootout Poles | AG2: Shootout Best | AH2: Top 3 | AI2: Career Span | AJ2: Rounds | AK2: Round Best Finish | AL2: Round Wins | AM2: Round Podiums | AN2: Race Starts | AO2: Race Wins | AP2: Race Best Finish | AQ2: Race Top 3 | AR2: Race Top 10 | AS2: Race Finishes | AT2: Poles
A3: 6 | B3: Aaron Cameron | C3: 2000 | D3: 25 | E3: 2024-2025 | F3: 10 | G3: 25 | H3: 0 | I3: 9th | J3: 1 | K3: 24 | L3: =+K3/G3 | M3: 0 | N3: 0 | O3: =+N3/G3 | P3: - | Q3: - | R3: - | S3: - | T3: - | U3: 2024 | V3: 1 | W3: 23rd | X3: 0 | Y3: =+X3/V3 | Z3: 0 | AA3: 0 | AB3: 1 | AC3: 0 | AD3: - | AE3: - | AF3: - | AG3: - | AH3: - | AI3: 2023-2024 | AJ3: 9 | AK3: 2nd | AL3: 0 | AM3: 3 | AN3: 18 | AO3: 2 | AP3: 1st | AQ3: 4 | AR3: 16 | AS3: 18 | AT3: 2
A4: 39 | B4: Aaron Seton | C4: 1998 | D4: 27 | E4: 2022-2025 | F4: 2 | G4: 2 | H4: 0 | I4: 14th | J4: 0 | K4: 2 | L4: =+K4/G4 | M4: 0 | N4: 0 | O4: =+N4/G4 | P4: - | Q4: - | R4: - | S4: - | T4: - | U4: 2022 | V4: 1 | W4: 14th | X4: 0 | Y4: =+X4/V4 | Z4: 0 | AA4: 0 | AB4: 1 | AC4: 0 | AD4: - | AE4: - | AF4: - | AG4: - | AH4: - | AI4: 2021-2023 | AJ4: 17 | AK4: 4th | AL4: 0 | AM4: 0 | AN4: 33 | AO4: 0 | AP4: 3rd | AQ4: 2 | AR4: 19 | AS4: 29 | AT4: 1
A5: 16 | B5: Andre Heimgartner | C5: 1995 | D5: 30 | E5: 2014-2025 | F5: 129 | G5: 294 | H5: 2 | I5: 1st | J5: 99 | K5: 270 | L5: =+K5/G5 | M5: 3 | N5: 16 | O5: =+N5/G5 | P5: 2015-2025 | Q5: 30 | R5: 0 | S5: 3rd | T5: 2 | U5: 2014-2024 | V5: 11 | W5: 9th | X5: 0 | Y5: =+X5/V5 | Z5: 0 | AA5: 1 | AB5: 5 | AC5: 0 | AD5: 2024 | AE5: 1 | AF5: 0 | AG5: 10th | AH5: 0 | AI5: 2013-2014 | AJ5: 14 | AK5: 2nd | AL5: 0 | AM5: 2 | AN5: 31 | AO5: 2 | AP5: 1st | AQ5: 4 | AR5: 14 | AS5: 28 | AT5: 0
A6: 28 | B6: Anton De Pasquale | C6: 1995 | D6: 30 | E6: 2018-2025 | F6: 100 | G6: 231 | H6: 9 | I6: 1st | J6: 114 | K6: 210 | L6: =+K6/G6 | M6: 16 | N6: 36 | O6: =+N6/G6 | P6: 2018-2025 | Q6: 64 | R6: 6 | S6: 1st | T6: 17 | U6: 2018-2024 | V6: 7 | W6: 3rd | X6: 0 | Y6: =+X6/V6 | Z6: 1 | AA6: 4 | AB6: 5 | AC6: 0 | AD6: 2018-2024 | AE6: 6 | AF6: 0 | AG6: 2nd | AH6: 2 | AI6: 2016-2017 | AJ6: 14 | AK6: 1st | AL6: 2 | AM6: 4 | AN6: 37 | AO6: 2 | AP6: 1st | AQ6: 7 | AR6: 24 | AS6: 33 | AT6: 1
A7: 25 | B7: Brad Vaughan | C7: 2004 | D7: 21 | E7: 2024-2025 | F7: 3 | G7: 3 | H7: 0 | I7: 19th | J7: 0 | K7: 3 | L7: =+K7/G7 | M7: 0 | N7: 0 | O7: =+N7/G7 | P7: - | Q7: - | R7: - | S7: - | T7: - | U7: 2024 | V7: 1 | W7: 25th | X7: 0 | Y7: =+X7/V7 | Z7: 0 | AA7: 0 | AB7: 1 | AC7: 0 | AD7: - | AE7: - | AF7: - | AG7: - | AH7: - | AI7: 2023-2025 | AJ7: 16 | AK7: 2nd | AL7: 0 | AM7: 2 | AN7: 30 | AO7: 1 | AP7: 1st | AQ7: 7 | AR7: 19 | AS7: 25 | AT7: 5
A8: 46 | B8: Broc Feeney | C8: 2002 | D8: 22 | E8: 2020-2025 | F8: 48 | G8: 114 | H8: 24 | I8: 1st | J8: 90 | K8: 110 | L8: =+K8/G8 | M8: 22 | N8: 44 | O8: =+N8/G8 | P8: 2022-2025 | Q8: 34 | R8: 8 | S8: 1st | T8: 19 | U8: 2020-2024 | V8: 5 | W8: 2nd | X8: 0 | Y8: =+X8/V8 | Z8: 1 | AA8: 2 | AB8: 4 | AC8: 0 | AD8: 2023-2024 | AE8: 2 | AF8: 0 | AG8: 2nd | AH8: 2 | AI8: 2020-2021 | AJ8: 8 | AK8: 1st | AL8: 3 | AM8: 5 | AN8: 15 | AO8: 5 | AP8: 1st | AQ8: 8 | AR8: 15 | AS8: 15 | AT8: 5
A9: 40 | B9: Brodie Kostecki | C9: 1997 | D9: 27 | E9: 2019-2025 | F9: 60 | G9: 142 | H9: 10 | I9: 1st | J9: 80 | K9: 135 | L9: =+K9/G9 | M9: 16 | N9: 29 | O9: =+N9/G9 | P9: 2021-2025 | Q9: 29 | R9: 9 | S9: 1st | T9: 14 | U9: 2019-2024 | V9: 6 | W9: 1st | X9: 1 | Y9: =+X9/V9 | Z9: 3 | AA9: 5 | AB9: 5 | AC9: 2 | AD9: 2021-2024 | AE9: 3 | AF9: 2 | AG9: 1st | AH9: 2 | AI9: 2017-2020 | AJ9: 18 | AK9: 1st | AL9: 2 | AM9: 5 | AN9: 45 | AO9: 6 | AP9: 1st | AQ9: 12 | AR9: 24 | AS9: 41 | AT9: 1
A10: 24 | B10: Bryce Fullwood | C10: 1998 | D10: 27 | E10: 2018-2025 | F10: 75 | G10: 179 | H10: 0 | I10: 3rd | J10: 38 | K10: 168 | L10: =+K10/G10 | M10: 0 | N10: 3 | O10: =+N10/G10 | P10: 2020-2025 | Q10: 13 | R10: 0 | S10: 8th | T10: 0 | U10: 2018-2024 | V10: 7 | W10: 5th | X10: 0 | Y10: =+X10/V10 | Z10: 0 | AA10: 3 | AB10: 5 | AC10: 0 | AD10: - | AE10: - | AF10: - | AG10: - | AH10: - | AI10: 2015-2019 | AJ10: 35 | AK10: 1st | AL10: 4 | AM10: 7 | AN10: 77 | AO10: 6 | AP10: 1st | AQ10: 15 | AR10: 35 | AS10: 70 | AT10: 3
A11: 12 | B11: Cam Waters | C11: 1994 | D11: 31 | E11: 2011-2025 | F11: 138 | G11: 301 | H11: 18 | I11: 1st | J11: 180 | K11: 282 | L11: =+K11/G11 | M11: 32 | N11: 64 | O11: =+N11/G11 | P11: 2016-2025 | Q11: 78 | R11: 14 | S11: 1st | T11: 39 | U11: 2011-2024 | V11: 12 | W11: 2nd | X11: 0 | Y11: =+X11/V11 | Z11: 3 | AA11: 5 | AB11: 10 | AC11: 2 | AD11: 2017-2024 | AE11: 7 | AF11: 1 | AG11: 1st | AH11: 5 | AI11: 2011-2015 | AJ11: 26 | AK11: 1st | AL11: 5 | AM11: 9 | AN11: 60 | AO11: 12 | AP11: 1st | AQ11: 22 | AR11: 36 | AS11: 55 | AT11: 9
A12: 38 | B12: Cameron Crick | C12: 1997 | D12: 27 | E12: 2024-2025 | F12: 5 | G12: 9 | H12: 0 | I12: 10th | J12: 2 | K12: 9 | L12: =+K12/G12 | M12: 0 | N12: 0 | O12: =+N12/G12 | P12: - | Q12: - | R12: - | S12: - | T12: - | U12: 2024 | V12: 1 | W12: 10th | X12: 0 | Y12: =+X12/V12 | Z12: 0 | AA12: 1 | AB12: 1 | AC12: 0 | AD12: - | AE12: - | AF12: - | AG12: - | AH12: - | AI12: 2022-2024 | AJ12: 15 | AK12: 4th | AL12: 0 | AM12: 0 | AN12: 29 | AO12: 0 | AP12: 2nd | AQ12: 1 | AR12: 15 | AS12: 25 | AT12: 0
A13: 8 | B13: Cameron Hill | C13: 1996 | D13: 28 | E13: 2022-2025 | F13: 34 | G13: 79 | H13: 1 | I13: 1st | J13: 16 | K13: 74 | L13: =+K13/G13 | M13: 0 | N13: 3 | O13: =+N13/G13 | P13: 2024-2025 | Q13: 9 | R13: 0 | S13: 2nd | T13: 1 | U13: 2022-2024 | V13: 3 | W13: 10th | X13: 0 | Y13: =+X13/V13 | Z13: 0 | AA13: 1 | AB13: 3 | AC13: 0 | AD13: - | AE13: - | AF13: - | AG13: - | AH13: - | AI13: 2022 | AJ13: 6 | AK13: 3rd | AL13: 0 | AM13: 2 | AN13: 11 | AO13: 0 | AP13: 2nd | AQ13: 3 | AR13: 10 | AS13: 10 | AT13: 0
A14: 9 | B14: Cameron McLeod | C14: 2004 | D14: 20 | E14: 2024-2025 | F14: 3 | G14: 3 | H14: 0 | I14: 11th | J14: 0 | K14: 3 | L14: =+K14/G14 | M14: 0 | N14: 0 | O14: =+N14/G14 | P14: - | Q14: - | R14: - | S14: - | T14: - | U14: 2024 | V14: 1 | W14: 19th | X14: 0 | Y14: =+X14/V14 | Z14: 0 | AA14: 0 | AB14: 1 | AC14: 0 | AD14: - | AE14: - | AF14: - | AG14: - | AH14: - | AI14: 2024-2025 | AJ14: 9 | AK14: 2nd | AL14: 0 | AM14: 1 | AN14: 18 | AO14: 1 | AP14: 1st | AQ14: 3 | AR14: 10 | AS14: 16 | AT14: 1
A15: 32 | B15: Chaz Mostert | C15: 1992 | D15: 33 | E15: 2013-2025 | F15: 163 | G15: 374 | H15: 25 | I15: 1st | J15: 261 | K15: 358 | L15: =+K15/G15 | M15: 26 | N15: 106 | O15: =+N15/G15 | P15: 2014-2025 | Q15: 78 | R15: 3 | S15: 1st | T15: 19 | U15: 2013-2024 | V15: 11 | W15: 1st | X15: 2 | Y15: =+X15/V15 | Z15: 4 | AA15: 8 | AB15: 11 | AC15: 2 | AD15: 2016-2024 | AE15: 7 | AF15: 2 | AG15: 1st | AH15: 4 | AI15: 2010-2013 | AJ15: 16 | AK15: 1st | AL15: 3 | AM15: 7 | AN15: 39 | AO15: 5 | AP15: 1st | AQ15: 15 | AR15: 32 | AS15: 39 | AT15: 7
A16: 53 | B16: Cooper Murray | C16: 2001 | D16: 24 | E16: 2024-2025 | F16: 13 | G16: 32 | H16: 0 | I16: 5th | J16: 5 | K16: 29 | L16: =+K16/G16 | M16: 0 | N16: 0 | O16: =+N16/G16 | P16: 2024-2025 | Q16: 4 | R16: 0 | S16: 7th | T16: 0 | U16: 2024 | V16: 1 | W16: 14th | X16: 0 | Y16: =+X16/V16 | Z16: 0 | AA16: 0 | AB16: 1 | AC16: 0 | AD16: - | AE16: - | AF16: - | AG16: - | AH16: - | AI16: 2023-2024 | AJ16: 10 | AK16: 2nd | AL16: 0 | AM16: 3 | AN16: 20 | AO16: 2 | AP16: 1st | AQ16: 6 | AR16: 12 | AS16: 15 | AT16: 3
A17: 48 | B17: Craig Lowndes | C17: 1974 | D17: 51 | E17: 1996-2025 | F17: 305 | G17: 680 | H17: 110 | I17: 1st | J17: 501 | K17: 626 | L17: =+K17/G17 | M17: 43 | N17: 169 | O17: =+N17/G17 | P17: 1999-2018 | Q17: 115 | R17: 11 | S17: 1st | T17: 33 | U17: 1994-2024 | V17: 31 | W17: 1st | X17: 7 | Y17: =+X17/V17 | Z17: 14 | AA17: 21 | AB17: 27 | AC17: 2 | AD17: 1995-2018 | AE17: 17 | AF17: 2 | AG17: 1st | AH17: 7 | AI17: - | AJ17: - | AK17: - | AL17: - | AM17: - | AN17: - | AO17: - | AP17: - | AQ17: - | AR17: - | AS17: - | AT17: - | AU17: From Race Results 108, From Round Results 61
A18: 35 | B18: Dale Wood | C18: 1983 | D18: 42 | E18: 2008-2025 | F18: 90 | G18: 173 | H18: 0 | I18: 3rd | J18: 16 | K18: 155 | L18: =+K18/G18 | M18: 0 | N18: 1 | O18: =+N18/G18 | P18: 2014 | Q18: 1 | R18: 0 | S18: 8th | T18: 0 | U18: 2008-2024 | V18: 17 | W18: 4th | X18: 0 | Y18: =+X18/V18 | Z18: 0 | AA18: 6 | AB18: 13 | AC18: 0 | AD18: 2014 | AE18: 1 | AF18: 0 | AG18: 8th | AH18: 0 | AI18: 2007-2013 | AJ18: 29 | AK18: 1st | AL18: 1 | AM18: 9 | AN18: 74 | AO18: 4 | AP18: 1st | AQ18: 19 | AR18: 51 | AS18: 66 | AT18: 1
A19: 30 | B19: David Reynolds | C19: 1985 | D19: 40 | E19: 2007-2025 | F19: 218 | G19: 482 | H19: 8 | I19: 1st | J19: 220 | K19: 448 | L19: =+K19/G19 | M19: 17 | N19: 44 | O19: =+N19/G19 | P19: 2009-2025 | Q19: 84 | R19: 8 | S19: 1st | T19: 25 | U19: 2007-2024 | V19: 17 | W19: 1st | X19: 1 | Y19: =+X19/V19 | Z19: 2 | AA19: 6 | AB19: 13 | AC19: 2 | AD19: 2011-2023 | AE19: 7 | AF19: 2 | AG19: 1st | AH19: 3 | AI19: 2008-2010 | AJ19: 8 | AK19: 2nd | AL19: 0 | AM19: 3 | AN19: 21 | AO19: 0 | AP19: 2nd | AQ19: 5 | AR19: 18 | AS19: 20 | AT19: 0
A20: 37 | B20: David Russell | C20: 1982 | D20: 43 | E20: 2003-2025 | F20: 35 | G20: 43 | H20: 0 | I20: 2nd | J20: 15 | K20: 34 | L20: =+K20/G20 | M20: 0 | N20: 5 | O20: =+N20/G20 | P20: - | Q20: - | R20: - | S20: - | T20: - | U20: 2003-2024 | V20: 15 | W20: 2nd | X20: 0 | Y20: =+X20/V20 | Z20: 2 | AA20: 6 | AB20: 11 | AC20: 0 | AD20: - | AE20: - | AF20: - | AG20: - | AH20: - | AI20: 2003-2019 | AJ20: 32 | AK20: 1st | AL20: 3 | AM20: 11 | AN20: 79 | AO20: 9 | AP20: 1st | AQ20: 26 | AR20: 56 | AS20: 73 | AT20: 2
A21: 17 | B21: Declan Fraser | C21: 2000 | D21: 25 | E21: 2022-2025 | F21: 16 | G21: 32 | H21: 0 | I21: 8th | J21: 2 | K21: 28 | L21: =+K21/G21 | M21: 0 | N21: 0 | O21: =+N21/G21 | P21: - | Q21: - | R21: - | S21: - | T21: - | U21: 2022-2024 | V21: 3 | W21: 8th | X21: 0 | Y21: =+X21/V21 | Z21: 0 | AA21: 1 | AB21: 3 | AC21: 0 | AD21: - | AE21: - | AF21: - | AG21: - | AH21: - | AI21: 2021-2022 | AJ21: 11 | AK21: 1st | AL21: 2 | AM21: 4 | AN21: 19 | AO21: 4 | AP21: 1st | AQ21: 7 | AR21: 18 | AS21: 18 | AT21: 4
A22: 33 | B22: Fabian Coulthard | C22: 1982 | D22: 43 | E22: 2004-2025 | F22: 220 | G22: 477 | H22: 13 | I22: 1st | J22: 220 | K22: 430 | L22: =+K22/G22 | M22: 9 | N22: 61 | O22: =+N22/G22 | P22: 2008-2021 | Q22: 52 | R22: 2 | S22: 1st | T22: 9 | U22: 2004-2024 | V22: 21 | W22: 2nd | X22: 0 | Y22: =+X22/V22 | Z22: 2 | AA22: 8 | AB22: 16 | AC22: 0 | AD22: 2008-2020 | AE22: 7 | AF22: 0 | AG22: 4th | AH22: 0 | AI22: - | AJ22: - | AK22: - | AL22: - | AM22: - | AN22: - | AO22: - | AP22: - | AQ22: - | AR22: - | AS22: - | AT22: -
A23: 52 | B23: Garth Tander | C23: 1977 | D23: 48 | E23: 1998-2025 | F23: 293 | G23: 647 | H23: 57 | I23: 1st | J23: 413 | K23: 603 | L23: =+K23/G23 | M23: 30 | N23: 101 | O23: =+N23/G23 | P23: 1999-2018 | Q23: 112 | R23: 18 | S23: 1st | T23: 42 | U23: 1998-2024 | V23: 26 | W23: 1st | X23: 5 | Y23: =+X23/V23 | Z23: 8 | AA23: 12 | AB23: 18 | AC23: 2 | AD23: 199-2018 | AE23: 15 | AF23: 2 | AG23: 1st | AH23: 3 | AI23: - | AJ23: - | AK23: - | AL23: - | AM23: - | AN23: - | AO23: - | AP23: - | AQ23: - | AR23: - | AS23: - | AT23: - | AU23: From Race Results 62, From Round Results 39
A24: 29 | B24: Harri Jones | C24: 1999 | D24: 26 | E24: 2025 | F24: 1 | G24: 1 | H24: 0 | I24: 10th | J24: 1 | K24: 1 | L24: =+K24/G24 | M24: 0 | N24: 0 | O24: =+N24/G24 | P24: - | Q24: - | R24: - | S24: - | T24: - | U24: 2025 | Y24: =+X24/V24 | AI24: - | AJ24: - | AK24: - | AL24: - | AM24: - | AN24: - | AO24: - | AP24: - | AQ24: - | AR24: - | AS24: - | AT24: -
A25: 18 | B25: Jack Le Brocq | C25: 1992 | D25: 33 | E25: 2015-2025 | F25: 111 | G25: 246 | H25: 2 | I25: 1st | J25: 56 | K25: 220 | L25: =+K25/G25 | M25: 2 | N25: 3 | O25: =+N25/G25 | P25: 2020-2025 | Q25: 25 | R25: 1 | S25: 1st | T25: 4 | U25: 2015-2024 | V25: 10 | W25: 4th | X25: 0 | Y25: =+X25/V25 | Z25: 0 | AA25: 4 | AB25: 9 | AC25: 0 | AD25: 2021-2024 | AE25: 2 | AF25: 0 | AG25: 6th | AH25: 0 | AI25: 2014-2017 | AJ25: 27 | AK25: 1st | AL25: 4 | AM25: 11 | AN25: 64 | AO25: 11 | AP25: 1st | AQ25: 26 | AR25: 52 | AS25: 59 | AT25: 6
A26: 15 | B26: Jack Perkins | C26: 1986 | D26: 39 | E26: 2006-2025 | F26: 85 | G26: 159 | H26: 1 | I26: 1st | J26: 21 | K26: 134 | L26: =+K26/G26 | M26: 0 | N26: 3 | O26: =+N26/G26 | P26: 2014 | Q26: 1 | R26: 0 | S26: 9th | T26: 0 | U26: 2006-2024 | V26: 19 | W26: 3rd | X26: 0 | Y26: =+X26/V26 | Z26: 1 | AA26: 6 | AB26: 15 | AC26: 0 | AD26: 2014 | AE26: 1 | AF26: 0 | AG26: 9th | AH26: 0 | AI26: 2006-2024 | AJ26: 53 | AK26: 1st | AL26: 4 | AM26: 17 | AN26: 123 | AO26: 9 | AP26: 1st | AQ26: 37 | AR26: 92 | AS26: 111 | AT26: 3
A27: 23 | B27: Jack Smith | C27: 1999 | D27: 26 | E27: 2019-2025 | F27: 56 | G27: 134 | H27: 0 | I27: 10th | J27: 1 | K27: 123 | L27: =+K27/G27 | M27: 0 | N27: 0 | O27: =+N27/G27 | P27: - | Q27: - | R27: - | S27: - | T27: - | U27: 2019-2023 | V27: 5 | W27: 17th | X27: 0 | Y27: =+X27/V27 | Z27: 0 | AA27: 0 | AB27: 2 | AC27: 0 | AD27: - | AE27: - | AF27: - | AG27: - | AH27: - | AI27: 2016-2019 | AJ27: 22 | AK27: 6th | AL27: 0 | AM27: 0 | AN27: 50 | AO27: 0 | AP27: 3rd | AQ27: 1 | AR27: 9 | AS27: 45 | AT27: 0
A28: 14 | B28: James Courtney | C28: 1980 | D28: 45 | E28: 2005-2025 | F28: 266 | G28: 603 | H28: 15 | I28: 1st | J28: 297 | K28: 547 | L28: =+K28/G28 | M28: 10 | N28: 66 | O28: =+N28/G28 | P28: 2006-2025 | Q28: 81 | R28: 3 | S28: 1st | T28: 16 | U28: 2005-2024 | V28: 19 | W28: 2nd | X28: 0 | Y28: =+X28/V28 | Z28: 4 | AA28: 10 | AB28: 15 | AC28: 0 | AD28: 2007-2022 | AE28: 8 | AF28: 0 | AG28: 3rd | AH28: 1 | AI28: - | AJ28: - | AK28: - | AL28: - | AM28: - | AN28: - | AO28: - | AP28: - | AQ28: - | AR28: - | AS28: - | AT28: - | AU28: From Race Results 57, From Round Results 9
A29: 36 | B29: James Golding | C29: 1996 | D29: 29 | E29: 2016-2025 | F29: 81 | G29: 170 | H29: 0 | I29: 3rd | J29: 32 | K29: 157 | L29: =+K29/G29 | M29: 1 | N29: 1 | O29: =+N29/G29 | P29: 2022-2025 | Q29: 21 | R29: 1 | S29: 1st | T29: 2 | U29: 2016-2024 | V29: 9 | W29: 6th | X29: 0 | Y29: =+X29/V29 | Z29: 0 | AA29: 4 | AB29: 7 | AC29: 0 | AD29: 2023 | AE29: 2 | AF29: 0 | AG29: 4th | AH29: 0 | AI29: 2014-2016 | AJ29: 15 | AK29: 2nd | AL29: 0 | AM29: 4 | AN29: 34 | AO29: 2 | AP29: 1st | AQ29: 8 | AR29: 20 | AS29: 29 | AT29: 0
A30: 43 | B30: James Moffat | C30: 1984 | D30: 41 | E30: 2010-2025 | F30: 115 | G30: 240 | H30: 2 | I30: 1st | J30: 63 | K30: 204 | L30: =+K30/G30 | M30: 1 | N30: 6 | O30: =+N30/G30 | P30: 2011-2017 | Q30: 10 | R30: 0 | S30: 3rd | T30: 1 | U30: 2010-2024 | V30: 15 | W30: 2nd | X30: 0 | Y30: =+X30/V30 | Z30: 3 | AA30: 7 | AB30: 12 | AC30: 0 | AD30: 2014-2015 | AE30: 2 | AF30: 0 | AG30: 5th | AH30: 0 | AI30: 2009-2010 | AJ30: 14 | AK30: 1st | AL30: 1 | AM30: 8 | AN30: 36 | AO30: 5 | AP30: 1st | AQ30: 22 | AR30: 30 | AS30: 31 | AT30: 3
A31: 47 | B31: Jamie Whincup | C31: 1983 | D31: 42 | E31: 2002-2025 | F31: 258 | G31: 560 | H31: 125 | I31: 1st | J31: 417 | K31: 528 | L31: =+K31/G31 | M31: 92 | N31: 240 | O31: =+N31/G31 | P31: 2003-2021 | Q31: 112 | R31: 23 | S31: 1st | T31: 60 | U31: 2002-2024 | V31: 23 | W31: 1st | X31: 4 | Y31: =+X31/V31 | Z31: 8 | AA31: 15 | AB31: 21 | AC31: 2 | AD31: 2008-2020 | AE31: 10 | AF31: 2 | AG31: 1st | AH31: 6 | AI31: - | AJ31: - | AK31: - | AL31: - | AM31: - | AN31: - | AO31: - | AP31: - | AQ31: - | AR31: - | AS31: - | AT31: - | AU31: From Race Results 219, From Round Results 21
A32: 19 | B32: Jarrod Hughes | C32: 2005 | D32: 20 | E32: 2025 | F32: 1 | G32: 1 | H32: 0 | I32: 12th | J32: 0 | K32: 1 | L32: =+K32/G32 | M32: 0 | N32: 0 | O32: =+N32/G32 | P32: - | Q32: - | R32: - | S32: - | T32: - | U32: 2025 | Y32: =+X32/V32 | AD32: - | AE32: - | AF32: - | AG32: - | AH32: - | AI32: 2024-2025 | AJ32: 10 | AK32: 4th | AL32: 0 | AM32: 0 | AN32: 19 | AO32: 0 | AP32: 4th | AQ32: 0 | AR32: 12 | AS32: 17 | AT32: 1
A33: 22 | B33: Jaxon Evans | C33: 1996 | D33: 29 | E33: 2022-2025 | F33: 24 | G33: 50 | H33: 0 | I33: 7th | J33: 4 | K33: 42 | L33: =+K33/G33 | M33: 0 | N33: 0 | O33: =+N33/G33 | P33: 2024-2025 | Q33: 2 | R33: 0 | S33: 7th | T33: 0 | U33: 2022-2024 | V33: 3 | W33: 20th | X33: 0 | Y33: =+X33/V33 | Z33: 0 | AA33: 0 | AB33: 2 | AC33: 0 | AD33: - | AE33: - | AF33: - | AG33: - | AH33: - | AI33: - | AJ33: - | AK33: - | AL33: - | AM33: - | AN33: - | AO33: - | AP33: - | AQ33: - | AR33: - | AS33: - | AT33: -
A34: 5 | B34: Jayden Ojeda | C34: 1999 | D34: 26 | E34: 2020-2025 | F34: 10 | G34: 14 | H34: 0 | I34: 6th | J34: 3 | K34: 12 | L34: =+K34/G34 | M34: 0 | N34: 0 | O34: =+N34/G34 | P34: - | Q34: - | R34: - | S34: - | T34: - | U34: 2020-2024 | V34: 5 | W34: 8th | X34: 0 | Y34: =+X34/V34 | Z34: 0 | AA34: 2 | AB34: 4 | AC34: 0 | AD34: - | AE34: - | AF34: - | AG34: - | AH34: - | AI34: 2020-2021 | AJ34: 8 | AK34: 3rd | AL34: 0 | AM34: 3 | AN34: 17 | AO34: 0 | AP34: 2nd | AQ34: 8 | AR34: 14 | AS34: 14 | AT34: 2
A35: 54 | B35: Jobe Stewart | C35: 2004 | D35: 21 | E35: 2025 | F35: 1 | G35: 1 | H35: 0 | I35: 7th | J35: 1 | K35: 1 | L35: =+K35/G35 | M35: 0 | N35: 0 | O35: =+N35/G35 | P35: - | Q35: - | R35: - | S35: - | T35: - | U35: 2025 | Y35: =+X35/V35 | AD35: - | AE35: - | AF35: - | AG35: - | AH35: - | AI35: 2024-2025 | AJ35: 10 | AK35: 2nd | AL35: 0 | AM35: 1 | AN35: 20 | AO35: 1 | AP35: 1st | AQ35: 5 | AR35: 10 | AS35: 18 | AT35: 0
A36: 50 | B36: Jordan Boys | C36: 1997 | D36: 27 | E36: 2020-2025 | F36: 9 | G36: 13 | H36: 0 | I36: 11th | J36: 0 | K36: 12 | L36: =+K36/G36 | M36: 0 | N36: 0 | O36: =+N36/G36 | P36: - | Q36: - | R36: - | S36: - | T36: - | U36: 2020-2024 | V36: 4 | W36: 13th | X36: 0 | Y36: =+X36/V36 | Z36: 0 | AA36: 0 | AB36: 3 | AC36: 0 | AD36: - | AE36: - | AF36: - | AG36: - | AH36: - | AI36: 2017-2023 | AJ36: 25 | AK36: 2nd | AL36: 0 | AM36: 3 | AN36: 53 | AO36: 3 | AP36: 1st | AQ36: 7 | AR36: 24 | AS36: 43 | AT36: 2
A37: 34 | B37: Kai Allen | C37: 2005 | D37: 20 | E37: 2023-2025 | F37: 13 | G37: 30 | H37: 0 | I37: 2nd | J37: 8 | K37: 29 | L37: =+K37/G37 | M37: 0 | N37: 4 | O37: =+N37/G37 | P37: 2025 | Q37: 3 | R37: 0 | S37: 5th | T37: 0 | U37: 2023-2024 | V37: 2 | W37: 12th | X37: 0 | Y37: =+X37/V37 | Z37: 0 | AA37: 0 | AB37: 2 | AC37: 0 | AD37: - | AE37: - | AF37: - | AG37: - | AH37: - | AI37: 2023-2024 | AJ37: 12 | AK37: 1st | AL37: 3 | AM37: 8 | AN37: 24 | AO37: 6 | AP37: 1st | AQ37: 10 | AR37: 21 | AS37: 23 | AT37: 2
A38: 31 | B38: Lee Holdsworth | C38: 1983 | D38: 42 | E38: 2004-2025 | F38: 232 | G38: 515 | H38: 4 | I38: 1st | J38: 170 | K38: 463 | L38: =+K38/G38 | M38: 4 | N38: 18 | O38: =+N38/G38 | P38: 2007-2022 | Q38: 47 | R38: 2 | S38: 1st | T38: 6 | U38: 2004-2024 | V38: 21 | W38: 1st | X38: 1 | Y38: =+X38/V38 | Z38: 2 | AA38: 10 | AB38: 14 | AC38: 0 | AD38: 2007-2022 | AE38: 5 | AF38: 0 | AG38: 4th | AH38: 0 | AI38: 2004-2005 | AJ38: 11 | AK38: 3rd | AL38: 0 | AM38: 1 | AN38: 29 | AO38: 2 | AP38: 1st | AQ38: 4 | AR38: 16 | AS38: 23 | AT38: 0 | AU38: From Race Results 16, From Round Results 2
A39: 10 | B39: Lochie Dalton | C39: 2002 | D39: 23 | E39: 2024-2025 | F39: 3 | G39: 6 | H39: 0 | I39: 21st | J39: 0 | K39: 6 | L39: =+K39/G39 | M39: 0 | N39: 0 | O39: =+N39/G39 | P39: - | Q39: - | R39: - | S39: - | T39: - | U39: 2025 | X39: 0 | Y39: =+X39/V39 | AD39: - | AE39: - | AF39: - | AG39: - | AH39: - | AI39: 2022-2025 | AJ39: 17 | AK39: 1st | AL39: 1 | AM39: 3 | AN39: 33 | AO39: 2 | AP39: 1st | AQ39: 3 | AR39: 20 | AS39: 33 | AT39: 2
A40: 49 | B40: Macauley Jones | C40: 1994 | D40: 31 | E40: 2015-2025 | F40: 100 | G40: 224 | H40: 0 | I40: 5th | J40: 10 | K40: 204 | L40: =+K40/G40 | M40: 0 | N40: 0 | O40: =+N40/G40 | P40: 2020-2025 | Q40: 4 | R40: 0 | S40: 8th | T40: 0 | U40: 2015-2024 | V40: 10 | W40: 7th | X40: 0 | Y40: =+X40/V40 | Z40: 0 | AA40: 2 | AB40: 9 | AC40: 0 | AD40: - | AE40: - | AF40: - | AG40: - | AH40: - | AI40: 2014-2018 | AJ40: 32 | AK40: 3rd | AL40: 0 | AM40: 1 | AN40: 74 | AO40: 0 | AP40: 2nd | AQ40: 3 | AR40: 42 | AS40: 66 | AT40: 1
A41: 13 | B41: Mark Winterbottom | C41: 1981 | D41: 44 | E41: 2003-2025 | F41: 288 | G41: 646 | H41: 39 | I41: 1st | J41: 366 | K41: 616 | L41: =+K41/G41 | M41: 36 | N41: 121 | O41: =+N41/G41 | P41: 2005-2024 | Q41: 88 | R41: 11 | S41: 1st | T41: 34 | U41: 2003-2024 | V41: 22 | W41: 1st | X41: 1 | Y41: =+X41/V41 | Z41: 2 | AA41: 10 | AB41: 15 | AC41: 2 | AD41: 2007-2019 | AE41: 11 | AF41: 2 | AG41: 1st | AH41: 7 | AI41: 2003 | AJ41: 6 | AK41: 1st | AL41: 4 | AM41: 6 | AN41: 16 | AO41: 8 | AP41: 1st | AQ41: 12 | AR41: 15 | AS41: 16 | AT41: 5 | AU41: From Race Results 108, From Round Results 13
A42: 51 | B42: Matt Payne | C42: 2002 | D42: 23 | E42: 2022-2025 | F42: 34 | G42: 79 | H42: 5 | I42: 1st | J42: 46 | K42: 76 | L42: =+K42/G42 | M42: 3 | N42: 13 | O42: =+N42/G42 | P42: 2023-2025 | Q42: 25 | R42: 1 | S42: 1st | T42: 6 | U42: 2022-2024 | V42: 3 | W42: 6th | X42: 0 | Y42: =+X42/V42 | Z42: 0 | AA42: 1 | AB42: 2 | AC42: 0 | AD42: 2023-2024 | AE42: 2 | AF42: 0 | AG42: 7th | AH42: 0 | AI42: 2021-2022 | AJ42: 8 | AK42: 1st | AL42: 1 | AM42: 4 | AN42: 15 | AO42: 2 | AP42: 1st | AQ42: 6 | AR42: 10 | AS42: 13 | AT42: 3
A43: 45 | B43: Nash Morris | C43: 2003 | D43: 22 | E43: 2025 | F43: 1 | G43: 1 | H43: 0 | I43: 23rd | J43: 0 | K43: 1 | L43: =+K43/G43 | M43: 0 | N43: 0 | O43: =+N43/G43 | P43: - | Q43: - | R43: - | S43: - | T43: - | U43: 2025 | Y43: =+X43/V43 | AD43: - | AE43: - | AF43: - | AG43: - | AH43: - | AI43: 2022-2025 | AJ43: 16 | AK43: 3rd | AL43: 0 | AM43: 1 | AN43: 31 | AO43: 1 | AP43: 1st | AQ43: 2 | AR43: 13 | AS43: 23 | AT43: 0
A44: 20 | B44: Nick Percat | C44: 1988 | D44: 37 | E44: 2010-2025 | F44: 164 | G44: 366 | H44: 6 | I44: 1st | J44: 150 | K44: 339 | L44: =+K44/G44 | M44: 2 | N44: 19 | O44: =+N44/G44 | P44: 2014-2024 | Q44: 38 | R44: 1 | S44: 1st | T44: 2 | U44: 2011-2024 | V44: 14 | W44: 1st | X44: 1 | Y44: =+X44/V44 | Z44: 3 | AA44: 6 | AB44: 13 | AC44: 0 | AD44: 2018-2022 | AE44: 4 | AF44: 0 | AG44: 7th | AH44: 0 | AI44: 2010-2012 | AJ44: 21 | AK44: 1st | AL44: 3 | AM44: 9 | AN44: 53 | AO44: 6 | AP44: 1st | AQ44: 24 | AR44: 43 | AS44: 34 | AT44: 1
A45: 44 | B45: Richie Stanaway | C45: 1991 | D45: 33 | E45: 2016-2025 | F45: 58 | G45: 113 | H45: 2 | I45: 1st | J45: 20 | K45: 102 | L45: =+K45/G45 | M45: 1 | N45: 4 | O45: =+N45/G45 | P45: 2018-2025 | Q45: 7 | R45: 0 | S45: 2nd | T45: 1 | U45: 2016-2024 | V45: 7 | W45: 1st | X45: 1 | Y45: =+X45/V45 | Z45: 1 | AA45: 2 | AB45: 7 | AC45: 0 | AD45: 2022-2024 | AE45: 1 | AF45: 0 | AG45: 4th | AH45: 0 | AI45: 2017 | AJ45: 1 | AK45: 3rd | AL45: 0 | AM45: 1 | AN45: 4 | AO45: 1 | AP45: 1st | AQ45: 3 | AR45: 4 | AS45: 4 | AT45: 0
A46: 4 | B46: Ryan Wood | C46: 2003 | D46: 21 | E46: 2024-2025 | F46: 21 | G46: 50 | H46: 1 | I46: 1st | J46: 22 | K46: 45 | L46: =+K46/G46 | M46: 1 | N46: 4 | O46: =+N46/G46 | P46: 2024-2025 | Q46: 14 | R46: 0 | S46: 2nd | T46: 3 | U46: 2024 | V46: 1 | W46: 15th | X46: 0 | Y46: =+X46/V46 | Z46: 0 | AA46: 0 | AB46: 1 | AC46: 0 | AD46: - | AE46: - | AF46: - | AG46: - | AH46: - | AI46: 2023 | AJ46: 6 | AK46: 1st | AL46: 3 | AM46: 3 | AN46: 12 | AO46: 5 | AP46: 1st | AQ46: 6 | AR46: 10 | AS46: 10 | AT46: 4
A47: 11 | B47: Rylan Gray | C47: 2006 | D47: 18 | E47: 2025 | F47: 2 | G47: 4 | H47: 0 | I47: 21st | J47: 0 | K47: 4 | L47: =+K47/G47 | M47: 0 | N47: 0 | O47: =+N47/G47 | P47: - | Q47: - | R47: - | S47: - | T47: - | U47: 2025 | X47: 0 | Y47: =+X47/V47 | AD47: - | AE47: - | AF47: - | AG47: - | AH47: - | AI47: 2024-2025 | AJ47: 10 | AK47: 1st | AL47: 2 | AM47: 4 | AN47: 20 | AO47: 2 | AP47: 1st | AQ47: 8 | AR47: 15 | AS47: 19 | AT47: 1
A48: 3 | B48: Scott Pye | C48: 1990 | D48: 35 | E48: 2012-2025 | F48: 152 | G48: 343 | H48: 2 | I48: 1st | J48: 116 | K48: 308 | L48: =+K48/G48 | M48: 1 | N48: 12 | O48: =+N48/G48 | P48: 2014-2023 | Q48: 23 | R48: 0 | S48: 2nd | T48: 1 | U48: 2012-2024 | V48: 13 | W48: 2nd | X48: 0 | Y48: =+X48/V48 | Z48: 3 | AA48: 7 | AB48: 9 | AC48: 0 | AD48: 2015-2016 | AE48: 2 | AF48: 0 | AG48: 7th | AH48: 0 | AI48: 2012 | AJ48: 7 | AK48: 1st | AL48: 1 | AM48: 5 | AN48: 18 | AO48: 2 | AP48: 1st | AQ48: 10 | AR48: 15 | AS48: 17 | AT48: 2
A49: 42 | B49: Thomas Randle | C49: 1996 | D49: 29 | E49: 2019-2025 | F49: 55 | G49: 129 | H49: 0 | I49: 2nd | J49: 48 | K49: 121 | L49: =+K49/G49 | M49: 3 | N49: 10 | O49: =+N49/G49 | P49: 2022-2025 | Q49: 22 | R49: 0 | S49: 2nd | T49: 6 | U49: 2019-2024 | V49: 6 | W49: 7th | X49: 0 | Y49: =+X49/V49 | Z49: 0 | AA49: 2 | AB49: 5 | AC49: 0 | AD49: - | AE49: - | AF49: - | AG49: - | AH49: - | AI49: 2018-2020 | AJ49: 17 | AK49: 1st | AL49: 3 | AM49: 7 | AN49: 35 | AO49: 5 | AP49: 1st | AQ49: 14 | AR49: 25 | AS49: 30 | AT49: 6
A50: 21 | B50: Tim Slade | C50: 1985 | D50: 40 | E50: 2009-2025 | F50: 209 | G50: 452 | H50: 2 | I50: 1st | J50: 154 | K50: 415 | L50: =+K50/G50 | M50: 2 | N50: 17 | O50: =+N50/G50 | P50: 2010-2024 | Q50: 42 | R50: 1 | S50: 1st | T50: 5 | U50: 2009-2024 | V50: 16 | W50: 5th | X50: 0 | Y50: =+X50/V50 | Z50: 0 | AA50: 6 | AB50: 14 | AC50: 0 | AD50: 2012-2021 | AE50: 5 | AF50: 0 | AG50: 4th | AH50: 0 | AI50: 2007-2008 | AJ50: 13 | AK50: 1st | AL50: 1 | AM50: 2 | AN50: 34 | AO50: 1 | AP50: 1st | AQ50: 5 | AR50: 18 | AS50: 30 | AT50: 0
A51: 41 | B51: Todd Hazelwood | C51: 1995 | D51: 30 | E51: 2017-2025 | F51: 88 | G51: 196 | H51: 2 | I51: 1st | J51: 36 | K51: 182 | L51: =+K51/G51 | M51: 1 | N51: 3 | O51: =+N51/G51 | P51: 2019-2024 | Q51: 17 | R51: 0 | S51: 3rd | T51: 1 | U51: 2017-2024 | V51: 8 | W51: 1st | X51: 1 | Y51: =+X51/V51 | Z51: 1 | AA51: 2 | AB51: 5 | AC51: 0 | AD51: - | AE51: - | AF51: - | AG51: - | AH51: - | AI51: 2013-2017 | AJ51: 29 | AK51: 1st | AL51: 2 | AM51: 8 | AN51: 66 | AO51: 6 | AP51: 1st | AQ51: 18 | AR51: 56 | AS51: 64 | AT51: 4
A52: 27 | B52: Tony D'Alberto | C52: 1985 | D52: 39 | E52: 2005-2025 | F52: 117 | G52: 219 | H52: 0 | I52: 3rd | J52: 35 | K52: 180 | L52: =+K52/G52 | M52: 0 | N52: 3 | O52: =+N52/G52 | P52: 2010-2013 | Q52: 8 | R52: 0 | S52: 4th | T52: 0 | U52: 2005-2024 | V52: 20 | W52: 3rd | X52: 0 | Y52: =+X52/V52 | Z52: 2 | AA52: 10 | AB52: 13 | AC52: 0 | AD52: - | AE52: - | AF52: - | AG52: - | AH52: - | AI52: 2003-2021 | AJ52: 33 | AK52: 1st | AL52: 2 | AM52: 8 | AN52: 4 | AO52: 2 | AP52: 1st | AQ52: 19 | AR52: 56 | AS52: 74 | AT52: 2
A53: 2 | B53: Will Brown | C53: 1998 | D53: 27 | E53: 2018-2025 | F53: 65 | G53: 152 | H53: 12 | I53: 1st | J53: 95 | K53: 141 | L53: =+K53/G53 | M53: 8 | N53: 42 | O53: =+N53/G53 | P53: 2021-2025 | Q53: 31 | R53: 5 | S53: 1st | T53: 13 | U53: 2018-2024 | V53: 7 | W53: 3rd | X53: 0 | Y53: =+X53/V53 | Z53: 1 | AA53: 3 | AB53: 6 | AC53: 0 | AD53: 2021-2024 | AE53: 2 | AF53: 0 | AG53: 5th | AH53: 0 | AI53: 2017-2020 | AJ53: 24 | AK53: 2nd | AL53: 0 | AM53: 6 | AN53: 58 | AO53: 3 | AP53: 1st | AQ53: 11 | AR53: 39 | AS53: 51 | AT53: 2
A54: 26 | B54: Will Davison | C54: 1982 | D54: 43 | E54: 2004-2025 | F54: 266 | G54: 596 | H54: 22 | I54: 1st | J54: 318 | K54: 542 | L54: =+K54/G54 | M54: 29 | N54: 81 | O54: =+N54/G54 | P54: 2006-2025 | Q54: 80 | R54: 7 | S54: 1st | T54: 26 | U54: 2004-2024 | V54: 21 | W54: 1st | X54: 2 | Y54: =+X54/V54 | Z54: 4 | AA54: 9 | AB54: 17 | AC54: 1 | AD54: 2008-2023 | AE54: 8 | AF54: 1 | AG54: 1st | AH54: 2 | AI54: 2005 | AJ54: 1 | AK54: 2nd | AL54: 0 | AM54: 1 | AN54: 3 | AO54: 0 | AP54: 2nd | AQ54: 3 | AR54: 3 | AS54: 3 | AT54: 0 | AU54: From Race Results 77, From Round Results 4
A55: 1 | B55: Zac Bates | C55: 2004 | D55: 21 | E55: 2025 | F55: 2 | G55: 4 | H55: 0 | I55: 16th | J55: 0 | K55: 4 | L55: =+K55/G55 | M55: 0 | N55: 0 | O55: =+N55/G55 | P55: 2025 | Q55: 1 | R55: 0 | S55: 5th | T55: 0 | U55: 2025 | X55: 0 | Y55: =+X55/V55 | AC55: 0 | AD55: - | AE55: - | AF55: - | AG55: - | AH55: - | AI55: 2023-2025 | AJ55: 16 | AK55: 1st | AL55: 3 | AM55: 4 | AN55: 32 | AO55: 2 | AP55: 1st | AQ55: 12 | AR55: 24 | AS55: 31 | AT55: 3
A56: 7 | B56: Zak Best | C56: 2001 | D56: 23 | E56: 2021-2025 | F56: 7 | G56: 11 | H56: 0 | I56: 5th | J56: 2 | K56: 8 | L56: =+K56/G56 | M56: 1 | N56: 0 | O56: =+N56/G56 | P56: - | Q56: - | R56: - | S56: - | T56: - | U56: 2021-2023 | V56: 3 | W56: 6th | X56: 0 | Y56: =+X56/V56 | Z56: 0 | AA56: 1 | AB56: 2 | AC56: 0 | AD56: - | AE56: - | AF56: - | AG56: - | AH56: - | AI56: 2020-2023 | AJ56: 20 | AK56: 1st | AL56: 5 | AM56: 10 | AN56: 40 | AO56: 5 | AP56: 1st | AQ56: 18 | AR56: 21 | AS56: 38 | AT56: 6

Sheet Yearly Results 1960-1962 P Isl.
B1: Event | C1: Position | D1: Class | E1: Pos. in Class | F1: Car | G1: Team | H1: Sponsor | I1: Vehicle | J1: Engine Vol (cc) / Engine Type | K1: Driver 1 | L1: Country ISO | M1: Birth Date | N1: Age on Race Day | O1: Driver 2 | P1: Country ISO | Q1: Birth Date | R1: Age on Race Day | S1: Driver 3 | T1: Country ISO | U1: Birth Date | V1: Age on Race Day | W1: Qualifying Position | X1: Laps | Y1: On Lap | Z1: Qualifying Time | AA1: Average Speed kph | AB1: Shootout Position | AC1: Shootout Time | AD1: Average Speed kph | AE1: Position Improvement | AF1: DNF Reason | AG1: Laps | AH1: Race Time | AI1: Average Speed kph | AJ1: Difference | AK1: Fastest Lap Time | AL1: Average Speed kph | AM1: On Lap | AN1: Position Improvement | AO1: Remarks | AP1: Photo File Name
A2: 22240 | B2: Armstrong 500 | C2: 1 | D2: D | E2: 1 | F2: 37 | G2: S. A. Chenery P/L | I2: Vauxhall Cresta | K2: Frank Coad | L2: AUS | M2: =_xlfn.LET(_xlpm.d,_xlfn.XLOOKUP(K2,'[1]Birth Dates'!$A:$A,'[1]Birth Dates'!$B:$B,"",0),IF(_xlpm.d=0,"",_xlpm.d)) | N2: =IF(OR(M2="",A2="",NOT(ISNUMBER(M2)),M2>A2),"",DATEDIF(M2,A2,"Y")&" years, "&DATEDIF(M2,A2,"YM")&" months, "&DATEDIF(M2,A2,"MD")&" days") | O2: John Roxburgh | P2: AUS | Q2: =_xlfn.LET(_xlpm.d,_xlfn.XLOOKUP(O2,'[1]Birth Dates'!$A:$A,'[1]Birth Dates'!$B:$B,"",0),IF(_xlpm.d=0,"",_xlpm.d)) | R2: =IF(OR(Q2="",A2="",NOT(ISNUMBER(Q2)),Q2>A2),"",DATEDIF(Q2,A2,"Y")&" years, "&DATEDIF(Q2,A2,"YM")&" months, "&DATEDIF(Q2,A2,"MD")&" days") | U2: =_xlfn.LET(_xlpm.d,_xlfn.XLOOKUP(S2,'[1]Birth Dates'!$A:$A,'[1]Birth Dates'!$B:$B,"",0),IF(_xlpm.d=0,"",_xlpm.d)) | Z2: 0 | AA2: =IF(OR(Y2="",Z2="",Z2=0),"",Y2*4.828/(Z2*24)) | AD2: =IF(OR(AB2="",AC2="",AC2=0),"",AB2*4.828/(AC2*24)) | AE2: =IF(OR(NOT(ISNUMBER(C1)),NOT(ISNUMBER(N2))),"",IF(S2<>"",S2,N2)-C1) | AG2: 167 | AH2: 0.34767477 | AI2: =IF(OR(AG2="",AH2="",AH2=0),"",AG2*4.828/(AH2*24)) | AL2: =IF(OR(AK2="",AK2="",AK2=0),"",4.828/(AK2*24)) | AN2: =IF(OR(NOT(ISNUMBER(C2)),NOT(ISNUMBER(W2))),"",IF(AB2<>"",AB2,W2)-C2) | AP2: =IF($B2="","",TEXT($A2,"yyyymmdd")&"_P"&$C2&"_C"&$F2&"_"&TRIM(RIGHT(SUBSTITUTE(TRIM(SUBSTITUTE($K2,CHAR(160)," "))," ",REPT(" ",60)),60))&IF($O2="","","-"&TRIM(RIGHT(SUBSTITUTE(TRIM(SUBSTITUTE($O2,CHAR(160)," "))," ",REPT(" ",60)),60)))&IF($S2="","","-"&TRIM(RIGHT(SUBSTITUTE(TRIM(SUBSTITUTE($S2,CHAR(160)," "))," ",REPT(" ",60)),60)))&".jpg")
A3: 22240 | B3: Armstrong 500 | C3: 2 | D3: C | E3: 1 | F3: 34 | G3: Continental & General Dist. P/L | I3: Peugeot 403 | K3: Geoff Russell(1) | L3: AUS | M3: =_xlfn.LET(_xlpm.d,_xlfn.XLOOKUP(K3,'[1]Birth Dates'!$A:$A,'[1]Birth Dates'!$B:$B,"",0),IF(_xlpm.d=0,"",_xlpm.d)) | N3: =IF(OR(M3="",A3="",NOT(ISNUMBER(M3)),M3>A3),"",DATEDIF(M3,A3,"Y")&" years, "&DATEDIF(M3,A3,"YM")&" months, "&DATEDIF(M3,A3,"MD")&" days") | O3: David Anderson | Q3: =_xlfn.LET(_xlpm.d,_xlfn.XLOOKUP(O3,'[1]Birth Dates'!$A:$A,'[1]Birth Dates'!$B:$B,"",0),IF(_xlpm.d=0,"",_xlpm.d)) | R3: =IF(OR(Q3="",A3="",NOT(ISNUMBER(Q3)),Q3>A3),"",DATEDIF(Q3,A3,"Y")&" years, "&DATEDIF(Q3,A3,"YM")&" months, "&DATEDIF(Q3,A3,"MD")&" days") | S3: Tony Loxton | U3: =_xlfn.LET(_xlpm.d,_xlfn.XLOOKUP(S3,'[1]Birth Dates'!$A:$A,'[1]Birth Dates'!$B:$B,"",0),IF(_xlpm.d=0,"",_xlpm.d)) | V3: =IF(OR(U3="",A3="",NOT(ISNUMBER(U3)),U3>A3),"",DATEDIF(U3,A3,"Y")&" years, "&DATEDIF(U3,A3,"YM")&" months, "&DATEDIF(U3,A3,"MD")&" days") | Z3: 0 | AA3: =IF(OR(Y3="",Z3="",Z3=0),"",Y3*4.828/(Z3*24)) | AD3: =IF(OR(AB3="",AC3="",AC3=0),"",AB3*4.828/(AC3*24)) | AE3: =IF(OR(NOT(ISNUMBER(C2)),NOT(ISNUMBER(N3))),"",IF(S3<>"",S3,N3)-C2) | AG3: 167 | AH3: 8:19:99.1 am | AI3: =IF(OR(AG3="",AH3="",AH3=0),"",AG3*4.828/(AH3*24)) | AL3: =IF(OR(AK3="",AK3="",AK3=0),"",4.828/(AK3*24)) | AN3: =IF(OR(NOT(ISNUMBER(C3)),NOT(ISNUMBER(W3))),"",IF(AB3<>"",AB3,W3)-C3) | AP3: =IF($B3="","",TEXT($A3,"yyyymmdd")&"_P"&$C3&"_C"&$F3&"_"&TRIM(RIGHT(SUBSTITUTE(TRIM(SUBSTITUTE($K3,CHAR(160)," "))," ",REPT(" ",60)),60))&IF($O3="","","-"&TRIM(RIGHT(SUBSTITUTE(TRIM(SUBSTITUTE($O3,CHAR(160)," "))," ",REPT(" ",60)),60)))&IF($S3="","","-"&TRIM(RIGHT(SUBSTITUTE(TRIM(SUBSTITUTE($S3,CHAR(160)," "))," ",REPT(" ",60)),60)))&".jpg")
A4: 22240 | B4: Armstrong 500 | C4: 3 | D4: B | E4: 1 | F4: 24 | G4: Melody Motors P/L | I4: Simca Aronde | K4: Doug Stewart | L4: AUS | M4: =_xlfn.LET(_xlpm.d,_xlfn.XLOOKUP(K4,'[1]Birth Dates'!$A:$A,'[1]Birth Dates'!$B:$B,"",0),IF(_xlpm.d=0,"",_xlpm.d)) | N4: =IF(OR(M4="",A4="",NOT(ISNUMBER(M4)),M4>A4),"",DATEDIF(M4,A4,"Y")&" years, "&DATEDIF(M4,A4,"YM")&" months, "&DATEDIF(M4,A4,"MD")&" days") | O4: Murray Galt | Q4: =_xlfn.LET(_xlpm.d,_xlfn.XLOOKUP(O4,'[1]Birth Dates'!$A:$A,'[1]Birth Dates'!$B:$B,"",0),IF(_xlpm.d=0,"",_xlpm.d)) | R4: =IF(OR(Q4="",A4="",NOT(ISNUMBER(Q4)),Q4>A4),"",DATEDIF(Q4,A4,"Y")&" years, "&DATEDIF(Q4,A4,"YM")&" months, "&DATEDIF(Q4,A4,"MD")&" days") | S4: Bill Murray | U4: =_xlfn.LET(_xlpm.d,_xlfn.XLOOKUP(S4,'[1]Birth Dates'!$A:$A,'[1]Birth Dates'!$B:$B,"",0),IF(_xlpm.d=0,"",_xlpm.d)) | V4: =IF(OR(U4="",A4="",NOT(ISNUMBER(U4)),U4>A4),"",DATEDIF(U4,A4,"Y")&" years, "&DATEDIF(U4,A4,"YM")&" months, "&DATEDIF(U4,A4,"MD")&" days") | Z4: 0 | AA4: =IF(OR(Y4="",Z4="",Z4=0),"",Y4*4.828/(Z4*24)) | AD4: =IF(OR(AB4="",AC4="",AC4=0),"",AB4*4.828/(AC4*24)) | AE4: =IF(OR(NOT(ISNUMBER(C3)),NOT(ISNUMBER(N4))),"",IF(S4<>"",S4,N4)-C3) | AG4: 162 | AI4: =IF(OR(AG4="",AH4="",AH4=0),"",AG4*4.828/(AH4*24)) | AL4: =IF(OR(AK4="",AK4="",AK4=0),"",4.828/(AK4*24)) | AN4: =IF(OR(NOT(ISNUMBER(C4)),NOT(ISNUMBER(W4))),"",IF(AB4<>"",AB4,W4)-C4) | AP4: =IF($B4="","",TEXT($A4,"yyyymmdd")&"_P"&$C4&"_C"&$F4&"_"&TRIM(RIGHT(SUBSTITUTE(TRIM(SUBSTITUTE($K4,CHAR(160)," "))," ",REPT(" ",60)),60))&IF($O4="","","-"&TRIM(RIGHT(SUBSTITUTE(TRIM(SUBSTITUTE($O4,CHAR(160)," "))," ",REPT(" ",60)),60)))&IF($S4="","","-"&TRIM(RIGHT(SUBSTITUTE(TRIM(SUBSTITUTE($S4,CHAR(160)," "))," ",REPT(" ",60)),60)))&".jpg")
A5: 22240 | B5: Armstrong 500 | C5: 4 | D5: C | E5: 2 | F5: 41 | G5: British Motor Corp. | I5: Morris Major | K5: Peter Manton | L5: AUS | M5: =_xlfn.LET(_xlpm.d,_xlfn.XLOOKUP(K5,'[1]Birth Dates'!$A:$A,'[1]Birth Dates'!$B:$B,"",0),IF(_xlpm.d=0,"",_xlpm.d)) | N5: =IF(OR(M5="",A5="",NOT(ISNUMBER(M5)),M5>A5),"",DATEDIF(M5,A5,"Y")&" years, "&DATEDIF(M5,A5,"YM")&" months, "&DATEDIF(M5,A5,"MD")&" days") | O5: Barry Topen | Q5: =_xlfn.LET(_xlpm.d,_xlfn.XLOOKUP(O5,'[1]Birth Dates'!$A:$A,'[1]Birth Dates'!$B:$B,"",0),IF(_xlpm.d=0,"",_xlpm.d)) | R5: =IF(OR(Q5="",A5="",NOT(ISNUMBER(Q5)),Q5>A5),"",DATEDIF(Q5,A5,"Y")&" years, "&DATEDIF(Q5,A5,"YM")&" months, "&DATEDIF(Q5,A5,"MD")&" days") | U5: =_xlfn.LET(_xlpm.d,_xlfn.XLOOKUP(S5,'[1]Birth Dates'!$A:$A,'[1]Birth Dates'!$B:$B,"",0),IF(_xlpm.d=0,"",_xlpm.d)) | V5: =IF(OR(U5="",A5="",NOT(ISNUMBER(U5)),U5>A5),"",DATEDIF(U5,A5,"Y")&" years, "&DATEDIF(U5,A5,"YM")&" months, "&DATEDIF(U5,A5,"MD")&" days") | Z5: 0 | AA5: =IF(OR(Y5="",Z5="",Z5=0),"",Y5*4.828/(Z5*24)) | AD5: =IF(OR(AB5="",AC5="",AC5=0),"",AB5*4.828/(AC5*24)) | AE5: =IF(OR(NOT(ISNUMBER(C4)),NOT(ISNUMBER(N5))),"",IF(S5<>"",S5,N5)-C4) | AG5: 162 | AI5: =IF(OR(AG5="",AH5="",AH5=0),"",AG5*4.828/(AH5*24)) | AL5: =IF(OR(AK5="",AK5="",AK5=0),"",4.828/(AK5*24)) | AN5: =IF(OR(NOT(ISNUMBER(C5)),NOT(ISNUMBER(W5))),"",IF(AB5<>"",AB5,W5)-C5) | AP5: =IF($B5="","",TEXT($A5,"yyyymmdd")&"_P"&$C5&"_C"&$F5&"_"&TRIM(RIGHT(SUBSTITUTE(TRIM(SUBSTITUTE($K5,CHAR(160)," "))," ",REPT(" ",60)),60))&IF($O5="","","-"&TRIM(RIGHT(SUBSTITUTE(TRIM(SUBSTITUTE($O5,CHAR(160)," "))," ",REPT(" ",60)),60)))&IF($S5="","","-"&TRIM(RIGHT(SUBSTITUTE(TRIM(SUBSTITUTE($S5,CHAR(160)," "))," ",REPT(" ",60)),60)))&".jpg")
A6: 22240 | B6: Armstrong 500 | C6: 5 | D6: C | E6: 3 | F6: 38 | G6: British Motor Corp. | I6: Austin Lancer | K6: George Spanos | M6: =_xlfn.LET(_xlpm.d,_xlfn.XLOOKUP(K6,'[1]Birth Dates'!$A:$A,'[1]Birth Dates'!$B:$B,"",0),IF(_xlpm.d=0,"",_xlpm.d)) | N6: =IF(OR(M6="",A6="",NOT(ISNUMBER(M6)),M6>A6),"",DATEDIF(M6,A6,"Y")&" years, "&DATEDIF(M6,A6,"YM")&" months, "&DATEDIF(M6,A6,"MD")&" days") | O6: Leo Taylor | Q6: =_xlfn.LET(_xlpm.d,_xlfn.XLOOKUP(O6,'[1]Birth Dates'!$A:$A,'[1]Birth Dates'!$B:$B,"",0),IF(_xlpm.d=0,"",_xlpm.d)) | R6: =IF(OR(Q6="",A6="",NOT(ISNUMBER(Q6)),Q6>A6),"",DATEDIF(Q6,A6,"Y")&" years, "&DATEDIF(Q6,A6,"YM")&" months, "&DATEDIF(Q6,A6,"MD")&" days") | U6: =_xlfn.LET(_xlpm.d,_xlfn.XLOOKUP(S6,'[1]Birth Dates'!$A:$A,'[1]Birth Dates'!$B:$B,"",0),IF(_xlpm.d=0,"",_xlpm.d)) | V6: =IF(OR(U6="",A6="",NOT(ISNUMBER(U6)),U6>A6),"",DATEDIF(U6,A6,"Y")&" years, "&DATEDIF(U6,A6,"YM")&" months, "&DATEDIF(U6,A6,"MD")&" days") | Z6: 0 | AA6: =IF(OR(Y6="",Z6="",Z6=0),"",Y6*4.828/(Z6*24)) | AD6: =IF(OR(AB6="",AC6="",AC6=0),"",AB6*4.828/(AC6*24)) | AE6: =IF(OR(NOT(ISNUMBER(C5)),NOT(ISNUMBER(N6))),"",IF(S6<>"",S6,N6)-C5) | AG6: 161 | AI6: =IF(OR(AG6="",AH6="",AH6=0),"",AG6*4.828/(AH6*24)) | AL6: =IF(OR(AK6="",AK6="",AK6=0),"",4.828/(AK6*24)) | AN6: =IF(OR(NOT(ISNUMBER(C6)),NOT(ISNUMBER(W6))),"",IF(AB6<>"",AB6,W6)-C6) | AP6: =IF($B6="","",TEXT($A6,"yyyymmdd")&"_P"&$C6&"_C"&$F6&"_"&TRIM(RIGHT(SUBSTITUTE(TRIM(SUBSTITUTE($K6,CHAR(160)," "))," ",REPT(" ",60)),60))&IF($O6="","","-"&TRIM(RIGHT(SUBSTITUTE(TRIM(SUBSTITUTE($O6,CHAR(160)," "))," ",REPT(" ",60)),60)))&IF($S6="","","-"&TRIM(RIGHT(SUBSTITUTE(TRIM(SUBSTITUTE($S6,CHAR(160)," "))," ",REPT(" ",60)),60)))&".jpg")
A7: 22240 | B7: Armstrong 500 | C7: 6 | D7: B | E7: 2 | F7: 23 | G7: Chrysler Australia Ltd. (Eiffel Tower Group) | I7: Simca Aronde | K7: Jack Nougher | L7: AUS | M7: =_xlfn.LET(_xlpm.d,_xlfn.XLOOKUP(K7,'[1]Birth Dates'!$A:$A,'[1]Birth Dates'!$B:$B,"",0),IF(_xlpm.d=0,"",_xlpm.d)) | N7: =IF(OR(M7="",A7="",NOT(ISNUMBER(M7)),M7>A7),"",DATEDIF(M7,A7,"Y")&" years, "&DATEDIF(M7,A7,"YM")&" months, "&DATEDIF(M7,A7,"MD")&" days") | O7: Lionel Marsh | Q7: =_xlfn.LET(_xlpm.d,_xlfn.XLOOKUP(O7,'[1]Birth Dates'!$A:$A,'[1]Birth Dates'!$B:$B,"",0),IF(_xlpm.d=0,"",_xlpm.d)) | R7: =IF(OR(Q7="",A7="",NOT(ISNUMBER(Q7)),Q7>A7),"",DATEDIF(Q7,A7,"Y")&" years, "&DATEDIF(Q7,A7,"YM")&" months, "&DATEDIF(Q7,A7,"MD")&" days") | U7: =_xlfn.LET(_xlpm.d,_xlfn.XLOOKUP(S7,'[1]Birth Dates'!$A:$A,'[1]Birth Dates'!$B:$B,"",0),IF(_xlpm.d=0,"",_xlpm.d)) | V7: =IF(OR(U7="",A7="",NOT(ISNUMBER(U7)),U7>A7),"",DATEDIF(U7,A7,"Y")&" years, "&DATEDIF(U7,A7,"YM")&" months, "&DATEDIF(U7,A7,"MD")&" days") | Z7: 0 | AA7: =IF(OR(Y7="",Z7="",Z7=0),"",Y7*4.828/(Z7*24)) | AD7: =IF(OR(AB7="",AC7="",AC7=0),"",AB7*4.828/(AC7*24)) | AE7: =IF(OR(NOT(ISNUMBER(C6)),NOT(ISNUMBER(N7))),"",IF(S7<>"",S7,N7)-C6) | AG7: 160 | AI7: =IF(OR(AG7="",AH7="",AH7=0),"",AG7*4.828/(AH7*24)) | AL7: =IF(OR(AK7="",AK7="",AK7=0),"",4.828/(AK7*24)) | AN7: =IF(OR(NOT(ISNUMBER(C7)),NOT(ISNUMBER(W7))),"",IF(AB7<>"",AB7,W7)-C7) | AP7: =IF($B7="","",TEXT($A7,"yyyymmdd")&"_P"&$C7&"_C"&$F7&"_"&TRIM(RIGHT(SUBSTITUTE(TRIM(SUBSTITUTE($K7,CHAR(160)," "))," ",REPT(" ",60)),60))&IF($O7="","","-"&TRIM(RIGHT(SUBSTITUTE(TRIM(SUBSTITUTE($O7,CHAR(160)," "))," ",REPT(" ",60)),60)))&IF($S7="","","-"&TRIM(RIGHT(SUBSTITUTE(TRIM(SUBSTITUTE($S7,CHAR(160)," "))," ",REPT(" ",60)),60)))&".jpg")
A8: 22240 | B8: Armstrong 500 | C8: 7 | D8: D | E8: 2 | F8: 28 | G8: Australian Motor Industries | I8: Standard Vanguard | K8: Jack (John) French | L8: AUS | M8: =_xlfn.LET(_xlpm.d,_xlfn.XLOOKUP(K8,'[1]Birth Dates'!$A:$A,'[1]Birth Dates'!$B:$B,"",0),IF(_xlpm.d=0,"",_xlpm.d)) | N8: =IF(OR(M8="",A8="",NOT(ISNUMBER(M8)),M8>A8),"",DATEDIF(M8,A8,"Y")&" years, "&DATEDIF(M8,A8,"YM")&" months, "&DATEDIF(M8,A8,"MD")&" days") | O8: Norm Beechey | P8: AUS | Q8: =_xlfn.LET(_xlpm.d,_xlfn.XLOOKUP(O8,'[1]Birth Dates'!$A:$A,'[1]Birth Dates'!$B:$B,"",0),IF(_xlpm.d=0,"",_xlpm.d)) | R8: =IF(OR(Q8="",A8="",NOT(ISNUMBER(Q8)),Q8>A8),"",DATEDIF(Q8,A8,"Y")&" years, "&DATEDIF(Q8,A8,"YM")&" months, "&DATEDIF(Q8,A8,"MD")&" days") | U8: =_xlfn.LET(_xlpm.d,_xlfn.XLOOKUP(S8,'[1]Birth Dates'!$A:$A,'[1]Birth Dates'!$B:$B,"",0),IF(_xlpm.d=0,"",_xlpm.d)) | V8: =IF(OR(U8="",A8="",NOT(ISNUMBER(U8)),U8>A8),"",DATEDIF(U8,A8,"Y")&" years, "&DATEDIF(U8,A8,"YM")&" months, "&DATEDIF(U8,A8,"MD")&" days") | Z8: 0 | AA8: =IF(OR(Y8="",Z8="",Z8=0),"",Y8*4.828/(Z8*24)) | AD8: =IF(OR(AB8="",AC8="",AC8=0),"",AB8*4.828/(AC8*24)) | AE8: =IF(OR(NOT(ISNUMBER(C7)),NOT(ISNUMBER(N8))),"",IF(S8<>"",S8,N8)-C7) | AG8: 160 | AI8: =IF(OR(AG8="",AH8="",AH8=0),"",AG8*4.828/(AH8*24)) | AL8: =IF(OR(AK8="",AK8="",AK8=0),"",4.828/(AK8*24)) | AN8: =IF(OR(NOT(ISNUMBER(C8)),NOT(ISNUMBER(W8))),"",IF(AB8<>"",AB8,W8)-C8) | AP8: =IF($B8="","",TEXT($A8,"yyyymmdd")&"_P"&$C8&"_C"&$F8&"_"&TRIM(RIGHT(SUBSTITUTE(TRIM(SUBSTITUTE($K8,CHAR(160)," "))," ",REPT(" ",60)),60))&IF($O8="","","-"&TRIM(RIGHT(SUBSTITUTE(TRIM(SUBSTITUTE($O8,CHAR(160)," "))," ",REPT(" ",60)),60)))&IF($S8="","","-"&TRIM(RIGHT(SUBSTITUTE(TRIM(SUBSTITUTE($S8,CHAR(160)," "))," ",REPT(" ",60)),60)))&".jpg")
A9: 22240 | B9: Armstrong 500 | C9: 8 | D9: C | E9: 4 | F9: 35 | G9: Continental & General Dist. P/L | I9: Peugeot 403 | K9: Bob Holden | L9: AUS | M9: =_xlfn.LET(_xlpm.d,_xlfn.XLOOKUP(K9,'[1]Birth Dates'!$A:$A,'[1]Birth Dates'!$B:$B,"",0),IF(_xlpm.d=0,"",_xlpm.d)) | N9: =IF(OR(M9="",A9="",NOT(ISNUMBER(M9)),M9>A9),"",DATEDIF(M9,A9,"Y")&" years, "&DATEDIF(M9,A9,"YM")&" months, "&DATEDIF(M9,A9,"MD")&" days") | O9: Ken Brigden | P9: AUS | Q9: =_xlfn.LET(_xlpm.d,_xlfn.XLOOKUP(O9,'[1]Birth Dates'!$A:$A,'[1]Birth Dates'!$B:$B,"",0),IF(_xlpm.d=0,"",_xlpm.d)) | R9: =IF(OR(Q9="",A9="",NOT(ISNUMBER(Q9)),Q9>A9),"",DATEDIF(Q9,A9,"Y")&" years, "&DATEDIF(Q9,A9,"YM")&" months, "&DATEDIF(Q9,A9,"MD")&" days") | U9: =_xlfn.LET(_xlpm.d,_xlfn.XLOOKUP(S9,'[1]Birth Dates'!$A:$A,'[1]Birth Dates'!$B:$B,"",0),IF(_xlpm.d=0,"",_xlpm.d)) | V9: =IF(OR(U9="",A9="",NOT(ISNUMBER(U9)),U9>A9),"",DATEDIF(U9,A9,"Y")&" years, "&DATEDIF(U9,A9,"YM")&" months, "&DATEDIF(U9,A9,"MD")&" days") | Z9: 0 | AA9: =IF(OR(Y9="",Z9="",Z9=0),"",Y9*4.828/(Z9*24)) | AD9: =IF(OR(AB9="",AC9="",AC9=0),"",AB9*4.828/(AC9*24)) | AE9: =IF(OR(NOT(ISNUMBER(C8)),NOT(ISNUMBER(N9))),"",IF(S9<>"",S9,N9)-C8) | AG9: 160 | AI9: =IF(OR(AG9="",AH9="",AH9=0),"",AG9*4.828/(AH9*24)) | AL9: =IF(OR(AK9="",AK9="",AK9=0),"",4.828/(AK9*24)) | AN9: =IF(OR(NOT(ISNUMBER(C9)),NOT(ISNUMBER(W9))),"",IF(AB9<>"",AB9,W9)-C9) | AP9: =IF($B9="","",TEXT($A9,"yyyymmdd")&"_P"&$C9&"_C"&$F9&"_"&TRIM(RIGHT(SUBSTITUTE(TRIM(SUBSTITUTE($K9,CHAR(160)," "))," ",REPT(" ",60)),60))&IF($O9="","","-"&TRIM(RIGHT(SUBSTITUTE(TRIM(SUBSTITUTE($O9,CHAR(160)," "))," ",REPT(" ",60)),60)))&IF($S9="","","-"&TRIM(RIGHT(SUBSTITUTE(TRIM(SUBSTITUTE($S9,CHAR(160)," "))," ",REPT(" ",60)),60)))&".jpg")
A10: 22240 | B10: Armstrong 500 | C10: 9 | D10: C | E10: 5 | F10: 42 | G10: British Motor Corp. | I10: Morris Major | K10: Brian Muir | L10: AUS | M10: =_xlfn.LET(_xlpm.d,_xlfn.XLOOKUP(K10,'[1]Birth Dates'!$A:$A,'[1]Birth Dates'!$B:$B,"",0),IF(_xlpm.d=0,"",_xlpm.d)) | N10: =IF(OR(M10="",A10="",NOT(ISNUMBER(M10)),M10>A10),"",DATEDIF(M10,A10,"Y")&" years, "&DATEDIF(M10,A10,"YM")&" months, "&DATEDIF(M10,A10,"MD")&" days") | O10: Jim Smith | P10: AUS | Q10: =_xlfn.LET(_xlpm.d,_xlfn.XLOOKUP(O10,'[1]Birth Dates'!$A:$A,'[1]Birth Dates'!$B:$B,"",0),IF(_xlpm.d=0,"",_xlpm.d)) | R10: =IF(OR(Q10="",A10="",NOT(ISNUMBER(Q10)),Q10>A10),"",DATEDIF(Q10,A10,"Y")&" years, "&DATEDIF(Q10,A10,"YM")&" months, "&DATEDIF(Q10,A10,"MD")&" days") | U10: =_xlfn.LET(_xlpm.d,_xlfn.XLOOKUP(S10,'[1]Birth Dates'!$A:$A,'[1]Birth Dates'!$B:$B,"",0),IF(_xlpm.d=0,"",_xlpm.d)) | V10: =IF(OR(U10="",A10="",NOT(ISNUMBER(U10)),U10>A10),"",DATEDIF(U10,A10,"Y")&" years, "&DATEDIF(U10,A10,"YM")&" months, "&DATEDIF(U10,A10,"MD")&" days") | Z10: 0 | AA10: =IF(OR(Y10="",Z10="",Z10=0),"",Y10*4.828/(Z10*24)) | AD10: =IF(OR(AB10="",AC10="",AC10=0),"",AB10*4.828/(AC10*24)) | AE10: =IF(OR(NOT(ISNUMBER(C9)),NOT(ISNUMBER(N10))),"",IF(S10<>"",S10,N10)-C9) | AG10: 160 | AI10: =IF(OR(AG10="",AH10="",AH10=0),"",AG10*4.828/(AH10*24)) | AL10: =IF(OR(AK10="",AK10="",AK10=0),"",4.828/(AK10*24)) | AN10: =IF(OR(NOT(ISNUMBER(C10)),NOT(ISNUMBER(W10))),"",IF(AB10<>"",AB10,W10)-C10) | AP10: =IF($B10="","",TEXT($A10,"yyyymmdd")&"_P"&$C10&"_C"&$F10&"_"&TRIM(RIGHT(SUBSTITUTE(TRIM(SUBSTITUTE($K10,CHAR(160)," "))," ",REPT(" ",60)),60))&IF($O10="","","-"&TRIM(RIGHT(SUBSTITUTE(TRIM(SUBSTITUTE($O10,CHAR(160)," "))," ",REPT(" ",60)),60)))&IF($S10="","","-"&TRIM(RIGHT(SUBSTITUTE(TRIM(SUBSTITUTE($S10,CHAR(160)," "))," ",REPT(" ",60)),60)))&".jpg")
A11: 22240 | B11: Armstrong 500 | C11: 10 | D11: B | E11: 3 | F11: 22 | G11: Chrysler Australia Ltd. (B.J. Autos Service) | I11: Simca Aronde | K11: Bob Brown | M11: =_xlfn.LET(_xlpm.d,_xlfn.XLOOKUP(K11,'[1]Birth Dates'!$A:$A,'[1]Birth Dates'!$B:$B,"",0),IF(_xlpm.d=0,"",_xlpm.d)) | N11: =IF(OR(M11="",A11="",NOT(ISNUMBER(M11)),M11>A11),"",DATEDIF(M11,A11,"Y")&" years, "&DATEDIF(M11,A11,"YM")&" months, "&DATEDIF(M11,A11,"MD")&" days") | O11: Michael Lempriere | Q11: =_xlfn.LET(_xlpm.d,_xlfn.XLOOKUP(O11,'[1]Birth Dates'!$A:$A,'[1]Birth Dates'!$B:$B,"",0),IF(_xlpm.d=0,"",_xlpm.d)) | R11: =IF(OR(Q11="",A11="",NOT(ISNUMBER(Q11)),Q11>A11),"",DATEDIF(Q11,A11,"Y")&" years, "&DATEDIF(Q11,A11,"YM")&" months, "&DATEDIF(Q11,A11,"MD")&" days") | U11: =_xlfn.LET(_xlpm.d,_xlfn.XLOOKUP(S11,'[1]Birth Dates'!$A:$A,'[1]Birth Dates'!$B:$B,"",0),IF(_xlpm.d=0,"",_xlpm.d)) | V11: =IF(OR(U11="",A11="",NOT(ISNUMBER(U11)),U11>A11),"",DATEDIF(U11,A11,"Y")&" years, "&DATEDIF(U11,A11,"YM")&" months, "&DATEDIF(U11,A11,"MD")&" days") | Z11: 0 | AA11: =IF(OR(Y11="",Z11="",Z11=0),"",Y11*4.828/(Z11*24)) | AD11: =IF(OR(AB11="",AC11="",AC11=0),"",AB11*4.828/(AC11*24)) | AE11: =IF(OR(NOT(ISNUMBER(C10)),NOT(ISNUMBER(N11))),"",IF(S11<>"",S11,N11)-C10) | AG11: 160 | AI11: =IF(OR(AG11="",AH11="",AH11=0),"",AG11*4.828/(AH11*24)) | AL11: =IF(OR(AK11="",AK11="",AK11=0),"",4.828/(AK11*24)) | AN11: =IF(OR(NOT(ISNUMBER(C11)),NOT(ISNUMBER(W11))),"",IF(AB11<>"",AB11,W11)-C11) | AP11: =IF($B11="","",TEXT($A11,"yyyymmdd")&"_P"&$C11&"_C"&$F11&"_"&TRIM(RIGHT(SUBSTITUTE(TRIM(SUBSTITUTE($K11,CHAR(160)," "))," ",REPT(" ",60)),60))&IF($O11="","","-"&TRIM(RIGHT(SUBSTITUTE(TRIM(SUBSTITUTE($O11,CHAR(160)," "))," ",REPT(" ",60)),60)))&IF($S11="","","-"&TRIM(RIGHT(SUBSTITUTE(TRIM(SUBSTITUTE($S11,CHAR(160)," "))," ",REPT(" ",60)),60)))&".jpg")
A12: 22240 | B12: Armstrong 500 | C12: 11 | D12: C | E12: 6 | F12: 43 | G12: British Motor Corp. | I12: Morris Major | K12: Rod Murphy | M12: =_xlfn.LET(_xlpm.d,_xlfn.XLOOKUP(K12,'[1]Birth Dates'!$A:$A,'[1]Birth Dates'!$B:$B,"",0),IF(_xlpm.d=0,"",_xlpm.d)) | N12: =IF(OR(M12="",A12="",NOT(ISNUMBER(M12)),M12>A12),"",DATEDIF(M12,A12,"Y")&" years, "&DATEDIF(M12,A12,"YM")&" months, "&DATEDIF(M12,A12,"MD")&" days") | O12: John Calloway | Q12: =_xlfn.LET(_xlpm.d,_xlfn.XLOOKUP(O12,'[1]Birth Dates'!$A:$A,'[1]Birth Dates'!$B:$B,"",0),IF(_xlpm.d=0,"",_xlpm.d)) | R12: =IF(OR(Q12="",A12="",NOT(ISNUMBER(Q12)),Q12>A12),"",DATEDIF(Q12,A12,"Y")&" years, "&DATEDIF(Q12,A12,"YM")&" months, "&DATEDIF(Q12,A12,"MD")&" days") | U12: =_xlfn.LET(_xlpm.d,_xlfn.XLOOKUP(S12,'[1]Birth Dates'!$A:$A,'[1]Birth Dates'!$B:$B,"",0),IF(_xlpm.d=0,"",_xlpm.d)) | V12: =IF(OR(U12="",A12="",NOT(ISNUMBER(U12)),U12>A12),"",DATEDIF(U12,A12,"Y")&" years, "&DATEDIF(U12,A12,"YM")&" months, "&DATEDIF(U12,A12,"MD")&" days") | Z12: 0 | AA12: =IF(OR(Y12="",Z12="",Z12=0),"",Y12*4.828/(Z12*24)) | AD12: =IF(OR(AB12="",AC12="",AC12=0),"",AB12*4.828/(AC12*24)) | AE12: =IF(OR(NOT(ISNUMBER(C11)),NOT(ISNUMBER(N12))),"",IF(S12<>"",S12,N12)-C11) | AG12: 159 | AI12: =IF(OR(AG12="",AH12="",AH12=0),"",AG12*4.828/(AH12*24)) | AL12: =IF(OR(AK12="",AK12="",AK12=0),"",4.828/(AK12*24)) | AN12: =IF(OR(NOT(ISNUMBER(C12)),NOT(ISNUMBER(W12))),"",IF(AB12<>"",AB12,W12)-C12) | AP12: =IF($B12="","",TEXT($A12,"yyyymmdd")&"_P"&$C12&"_C"&$F12&"_"&TRIM(RIGHT(SUBSTITUTE(TRIM(SUBSTITUTE($K12,CHAR(160)," "))," ",REPT(" ",60)),60))&IF($O12="","","-"&TRIM(RIGHT(SUBSTITUTE(TRIM(SUBSTITUTE($O12,CHAR(160)," "))," ",REPT(" ",60)),60)))&IF($S12="","","-"&TRIM(RIGHT(SUBSTITUTE(TRIM(SUBSTITUTE($S12,CHAR(160)," "))," ",REPT(" ",60)),60)))&".jpg")
A13: 22240 | B13: Armstrong 500 | C13: 12 | D13: C | E13: 7 | F13: 45 | G13: Rootes (Aust) Limited | I13: Singer Gazelle | K13: Harry Firth | L13: AUS | M13: =_xlfn.LET(_xlpm.d,_xlfn.XLOOKUP(K13,'[1]Birth Dates'!$A:$A,'[1]Birth Dates'!$B:$B,"",0),IF(_xlpm.d=0,"",_xlpm.d)) | N13: =IF(OR(M13="",A13="",NOT(ISNUMBER(M13)),M13>A13),"",DATEDIF(M13,A13,"Y")&" years, "&DATEDIF(M13,A13,"YM")&" months, "&DATEDIF(M13,A13,"MD")&" days") | O13: John Reaburn | P13: AUS | Q13: =_xlfn.LET(_xlpm.d,_xlfn.XLOOKUP(O13,'[1]Birth Dates'!$A:$A,'[1]Birth Dates'!$B:$B,"",0),IF(_xlpm.d=0,"",_xlpm.d)) | R13: =IF(OR(Q13="",A13="",NOT(ISNUMBER(Q13)),Q13>A13),"",DATEDIF(Q13,A13,"Y")&" years, "&DATEDIF(Q13,A13,"YM")&" months, "&DATEDIF(Q13,A13,"MD")&" days") | U13: =_xlfn.LET(_xlpm.d,_xlfn.XLOOKUP(S13,'[1]Birth Dates'!$A:$A,'[1]Birth Dates'!$B:$B,"",0),IF(_xlpm.d=0,"",_xlpm.d)) | V13: =IF(OR(U13="",A13="",NOT(ISNUMBER(U13)),U13>A13),"",DATEDIF(U13,A13,"Y")&" years, "&DATEDIF(U13,A13,"YM")&" months, "&DATEDIF(U13,A13,"MD")&" days") | Z13: 0 | AA13: =IF(OR(Y13="",Z13="",Z13=0),"",Y13*4.828/(Z13*24)) | AD13: =IF(OR(AB13="",AC13="",AC13=0),"",AB13*4.828/(AC13*24)) | AE13: =IF(OR(NOT(ISNUMBER(C12)),NOT(ISNUMBER(N13))),"",IF(S13<>"",S13,N13)-C12) | AG13: 159 | AI13: =IF(OR(AG13="",AH13="",AH13=0),"",AG13*4.828/(AH13*24)) | AL13: =IF(OR(AK13="",AK13="",AK13=0),"",4.828/(AK13*24)) | AN13: =IF(OR(NOT(ISNUMBER(C13)),NOT(ISNUMBER(W13))),"",IF(AB13<>"",AB13,W13)-C13) | AP13: =IF($B13="","",TEXT($A13,"yyyymmdd")&"_P"&$C13&"_C"&$F13&"_"&TRIM(RIGHT(SUBSTITUTE(TRIM(SUBSTITUTE($K13,CHAR(160)," "))," ",REPT(" ",60)),60))&IF($O13="","","-"&TRIM(RIGHT(SUBSTITUTE(TRIM(SUBSTITUTE($O13,CHAR(160)," "))," ",REPT(" ",60)),60)))&IF($S13="","","-"&TRIM(RIGHT(SUBSTITUTE(TRIM(SUBSTITUTE($S13,CHAR(160)," "))," ",REPT(" ",60)),60)))&".jpg")
A14: 22240 | B14: Armstrong 500 | C14: 13 | D14: B | E14: 4 | F14: 27 | G14: Australian Motor Industries | I14: Triumph Herald | K14: Jack Maurer | M14: =_xlfn.LET(_xlpm.d,_xlfn.XLOOKUP(K14,'[1]Birth Dates'!$A:$A,'[1]Birth Dates'!$B:$B,"",0),IF(_xlpm.d=0,"",_xlpm.d)) | N14: =IF(OR(M14="",A14="",NOT(ISNUMBER(M14)),M14>A14),"",DATEDIF(M14,A14,"Y")&" years, "&DATEDIF(M14,A14,"YM")&" months, "&DATEDIF(M14,A14,"MD")&" days") | O14: Ern Abbott | P14: AUS | Q14: =_xlfn.LET(_xlpm.d,_xlfn.XLOOKUP(O14,'[1]Birth Dates'!$A:$A,'[1]Birth Dates'!$B:$B,"",0),IF(_xlpm.d=0,"",_xlpm.d)) | R14: =IF(OR(Q14="",A14="",NOT(ISNUMBER(Q14)),Q14>A14),"",DATEDIF(Q14,A14,"Y")&" years, "&DATEDIF(Q14,A14,"YM")&" months, "&DATEDIF(Q14,A14,"MD")&" days") | U14: =_xlfn.LET(_xlpm.d,_xlfn.XLOOKUP(S14,'[1]Birth Dates'!$A:$A,'[1]Birth Dates'!$B:$B,"",0),IF(_xlpm.d=0,"",_xlpm.d)) | V14: =IF(OR(U14="",A14="",NOT(ISNUMBER(U14)),U14>A14),"",DATEDIF(U14,A14,"Y")&" years, "&DATEDIF(U14,A14,"YM")&" months, "&DATEDIF(U14,A14,"MD")&" days") | Z14: 0 | AA14: =IF(OR(Y14="",Z14="",Z14=0),"",Y14*4.828/(Z14*24)) | AD14: =IF(OR(AB14="",AC14="",AC14=0),"",AB14*4.828/(AC14*24)) | AE14: =IF(OR(NOT(ISNUMBER(C13)),NOT(ISNUMBER(N14))),"",IF(S14<>"",S14,N14)-C13) | AG14: 158 | AI14: =IF(OR(AG14="",AH14="",AH14=0),"",AG14*4.828/(AH14*24)) | AL14: =IF(OR(AK14="",AK14="",AK14=0),"",4.828/(AK14*24)) | AN14: =IF(OR(NOT(ISNUMBER(C14)),NOT(ISNUMBER(W14))),"",IF(AB14<>"",AB14,W14)-C14) | AP14: =IF($B14="","",TEXT($A14,"yyyymmdd")&"_P"&$C14&"_C"&$F14&"_"&TRIM(RIGHT(SUBSTITUTE(TRIM(SUBSTITUTE($K14,CHAR(160)," "))," ",REPT(" ",60)),60))&IF($O14="","","-"&TRIM(RIGHT(SUBSTITUTE(TRIM(SUBSTITUTE($O14,CHAR(160)," "))," ",REPT(" ",60)),60)))&IF($S14="","","-"&TRIM(RIGHT(SUBSTITUTE(TRIM(SUBSTITUTE($S14,CHAR(160)," "))," ",REPT(" ",60)),60)))&".jpg")
A15: 22240 | B15: Armstrong 500 | C15: 14 | D15: B | E15: 5 | F15: 20 | G15: Orman's Service Station | I15: Volkswagen | K15: Ken (Rex) Orman | M15: =_xlfn.LET(_xlpm.d,_xlfn.XLOOKUP(K15,'[1]Birth Dates'!$A:$A,'[1]Birth Dates'!$B:$B,"",0),IF(_xlpm.d=0,"",_xlpm.d)) | N15: =IF(OR(M15="",A15="",NOT(ISNUMBER(M15)),M15>A15),"",DATEDIF(M15,A15,"Y")&" years, "&DATEDIF(M15,A15,"YM")&" months, "&DATEDIF(M15,A15,"MD")&" days") | O15: Max McPherson | Q15: =_xlfn.LET(_xlpm.d,_xlfn.XLOOKUP(O15,'[1]Birth Dates'!$A:$A,'[1]Birth Dates'!$B:$B,"",0),IF(_xlpm.d=0,"",_xlpm.d)) | R15: =IF(OR(Q15="",A15="",NOT(ISNUMBER(Q15)),Q15>A15),"",DATEDIF(Q15,A15,"Y")&" years, "&DATEDIF(Q15,A15,"YM")&" months, "&DATEDIF(Q15,A15,"MD")&" days") | U15: =_xlfn.LET(_xlpm.d,_xlfn.XLOOKUP(S15,'[1]Birth Dates'!$A:$A,'[1]Birth Dates'!$B:$B,"",0),IF(_xlpm.d=0,"",_xlpm.d)) | V15: =IF(OR(U15="",A15="",NOT(ISNUMBER(U15)),U15>A15),"",DATEDIF(U15,A15,"Y")&" years, "&DATEDIF(U15,A15,"YM")&" months, "&DATEDIF(U15,A15,"MD")&" days") | Z15: 0 | AA15: =IF(OR(Y15="",Z15="",Z15=0),"",Y15*4.828/(Z15*24)) | AD15: =IF(OR(AB15="",AC15="",AC15=0),"",AB15*4.828/(AC15*24)) | AE15: =IF(OR(NOT(ISNUMBER(C14)),NOT(ISNUMBER(N15))),"",IF(S15<>"",S15,N15)-C14) | AG15: 158 | AI15: =IF(OR(AG15="",AH15="",AH15=0),"",AG15*4.828/(AH15*24)) | AL15: =IF(OR(AK15="",AK15="",AK15=0),"",4.828/(AK15*24)) | AN15: =IF(OR(NOT(ISNUMBER(C15)),NOT(ISNUMBER(W15))),"",IF(AB15<>"",AB15,W15)-C15) | AP15: =IF($B15="","",TEXT($A15,"yyyymmdd")&"_P"&$C15&"_C"&$F15&"_"&TRIM(RIGHT(SUBSTITUTE(TRIM(SUBSTITUTE($K15,CHAR(160)," "))," ",REPT(" ",60)),60))&IF($O15="","","-"&TRIM(RIGHT(SUBSTITUTE(TRIM(SUBSTITUTE($O15,CHAR(160)," "))," ",REPT(" ",60)),60)))&IF($S15="","","-"&TRIM(RIGHT(SUBSTITUTE(TRIM(SUBSTITUTE($S15,CHAR(160)," "))," ",REPT(" ",60)),60)))&".jpg")
A16: 22240 | B16: Armstrong 500 | C16: 15 | D16: D | E16: 3 | F16: 30 | G16: Autoland P/L | I16: Ford Falcon XK | K16: Bob Jane | L16: AUS | M16: =_xlfn.LET(_xlpm.d,_xlfn.XLOOKUP(K16,'[1]Birth Dates'!$A:$A,'[1]Birth Dates'!$B:$B,"",0),IF(_xlpm.d=0,"",_xlpm.d)) | N16: =IF(OR(M16="",A16="",NOT(ISNUMBER(M16)),M16>A16),"",DATEDIF(M16,A16,"Y")&" years, "&DATEDIF(M16,A16,"YM")&" months, "&DATEDIF(M16,A16,"MD")&" days") | O16: Lou Molina | Q16: =_xlfn.LET(_xlpm.d,_xlfn.XLOOKUP(O16,'[1]Birth Dates'!$A:$A,'[1]Birth Dates'!$B:$B,"",0),IF(_xlpm.d=0,"",_xlpm.d)) | R16: =IF(OR(Q16="",A16="",NOT(ISNUMBER(Q16)),Q16>A16),"",DATEDIF(Q16,A16,"Y")&" years, "&DATEDIF(Q16,A16,"YM")&" months, "&DATEDIF(Q16,A16,"MD")&" days") | U16: =_xlfn.LET(_xlpm.d,_xlfn.XLOOKUP(S16,'[1]Birth Dates'!$A:$A,'[1]Birth Dates'!$B:$B,"",0),IF(_xlpm.d=0,"",_xlpm.d)) | V16: =IF(OR(U16="",A16="",NOT(ISNUMBER(U16)),U16>A16),"",DATEDIF(U16,A16,"Y")&" years, "&DATEDIF(U16,A16,"YM")&" months, "&DATEDIF(U16,A16,"MD")&" days") | Z16: 0 | AA16: =IF(OR(Y16="",Z16="",Z16=0),"",Y16*4.828/(Z16*24)) | AD16: =IF(OR(AB16="",AC16="",AC16=0),"",AB16*4.828/(AC16*24)) | AE16: =IF(OR(NOT(ISNUMBER(C15)),NOT(ISNUMBER(N16))),"",IF(S16<>"",S16,N16)-C15) | AG16: 158 | AI16: =IF(OR(AG16="",AH16="",AH16=0),"",AG16*4.828/(AH16*24)) | AL16: =IF(OR(AK16="",AK16="",AK16=0),"",4.828/(AK16*24)) | AN16: =IF(OR(NOT(ISNUMBER(C16)),NOT(ISNUMBER(W16))),"",IF(AB16<>"",AB16,W16)-C16) | AP16: =IF($B16="","",TEXT($A16,"yyyymmdd")&"_P"&$C16&"_C"&$F16&"_"&TRIM(RIGHT(SUBSTITUTE(TRIM(SUBSTITUTE($K16,CHAR(160)," "))," ",REPT(" ",60)),60))&IF($O16="","","-"&TRIM(RIGHT(SUBSTITUTE(TRIM(SUBSTITUTE($O16,CHAR(160)," "))," ",REPT(" ",60)),60)))&IF($S16="","","-"&TRIM(RIGHT(SUBSTITUTE(TRIM(SUBSTITUTE($S16,CHAR(160)," "))," ",REPT(" ",60)),60)))&".jpg")
A17: 22240 | B17: Armstrong 500 | C17: 16 | D17: B | E17: 6 | F17: 18 | G17: Lanock Motors Ltd. | I17: Volkswagen | K17: David McKay | L17: AUS | M17: =_xlfn.LET(_xlpm.d,_xlfn.XLOOKUP(K17,'[1]Birth Dates'!$A:$A,'[1]Birth Dates'!$B:$B,"",0),IF(_xlpm.d=0,"",_xlpm.d)) | N17: =IF(OR(M17="",A17="",NOT(ISNUMBER(M17)),M17>A17),"",DATEDIF(M17,A17,"Y")&" years, "&DATEDIF(M17,A17,"YM")&" months, "&DATEDIF(M17,A17,"MD")&" days") | O17: Greg Cusack | P17: AUS | Q17: =_xlfn.LET(_xlpm.d,_xlfn.XLOOKUP(O17,'[1]Birth Dates'!$A:$A,'[1]Birth Dates'!$B:$B,"",0),IF(_xlpm.d=0,"",_xlpm.d)) | R17: =IF(OR(Q17="",A17="",NOT(ISNUMBER(Q17)),Q17>A17),"",DATEDIF(Q17,A17,"Y")&" years, "&DATEDIF(Q17,A17,"YM")&" months, "&DATEDIF(Q17,A17,"MD")&" days") | U17: =_xlfn.LET(_xlpm.d,_xlfn.XLOOKUP(S17,'[1]Birth Dates'!$A:$A,'[1]Birth Dates'!$B:$B,"",0),IF(_xlpm.d=0,"",_xlpm.d)) | V17: =IF(OR(U17="",A17="",NOT(ISNUMBER(U17)),U17>A17),"",DATEDIF(U17,A17,"Y")&" years, "&DATEDIF(U17,A17,"YM")&" months, "&DATEDIF(U17,A17,"MD")&" days") | Z17: 0 | AA17: =IF(OR(Y17="",Z17="",Z17=0),"",Y17*4.828/(Z17*24)) | AD17: =IF(OR(AB17="",AC17="",AC17=0),"",AB17*4.828/(AC17*24)) | AE17: =IF(OR(NOT(ISNUMBER(C16)),NOT(ISNUMBER(N17))),"",IF(S17<>"",S17,N17)-C16) | AG17: 158 | AI17: =IF(OR(AG17="",AH17="",AH17=0),"",AG17*4.828/(AH17*24)) | AL17: =IF(OR(AK17="",AK17="",AK17=0),"",4.828/(AK17*24)) | AN17: =IF(OR(NOT(ISNUMBER(C17)),NOT(ISNUMBER(W17))),"",IF(AB17<>"",AB17,W17)-C17) | AP17: =IF($B17="","",TEXT($A17,"yyyymmdd")&"_P"&$C17&"_C"&$F17&"_"&TRIM(RIGHT(SUBSTITUTE(TRIM(SUBSTITUTE($K17,CHAR(160)," "))," ",REPT(" ",60)),60))&IF($O17="","","-"&TRIM(RIGHT(SUBSTITUTE(TRIM(SUBSTITUTE($O17,CHAR(160)," "))," ",REPT(" ",60)),60)))&IF($S17="","","-"&TRIM(RIGHT(SUBSTITUTE(TRIM(SUBSTITUTE($S17,CHAR(160)," "))," ",REPT(" ",60)),60)))&".jpg")
A18: 22240 | B18: Armstrong 500 | C18: 17 | D18: B | E18: 7 | F18: 19 | G18: Spencer Motors P/L | I18: Volkswagen | K18: Arthur Wylie | M18: =_xlfn.LET(_xlpm.d,_xlfn.XLOOKUP(K18,'[1]Birth Dates'!$A:$A,'[1]Birth Dates'!$B:$B,"",0),IF(_xlpm.d=0,"",_xlpm.d)) | N18: =IF(OR(M18="",A18="",NOT(ISNUMBER(M18)),M18>A18),"",DATEDIF(M18,A18,"Y")&" years, "&DATEDIF(M18,A18,"YM")&" months, "&DATEDIF(M18,A18,"MD")&" days") | O18: Ken Wylie | Q18: =_xlfn.LET(_xlpm.d,_xlfn.XLOOKUP(O18,'[1]Birth Dates'!$A:$A,'[1]Birth Dates'!$B:$B,"",0),IF(_xlpm.d=0,"",_xlpm.d)) | R18: =IF(OR(Q18="",A18="",NOT(ISNUMBER(Q18)),Q18>A18),"",DATEDIF(Q18,A18,"Y")&" years, "&DATEDIF(Q18,A18,"YM")&" months, "&DATEDIF(Q18,A18,"MD")&" days") | U18: =_xlfn.LET(_xlpm.d,_xlfn.XLOOKUP(S18,'[1]Birth Dates'!$A:$A,'[1]Birth Dates'!$B:$B,"",0),IF(_xlpm.d=0,"",_xlpm.d)) | V18: =IF(OR(U18="",A18="",NOT(ISNUMBER(U18)),U18>A18),"",DATEDIF(U18,A18,"Y")&" years, "&DATEDIF(U18,A18,"YM")&" months, "&DATEDIF(U18,A18,"MD")&" days") | Z18: 0 | AA18: =IF(OR(Y18="",Z18="",Z18=0),"",Y18*4.828/(Z18*24)) | AD18: =IF(OR(AB18="",AC18="",AC18=0),"",AB18*4.828/(AC18*24)) | AE18: =IF(OR(NOT(ISNUMBER(C17)),NOT(ISNUMBER(N18))),"",IF(S18<>"",S18,N18)-C17) | AG18: 157 | AI18: =IF(OR(AG18="",AH18="",AH18=0),"",AG18*4.828/(AH18*24)) | AL18: =IF(OR(AK18="",AK18="",AK18=0),"",4.828/(AK18*24)) | AN18: =IF(OR(NOT(ISNUMBER(C18)),NOT(ISNUMBER(W18))),"",IF(AB18<>"",AB18,W18)-C18) | AP18: =IF($B18="","",TEXT($A18,"yyyymmdd")&"_P"&$C18&"_C"&$F18&"_"&TRIM(RIGHT(SUBSTITUTE(TRIM(SUBSTITUTE($K18,CHAR(160)," "))," ",REPT(" ",60)),60))&IF($O18="","","-"&TRIM(RIGHT(SUBSTITUTE(TRIM(SUBSTITUTE($O18,CHAR(160)," "))," ",REPT(" ",60)),60)))&IF($S18="","","-"&TRIM(RIGHT(SUBSTITUTE(TRIM(SUBSTITUTE($S18,CHAR(160)," "))," ",REPT(" ",60)),60)))&".jpg")
A19: 22240 | B19: Armstrong 500 | C19: 18 | D19: C | E19: 8 | F19: 36 | G19: Continental & General Dist. P/L | I19: Peugeot 403 | K19: Ron Lilley | M19: =_xlfn.LET(_xlpm.d,_xlfn.XLOOKUP(K19,'[1]Birth Dates'!$A:$A,'[1]Birth Dates'!$B:$B,"",0),IF(_xlpm.d=0,"",_xlpm.d)) | N19: =IF(OR(M19="",A19="",NOT(ISNUMBER(M19)),M19>A19),"",DATEDIF(M19,A19,"Y")&" years, "&DATEDIF(M19,A19,"YM")&" months, "&DATEDIF(M19,A19,"MD")&" days") | O19: Jim Gullan | Q19: =_xlfn.LET(_xlpm.d,_xlfn.XLOOKUP(O19,'[1]Birth Dates'!$A:$A,'[1]Birth Dates'!$B:$B,"",0),IF(_xlpm.d=0,"",_xlpm.d)) | R19: =IF(OR(Q19="",A19="",NOT(ISNUMBER(Q19)),Q19>A19),"",DATEDIF(Q19,A19,"Y")&" years, "&DATEDIF(Q19,A19,"YM")&" months, "&DATEDIF(Q19,A19,"MD")&" days") | U19: =_xlfn.LET(_xlpm.d,_xlfn.XLOOKUP(S19,'[1]Birth Dates'!$A:$A,'[1]Birth Dates'!$B:$B,"",0),IF(_xlpm.d=0,"",_xlpm.d)) | V19: =IF(OR(U19="",A19="",NOT(ISNUMBER(U19)),U19>A19),"",DATEDIF(U19,A19,"Y")&" years, "&DATEDIF(U19,A19,"YM")&" months, "&DATEDIF(U19,A19,"MD")&" days") | Z19: 0 | AA19: =IF(OR(Y19="",Z19="",Z19=0),"",Y19*4.828/(Z19*24)) | AD19: =IF(OR(AB19="",AC19="",AC19=0),"",AB19*4.828/(AC19*24)) | AE19: =IF(OR(NOT(ISNUMBER(C18)),NOT(ISNUMBER(N19))),"",IF(S19<>"",S19,N19)-C18) | AG19: 157 | AI19: =IF(OR(AG19="",AH19="",AH19=0),"",AG19*4.828/(AH19*24)) | AL19: =IF(OR(AK19="",AK19="",AK19=0),"",4.828/(AK19*24)) | AN19: =IF(OR(NOT(ISNUMBER(C19)),NOT(ISNUMBER(W19))),"",IF(AB19<>"",AB19,W19)-C19) | AP19: =IF($B19="","",TEXT($A19,"yyyymmdd")&"_P"&$C19&"_C"&$F19&"_"&TRIM(RIGHT(SUBSTITUTE(TRIM(SUBSTITUTE($K19,CHAR(160)," "))," ",REPT(" ",60)),60))&IF($O19="","","-"&TRIM(RIGHT(SUBSTITUTE(TRIM(SUBSTITUTE($O19,CHAR(160)," "))," ",REPT(" ",60)),60)))&IF($S19="","","-"&TRIM(RIGHT(SUBSTITUTE(TRIM(SUBSTITUTE($S19,CHAR(160)," "))," ",REPT(" ",60)),60)))&".jpg")
A20: 22240 | B20: Armstrong 500 | C20: 19 | D20: B | E20: 8 | F20: 29 | G20: Nalders Garage | I20: Ford Anglia | K20: Bill Nalder | M20: =_xlfn.LET(_xlpm.d,_xlfn.XLOOKUP(K20,'[1]Birth Dates'!$A:$A,'[1]Birth Dates'!$B:$B,"",0),IF(_xlpm.d=0,"",_xlpm.d)) | N20: =IF(OR(M20="",A20="",NOT(ISNUMBER(M20)),M20>A20),"",DATEDIF(M20,A20,"Y")&" years, "&DATEDIF(M20,A20,"YM")&" months, "&DATEDIF(M20,A20,"MD")&" days") | O20: John Amp | Q20: =_xlfn.LET(_xlpm.d,_xlfn.XLOOKUP(O20,'[1]Birth Dates'!$A:$A,'[1]Birth Dates'!$B:$B,"",0),IF(_xlpm.d=0,"",_xlpm.d)) | R20: =IF(OR(Q20="",A20="",NOT(ISNUMBER(Q20)),Q20>A20),"",DATEDIF(Q20,A20,"Y")&" years, "&DATEDIF(Q20,A20,"YM")&" months, "&DATEDIF(Q20,A20,"MD")&" days") | U20: =_xlfn.LET(_xlpm.d,_xlfn.XLOOKUP(S20,'[1]Birth Dates'!$A:$A,'[1]Birth Dates'!$B:$B,"",0),IF(_xlpm.d=0,"",_xlpm.d)) | V20: =IF(OR(U20="",A20="",NOT(ISNUMBER(U20)),U20>A20),"",DATEDIF(U20,A20,"Y")&" years, "&DATEDIF(U20,A20,"YM")&" months, "&DATEDIF(U20,A20,"MD")&" days") | Z20: 0 | AA20: =IF(OR(Y20="",Z20="",Z20=0),"",Y20*4.828/(Z20*24)) | AD20: =IF(OR(AB20="",AC20="",AC20=0),"",AB20*4.828/(AC20*24)) | AE20: =IF(OR(NOT(ISNUMBER(C19)),NOT(ISNUMBER(N20))),"",IF(S20<>"",S20,N20)-C19) | AG20: 156 | AI20: =IF(OR(AG20="",AH20="",AH20=0),"",AG20*4.828/(AH20*24)) | AL20: =IF(OR(AK20="",AK20="",AK20=0),"",4.828/(AK20*24)) | AN20: =IF(OR(NOT(ISNUMBER(C20)),NOT(ISNUMBER(W20))),"",IF(AB20<>"",AB20,W20)-C20) | AP20: =IF($B20="","",TEXT($A20,"yyyymmdd")&"_P"&$C20&"_C"&$F20&"_"&TRIM(RIGHT(SUBSTITUTE(TRIM(SUBSTITUTE($K20,CHAR(160)," "))," ",REPT(" ",60)),60))&IF($O20="","","-"&TRIM(RIGHT(SUBSTITUTE(TRIM(SUBSTITUTE($O20,CHAR(160)," "))," ",REPT(" ",60)),60)))&IF($S20="","","-"&TRIM(RIGHT(SUBSTITUTE(TRIM(SUBSTITUTE($S20,CHAR(160)," "))," ",REPT(" ",60)),60)))&".jpg")
A21: 22240 | B21: Armstrong 500 | C21: 20 | D21: C | E21: 9 | F21: 39 | G21: Continental & General Dist. P/L | I21: Austin Lancer | K21: Brian Foley | L21: AUS | M21: =_xlfn.LET(_xlpm.d,_xlfn.XLOOKUP(K21,'[1]Birth Dates'!$A:$A,'[1]Birth Dates'!$B:$B,"",0),IF(_xlpm.d=0,"",_xlpm.d)) | N21: =IF(OR(M21="",A21="",NOT(ISNUMBER(M21)),M21>A21),"",DATEDIF(M21,A21,"Y")&" years, "&DATEDIF(M21,A21,"YM")&" months, "&DATEDIF(M21,A21,"MD")&" days") | O21: Alan Edney | P21: AUS | Q21: =_xlfn.LET(_xlpm.d,_xlfn.XLOOKUP(O21,'[1]Birth Dates'!$A:$A,'[1]Birth Dates'!$B:$B,"",0),IF(_xlpm.d=0,"",_xlpm.d)) | R21: =IF(OR(Q21="",A21="",NOT(ISNUMBER(Q21)),Q21>A21),"",DATEDIF(Q21,A21,"Y")&" years, "&DATEDIF(Q21,A21,"YM")&" months, "&DATEDIF(Q21,A21,"MD")&" days") | U21: =_xlfn.LET(_xlpm.d,_xlfn.XLOOKUP(S21,'[1]Birth Dates'!$A:$A,'[1]Birth Dates'!$B:$B,"",0),IF(_xlpm.d=0,"",_xlpm.d)) | V21: =IF(OR(U21="",A21="",NOT(ISNUMBER(U21)),U21>A21),"",DATEDIF(U21,A21,"Y")&" years, "&DATEDIF(U21,A21,"YM")&" months, "&DATEDIF(U21,A21,"MD")&" days") | Z21: 0 | AA21: =IF(OR(Y21="",Z21="",Z21=0),"",Y21*4.828/(Z21*24)) | AD21: =IF(OR(AB21="",AC21="",AC21=0),"",AB21*4.828/(AC21*24)) | AE21: =IF(OR(NOT(ISNUMBER(C20)),NOT(ISNUMBER(N21))),"",IF(S21<>"",S21,N21)-C20) | AG21: 155 | AI21: =IF(OR(AG21="",AH21="",AH21=0),"",AG21*4.828/(AH21*24)) | AL21: =IF(OR(AK21="",AK21="",AK21=0),"",4.828/(AK21*24)) | AN21: =IF(OR(NOT(ISNUMBER(C21)),NOT(ISNUMBER(W21))),"",IF(AB21<>"",AB21,W21)-C21) | AP21: =IF($B21="","",TEXT($A21,"yyyymmdd")&"_P"&$C21&"_C"&$F21&"_"&TRIM(RIGHT(SUBSTITUTE(TRIM(SUBSTITUTE($K21,CHAR(160)," "))," ",REPT(" ",60)),60))&IF($O21="","","-"&TRIM(RIGHT(SUBSTITUTE(TRIM(SUBSTITUTE($O21,CHAR(160)," "))," ",REPT(" ",60)),60)))&IF($S21="","","-"&TRIM(RIGHT(SUBSTITUTE(TRIM(SUBSTITUTE($S21,CHAR(160)," "))," ",REPT(" ",60)),60)))&".jpg")
A22: 22240 | B22: Armstrong 500 | C22: 21 | D22: E | E22: 1 | F22: 32 | G22: Sabina Motors P/L | I22: Ford Customline | K22: Ray Gibbs | M22: =_xlfn.LET(_xlpm.d,_xlfn.XLOOKUP(K22,'[1]Birth Dates'!$A:$A,'[1]Birth Dates'!$B:$B,"",0),IF(_xlpm.d=0,"",_xlpm.d)) | N22: =IF(OR(M22="",A22="",NOT(ISNUMBER(M22)),M22>A22),"",DATEDIF(M22,A22,"Y")&" years, "&DATEDIF(M22,A22,"YM")&" months, "&DATEDIF(M22,A22,"MD")&" days") | O22: Murray Carter | P22: AUS | Q22: =_xlfn.LET(_xlpm.d,_xlfn.XLOOKUP(O22,'[1]Birth Dates'!$A:$A,'[1]Birth Dates'!$B:$B,"",0),IF(_xlpm.d=0,"",_xlpm.d)) | R22: =IF(OR(Q22="",A22="",NOT(ISNUMBER(Q22)),Q22>A22),"",DATEDIF(Q22,A22,"Y")&" years, "&DATEDIF(Q22,A22,"YM")&" months, "&DATEDIF(Q22,A22,"MD")&" days") | U22: =_xlfn.LET(_xlpm.d,_xlfn.XLOOKUP(S22,'[1]Birth Dates'!$A:$A,'[1]Birth Dates'!$B:$B,"",0),IF(_xlpm.d=0,"",_xlpm.d)) | V22: =IF(OR(U22="",A22="",NOT(ISNUMBER(U22)),U22>A22),"",DATEDIF(U22,A22,"Y")&" years, "&DATEDIF(U22,A22,"YM")&" months, "&DATEDIF(U22,A22,"MD")&" days") | Z22: 0 | AA22: =IF(OR(Y22="",Z22="",Z22=0),"",Y22*4.828/(Z22*24)) | AD22: =IF(OR(AB22="",AC22="",AC22=0),"",AB22*4.828/(AC22*24)) | AE22: =IF(OR(NOT(ISNUMBER(C21)),NOT(ISNUMBER(N22))),"",IF(S22<>"",S22,N22)-C21) | AG22: 154 | AI22: =IF(OR(AG22="",AH22="",AH22=0),"",AG22*4.828/(AH22*24)) | AL22: =IF(OR(AK22="",AK22="",AK22=0),"",4.828/(AK22*24)) | AN22: =IF(OR(NOT(ISNUMBER(C22)),NOT(ISNUMBER(W22))),"",IF(AB22<>"",AB22,W22)-C22) | AP22: =IF($B22="","",TEXT($A22,"yyyymmdd")&"_P"&$C22&"_C"&$F22&"_"&TRIM(RIGHT(SUBSTITUTE(TRIM(SUBSTITUTE($K22,CHAR(160)," "))," ",REPT(" ",60)),60))&IF($O22="","","-"&TRIM(RIGHT(SUBSTITUTE(TRIM(SUBSTITUTE($O22,CHAR(160)," "))," ",REPT(" ",60)),60)))&IF($S22="","","-"&TRIM(RIGHT(SUBSTITUTE(TRIM(SUBSTITUTE($S22,CHAR(160)," "))," ",REPT(" ",60)),60)))&".jpg")
A23: 22240 | B23: Armstrong 500 | C23: 22 | D23: B | E23: 9 | F23: 14 | G23: Ecurie Dauphine | I23: Renault Dauphine | K23: Jm Leighton | M23: =_xlfn.LET(_xlpm.d,_xlfn.XLOOKUP(K23,'[1]Birth Dates'!$A:$A,'[1]Birth Dates'!$B:$B,"",0),IF(_xlpm.d=0,"",_xlpm.d)) | N23: =IF(OR(M23="",A23="",NOT(ISNUMBER(M23)),M23>A23),"",DATEDIF(M23,A23,"Y")&" years, "&DATEDIF(M23,A23,"YM")&" months, "&DATEDIF(M23,A23,"MD")&" days") | O23: Alan Ling | Q23: =_xlfn.LET(_xlpm.d,_xlfn.XLOOKUP(O23,'[1]Birth Dates'!$A:$A,'[1]Birth Dates'!$B:$B,"",0),IF(_xlpm.d=0,"",_xlpm.d)) | R23: =IF(OR(Q23="",A23="",NOT(ISNUMBER(Q23)),Q23>A23),"",DATEDIF(Q23,A23,"Y")&" years, "&DATEDIF(Q23,A23,"YM")&" months, "&DATEDIF(Q23,A23,"MD")&" days") | U23: =_xlfn.LET(_xlpm.d,_xlfn.XLOOKUP(S23,'[1]Birth Dates'!$A:$A,'[1]Birth Dates'!$B:$B,"",0),IF(_xlpm.d=0,"",_xlpm.d)) | V23: =IF(OR(U23="",A23="",NOT(ISNUMBER(U23)),U23>A23),"",DATEDIF(U23,A23,"Y")&" years, "&DATEDIF(U23,A23,"YM")&" months, "&DATEDIF(U23,A23,"MD")&" days") | Z23: 0 | AA23: =IF(OR(Y23="",Z23="",Z23=0),"",Y23*4.828/(Z23*24)) | AD23: =IF(OR(AB23="",AC23="",AC23=0),"",AB23*4.828/(AC23*24)) | AE23: =IF(OR(NOT(ISNUMBER(C22)),NOT(ISNUMBER(N23))),"",IF(S23<>"",S23,N23)-C22) | AG23: 154 | AI23: =IF(OR(AG23="",AH23="",AH23=0),"",AG23*4.828/(AH23*24)) | AL23: =IF(OR(AK23="",AK23="",AK23=0),"",4.828/(AK23*24)) | AN23: =IF(OR(NOT(ISNUMBER(C23)),NOT(ISNUMBER(W23))),"",IF(AB23<>"",AB23,W23)-C23) | AP23: =IF($B23="","",TEXT($A23,"yyyymmdd")&"_P"&$C23&"_C"&$F23&"_"&TRIM(RIGHT(SUBSTITUTE(TRIM(SUBSTITUTE($K23,CHAR(160)," "))," ",REPT(" ",60)),60))&IF($O23="","","-"&TRIM(RIGHT(SUBSTITUTE(TRIM(SUBSTITUTE($O23,CHAR(160)," "))," ",REPT(" ",60)),60)))&IF($S23="","","-"&TRIM(RIGHT(SUBSTITUTE(TRIM(SUBSTITUTE($S23,CHAR(160)," "))," ",REPT(" ",60)),60)))&".jpg")
A24: 22240 | B24: Armstrong 500 | C24: 23 | D24: A | E24: 1 | F24: 1 | G24: Continental & General Dist. | I24: NSU Prinz | K24: Lex Davison | L24: AUS | M24: =_xlfn.LET(_xlpm.d,_xlfn.XLOOKUP(K24,'[1]Birth Dates'!$A:$A,'[1]Birth Dates'!$B:$B,"",0),IF(_xlpm.d=0,"",_xlpm.d)) | N24: =IF(OR(M24="",A24="",NOT(ISNUMBER(M24)),M24>A24),"",DATEDIF(M24,A24,"Y")&" years, "&DATEDIF(M24,A24,"YM")&" months, "&DATEDIF(M24,A24,"MD")&" days") | O24: Doug Whiteford | P24: AUS | Q24: =_xlfn.LET(_xlpm.d,_xlfn.XLOOKUP(O24,'[1]Birth Dates'!$A:$A,'[1]Birth Dates'!$B:$B,"",0),IF(_xlpm.d=0,"",_xlpm.d)) | R24: =IF(OR(Q24="",A24="",NOT(ISNUMBER(Q24)),Q24>A24),"",DATEDIF(Q24,A24,"Y")&" years, "&DATEDIF(Q24,A24,"YM")&" months, "&DATEDIF(Q24,A24,"MD")&" days") | U24: =_xlfn.LET(_xlpm.d,_xlfn.XLOOKUP(S24,'[1]Birth Dates'!$A:$A,'[1]Birth Dates'!$B:$B,"",0),IF(_xlpm.d=0,"",_xlpm.d)) | V24: =IF(OR(U24="",A24="",NOT(ISNUMBER(U24)),U24>A24),"",DATEDIF(U24,A24,"Y")&" years, "&DATEDIF(U24,A24,"YM")&" months, "&DATEDIF(U24,A24,"MD")&" days") | Z24: 0 | AA24: =IF(OR(Y24="",Z24="",Z24=0),"",Y24*4.828/(Z24*24)) | AD24: =IF(OR(AB24="",AC24="",AC24=0),"",AB24*4.828/(AC24*24)) | AE24: =IF(OR(NOT(ISNUMBER(C23)),NOT(ISNUMBER(N24))),"",IF(S24<>"",S24,N24)-C23) | AG24: 153 | AI24: =IF(OR(AG24="",AH24="",AH24=0),"",AG24*4.828/(AH24*24)) | AL24: =IF(OR(AK24="",AK24="",AK24=0),"",4.828/(AK24*24)) | AN24: =IF(OR(NOT(ISNUMBER(C24)),NOT(ISNUMBER(W24))),"",IF(AB24<>"",AB24,W24)-C24) | AP24: =IF($B24="","",TEXT($A24,"yyyymmdd")&"_P"&$C24&"_C"&$F24&"_"&TRIM(RIGHT(SUBSTITUTE(TRIM(SUBSTITUTE($K24,CHAR(160)," "))," ",REPT(" ",60)),60))&IF($O24="","","-"&TRIM(RIGHT(SUBSTITUTE(TRIM(SUBSTITUTE($O24,CHAR(160)," "))," ",REPT(" ",60)),60)))&IF($S24="","","-"&TRIM(RIGHT(SUBSTITUTE(TRIM(SUBSTITUTE($S24,CHAR(160)," "))," ",REPT(" ",60)),60)))&".jpg")
A25: 22240 | B25: Armstrong 500 | C25: 24 | D25: B | E25: 10 | F25: 12 | G25: Ecurie Dauphine | I25: Renault Dauphine | K25: Des West | L25: AUS | M25: =_xlfn.LET(_xlpm.d,_xlfn.XLOOKUP(K25,'[1]Birth Dates'!$A:$A,'[1]Birth Dates'!$B:$B,"",0),IF(_xlpm.d=0,"",_xlpm.d)) | N25: =IF(OR(M25="",A25="",NOT(ISNUMBER(M25)),M25>A25),"",DATEDIF(M25,A25,"Y")&" years, "&DATEDIF(M25,A25,"YM")&" months, "&DATEDIF(M25,A25,"MD")&" days") | O25: Ian Geoghegan | P25: AUS | Q25: =_xlfn.LET(_xlpm.d,_xlfn.XLOOKUP(O25,'[1]Birth Dates'!$A:$A,'[1]Birth Dates'!$B:$B,"",0),IF(_xlpm.d=0,"",_xlpm.d)) | R25: =IF(OR(Q25="",A25="",NOT(ISNUMBER(Q25)),Q25>A25),"",DATEDIF(Q25,A25,"Y")&" years, "&DATEDIF(Q25,A25,"YM")&" months, "&DATEDIF(Q25,A25,"MD")&" days") | U25: =_xlfn.LET(_xlpm.d,_xlfn.XLOOKUP(S25,'[1]Birth Dates'!$A:$A,'[1]Birth Dates'!$B:$B,"",0),IF(_xlpm.d=0,"",_xlpm.d)) | V25: =IF(OR(U25="",A25="",NOT(ISNUMBER(U25)),U25>A25),"",DATEDIF(U25,A25,"Y")&" years, "&DATEDIF(U25,A25,"YM")&" months, "&DATEDIF(U25,A25,"MD")&" days") | Z25: 0 | AA25: =IF(OR(Y25="",Z25="",Z25=0),"",Y25*4.828/(Z25*24)) | AD25: =IF(OR(AB25="",AC25="",AC25=0),"",AB25*4.828/(AC25*24)) | AE25: =IF(OR(NOT(ISNUMBER(C24)),NOT(ISNUMBER(N25))),"",IF(S25<>"",S25,N25)-C24) | AG25: 152 | AI25: =IF(OR(AG25="",AH25="",AH25=0),"",AG25*4.828/(AH25*24)) | AL25: =IF(OR(AK25="",AK25="",AK25=0),"",4.828/(AK25*24)) | AN25: =IF(OR(NOT(ISNUMBER(C25)),NOT(ISNUMBER(W25))),"",IF(AB25<>"",AB25,W25)-C25) | AP25: =IF($B25="","",TEXT($A25,"yyyymmdd")&"_P"&$C25&"_C"&$F25&"_"&TRIM(RIGHT(SUBSTITUTE(TRIM(SUBSTITUTE($K25,CHAR(160)," "))," ",REPT(" ",60)),60))&IF($O25="","","-"&TRIM(RIGHT(SUBSTITUTE(TRIM(SUBSTITUTE($O25,CHAR(160)," "))," ",REPT(" ",60)),60)))&IF($S25="","","-"&TRIM(RIGHT(SUBSTITUTE(TRIM(SUBSTITUTE($S25,CHAR(160)," "))," ",REPT(" ",60)),60)))&".jpg")
A26: 22240 | B26: Armstrong 500 | C26: 25 | D26: B | E26: 11 | F26: 11 | G26: Ecurie Dauphine | I26: Renault Dauphine | K26: Bill Pitt | M26: =_xlfn.LET(_xlpm.d,_xlfn.XLOOKUP(K26,'[1]Birth Dates'!$A:$A,'[1]Birth Dates'!$B:$B,"",0),IF(_xlpm.d=0,"",_xlpm.d)) | N26: =IF(OR(M26="",A26="",NOT(ISNUMBER(M26)),M26>A26),"",DATEDIF(M26,A26,"Y")&" years, "&DATEDIF(M26,A26,"YM")&" months, "&DATEDIF(M26,A26,"MD")&" days") | O26: Leo Geoghegan | P26: AUS | Q26: =_xlfn.LET(_xlpm.d,_xlfn.XLOOKUP(O26,'[1]Birth Dates'!$A:$A,'[1]Birth Dates'!$B:$B,"",0),IF(_xlpm.d=0,"",_xlpm.d)) | R26: =IF(OR(Q26="",A26="",NOT(ISNUMBER(Q26)),Q26>A26),"",DATEDIF(Q26,A26,"Y")&" years, "&DATEDIF(Q26,A26,"YM")&" months, "&DATEDIF(Q26,A26,"MD")&" days") | U26: =_xlfn.LET(_xlpm.d,_xlfn.XLOOKUP(S26,'[1]Birth Dates'!$A:$A,'[1]Birth Dates'!$B:$B,"",0),IF(_xlpm.d=0,"",_xlpm.d)) | V26: =IF(OR(U26="",A26="",NOT(ISNUMBER(U26)),U26>A26),"",DATEDIF(U26,A26,"Y")&" years, "&DATEDIF(U26,A26,"YM")&" months, "&DATEDIF(U26,A26,"MD")&" days") | Z26: 0 | AA26: =IF(OR(Y26="",Z26="",Z26=0),"",Y26*4.828/(Z26*24)) | AD26: =IF(OR(AB26="",AC26="",AC26=0),"",AB26*4.828/(AC26*24)) | AE26: =IF(OR(NOT(ISNUMBER(C25)),NOT(ISNUMBER(N26))),"",IF(S26<>"",S26,N26)-C25) | AG26: 151 | AI26: =IF(OR(AG26="",AH26="",AH26=0),"",AG26*4.828/(AH26*24)) | AL26: =IF(OR(AK26="",AK26="",AK26=0),"",4.828/(AK26*24)) | AN26: =IF(OR(NOT(ISNUMBER(C26)),NOT(ISNUMBER(W26))),"",IF(AB26<>"",AB26,W26)-C26) | AP26: =IF($B26="","",TEXT($A26,"yyyymmdd")&"_P"&$C26&"_C"&$F26&"_"&TRIM(RIGHT(SUBSTITUTE(TRIM(SUBSTITUTE($K26,CHAR(160)," "))," ",REPT(" ",60)),60))&IF($O26="","","-"&TRIM(RIGHT(SUBSTITUTE(TRIM(SUBSTITUTE($O26,CHAR(160)," "))," ",REPT(" ",60)),60)))&IF($S26="","","-"&TRIM(RIGHT(SUBSTITUTE(TRIM(SUBSTITUTE($S26,CHAR(160)," "))," ",REPT(" ",60)),60)))&".jpg")
A27: 22240 | B27: Armstrong 500 | C27: 26 | D27: A | E27: 2 | F27: 2 | G27: Continental & General Dist. | I27: NSU Prinz | K27: Bruce Walton | M27: =_xlfn.LET(_xlpm.d,_xlfn.XLOOKUP(K27,'[1]Birth Dates'!$A:$A,'[1]Birth Dates'!$B:$B,"",0),IF(_xlpm.d=0,"",_xlpm.d)) | N27: =IF(OR(M27="",A27="",NOT(ISNUMBER(M27)),M27>A27),"",DATEDIF(M27,A27,"Y")&" years, "&DATEDIF(M27,A27,"YM")&" months, "&DATEDIF(M27,A27,"MD")&" days") | O27: Paul England | Q27: =_xlfn.LET(_xlpm.d,_xlfn.XLOOKUP(O27,'[1]Birth Dates'!$A:$A,'[1]Birth Dates'!$B:$B,"",0),IF(_xlpm.d=0,"",_xlpm.d)) | R27: =IF(OR(Q27="",A27="",NOT(ISNUMBER(Q27)),Q27>A27),"",DATEDIF(Q27,A27,"Y")&" years, "&DATEDIF(Q27,A27,"YM")&" months, "&DATEDIF(Q27,A27,"MD")&" days") | U27: =_xlfn.LET(_xlpm.d,_xlfn.XLOOKUP(S27,'[1]Birth Dates'!$A:$A,'[1]Birth Dates'!$B:$B,"",0),IF(_xlpm.d=0,"",_xlpm.d)) | V27: =IF(OR(U27="",A27="",NOT(ISNUMBER(U27)),U27>A27),"",DATEDIF(U27,A27,"Y")&" years, "&DATEDIF(U27,A27,"YM")&" months, "&DATEDIF(U27,A27,"MD")&" days") | Z27: 0 | AA27: =IF(OR(Y27="",Z27="",Z27=0),"",Y27*4.828/(Z27*24)) | AD27: =IF(OR(AB27="",AC27="",AC27=0),"",AB27*4.828/(AC27*24)) | AE27: =IF(OR(NOT(ISNUMBER(C26)),NOT(ISNUMBER(N27))),"",IF(S27<>"",S27,N27)-C26) | AG27: 150 | AI27: =IF(OR(AG27="",AH27="",AH27=0),"",AG27*4.828/(AH27*24)) | AL27: =IF(OR(AK27="",AK27="",AK27=0),"",4.828/(AK27*24)) | AN27: =IF(OR(NOT(ISNUMBER(C27)),NOT(ISNUMBER(W27))),"",IF(AB27<>"",AB27,W27)-C27) | AP27: =IF($B27="","",TEXT($A27,"yyyymmdd")&"_P"&$C27&"_C"&$F27&"_"&TRIM(RIGHT(SUBSTITUTE(TRIM(SUBSTITUTE($K27,CHAR(160)," "))," ",REPT(" ",60)),60))&IF($O27="","","-"&TRIM(RIGHT(SUBSTITUTE(TRIM(SUBSTITUTE($O27,CHAR(160)," "))," ",REPT(" ",60)),60)))&IF($S27="","","-"&TRIM(RIGHT(SUBSTITUTE(TRIM(SUBSTITUTE($S27,CHAR(160)," "))," ",REPT(" ",60)),60)))&".jpg")
A28: 22240 | B28: Armstrong 500 | C28: 27 | D28: A | E28: 3 | F28: 3 | G28: Continental & General Dist. | I28: NSU Prinz | K28: Hoot Gibson | M28: =_xlfn.LET(_xlpm.d,_xlfn.XLOOKUP(K28,'[1]Birth Dates'!$A:$A,'[1]Birth Dates'!$B:$B,"",0),IF(_xlpm.d=0,"",_xlpm.d)) | N28: =IF(OR(M28="",A28="",NOT(ISNUMBER(M28)),M28>A28),"",DATEDIF(M28,A28,"Y")&" years, "&DATEDIF(M28,A28,"YM")&" months, "&DATEDIF(M28,A28,"MD")&" days") | O28: Jm Gorman | Q28: =_xlfn.LET(_xlpm.d,_xlfn.XLOOKUP(O28,'[1]Birth Dates'!$A:$A,'[1]Birth Dates'!$B:$B,"",0),IF(_xlpm.d=0,"",_xlpm.d)) | R28: =IF(OR(Q28="",A28="",NOT(ISNUMBER(Q28)),Q28>A28),"",DATEDIF(Q28,A28,"Y")&" years, "&DATEDIF(Q28,A28,"YM")&" months, "&DATEDIF(Q28,A28,"MD")&" days") | U28: =_xlfn.LET(_xlpm.d,_xlfn.XLOOKUP(S28,'[1]Birth Dates'!$A:$A,'[1]Birth Dates'!$B:$B,"",0),IF(_xlpm.d=0,"",_xlpm.d)) | V28: =IF(OR(U28="",A28="",NOT(ISNUMBER(U28)),U28>A28),"",DATEDIF(U28,A28,"Y")&" years, "&DATEDIF(U28,A28,"YM")&" months, "&DATEDIF(U28,A28,"MD")&" days") | Z28: 0 | AA28: =IF(OR(Y28="",Z28="",Z28=0),"",Y28*4.828/(Z28*24)) | AD28: =IF(OR(AB28="",AC28="",AC28=0),"",AB28*4.828/(AC28*24)) | AE28: =IF(OR(NOT(ISNUMBER(C27)),NOT(ISNUMBER(N28))),"",IF(S28<>"",S28,N28)-C27) | AG28: 148 | AI28: =IF(OR(AG28="",AH28="",AH28=0),"",AG28*4.828/(AH28*24)) | AL28: =IF(OR(AK28="",AK28="",AK28=0),"",4.828/(AK28*24)) | AN28: =IF(OR(NOT(ISNUMBER(C28)),NOT(ISNUMBER(W28))),"",IF(AB28<>"",AB28,W28)-C28) | AP28: =IF($B28="","",TEXT($A28,"yyyymmdd")&"_P"&$C28&"_C"&$F28&"_"&TRIM(RIGHT(SUBSTITUTE(TRIM(SUBSTITUTE($K28,CHAR(160)," "))," ",REPT(" ",60)),60))&IF($O28="","","-"&TRIM(RIGHT(SUBSTITUTE(TRIM(SUBSTITUTE($O28,CHAR(160)," "))," ",REPT(" ",60)),60)))&IF($S28="","","-"&TRIM(RIGHT(SUBSTITUTE(TRIM(SUBSTITUTE($S28,CHAR(160)," "))," ",REPT(" ",60)),60)))&".jpg")
A29: 22240 | B29: Armstrong 500 | C29: 28 | D29: A | E29: 4 | F29: 10 | G29: W. McB. March | I29: Renault 750 | K29: Bill March | L29: AUS | M29: =_xlfn.LET(_xlpm.d,_xlfn.XLOOKUP(K29,'[1]Birth Dates'!$A:$A,'[1]Birth Dates'!$B:$B,"",0),IF(_xlpm.d=0,"",_xlpm.d)) | N29: =IF(OR(M29="",A29="",NOT(ISNUMBER(M29)),M29>A29),"",DATEDIF(M29,A29,"Y")&" years, "&DATEDIF(M29,A29,"YM")&" months, "&DATEDIF(M29,A29,"MD")&" days") | O29: John Connolly | P29: AUS | Q29: =_xlfn.LET(_xlpm.d,_xlfn.XLOOKUP(O29,'[1]Birth Dates'!$A:$A,'[1]Birth Dates'!$B:$B,"",0),IF(_xlpm.d=0,"",_xlpm.d)) | R29: =IF(OR(Q29="",A29="",NOT(ISNUMBER(Q29)),Q29>A29),"",DATEDIF(Q29,A29,"Y")&" years, "&DATEDIF(Q29,A29,"YM")&" months, "&DATEDIF(Q29,A29,"MD")&" days") | U29: =_xlfn.LET(_xlpm.d,_xlfn.XLOOKUP(S29,'[1]Birth Dates'!$A:$A,'[1]Birth Dates'!$B:$B,"",0),IF(_xlpm.d=0,"",_xlpm.d)) | V29: =IF(OR(U29="",A29="",NOT(ISNUMBER(U29)),U29>A29),"",DATEDIF(U29,A29,"Y")&" years, "&DATEDIF(U29,A29,"YM")&" months, "&DATEDIF(U29,A29,"MD")&" days") | Z29: 0 | AA29: =IF(OR(Y29="",Z29="",Z29=0),"",Y29*4.828/(Z29*24)) | AD29: =IF(OR(AB29="",AC29="",AC29=0),"",AB29*4.828/(AC29*24)) | AE29: =IF(OR(NOT(ISNUMBER(C28)),NOT(ISNUMBER(N29))),"",IF(S29<>"",S29,N29)-C28) | AG29: 145 | AI29: =IF(OR(AG29="",AH29="",AH29=0),"",AG29*4.828/(AH29*24)) | AL29: =IF(OR(AK29="",AK29="",AK29=0),"",4.828/(AK29*24)) | AN29: =IF(OR(NOT(ISNUMBER(C29)),NOT(ISNUMBER(W29))),"",IF(AB29<>"",AB29,W29)-C29) | AP29: =IF($B29="","",TEXT($A29,"yyyymmdd")&"_P"&$C29&"_C"&$F29&"_"&TRIM(RIGHT(SUBSTITUTE(TRIM(SUBSTITUTE($K29,CHAR(160)," "))," ",REPT(" ",60)),60))&IF($O29="","","-"&TRIM(RIGHT(SUBSTITUTE(TRIM(SUBSTITUTE($O29,CHAR(160)," "))," ",REPT(" ",60)),60)))&IF($S29="","","-"&TRIM(RIGHT(SUBSTITUTE(TRIM(SUBSTITUTE($S29,CHAR(160)," "))," ",REPT(" ",60)),60)))&".jpg")
A30: 22240 | B30: Armstrong 500 | C30: 29 | D30: A | E30: 5 | F30: 15 | G30: Wal Gillespie Fiat Services | I30: Fiat 600 | K30: Wal Gillespie | M30: =_xlfn.LET(_xlpm.d,_xlfn.XLOOKUP(K30,'[1]Birth Dates'!$A:$A,'[1]Birth Dates'!$B:$B,"",0),IF(_xlpm.d=0,"",_xlpm.d)) | N30: =IF(OR(M30="",A30="",NOT(ISNUMBER(M30)),M30>A30),"",DATEDIF(M30,A30,"Y")&" years, "&DATEDIF(M30,A30,"YM")&" months, "&DATEDIF(M30,A30,"MD")&" days") | O30: Lou Sinclair | Q30: =_xlfn.LET(_xlpm.d,_xlfn.XLOOKUP(O30,'[1]Birth Dates'!$A:$A,'[1]Birth Dates'!$B:$B,"",0),IF(_xlpm.d=0,"",_xlpm.d)) | R30: =IF(OR(Q30="",A30="",NOT(ISNUMBER(Q30)),Q30>A30),"",DATEDIF(Q30,A30,"Y")&" years, "&DATEDIF(Q30,A30,"YM")&" months, "&DATEDIF(Q30,A30,"MD")&" days") | U30: =_xlfn.LET(_xlpm.d,_xlfn.XLOOKUP(S30,'[1]Birth Dates'!$A:$A,'[1]Birth Dates'!$B:$B,"",0),IF(_xlpm.d=0,"",_xlpm.d)) | V30: =IF(OR(U30="",A30="",NOT(ISNUMBER(U30)),U30>A30),"",DATEDIF(U30,A30,"Y")&" years, "&DATEDIF(U30,A30,"YM")&" months, "&DATEDIF(U30,A30,"MD")&" days") | Z30: 0 | AA30: =IF(OR(Y30="",Z30="",Z30=0),"",Y30*4.828/(Z30*24)) | AD30: =IF(OR(AB30="",AC30="",AC30=0),"",AB30*4.828/(AC30*24)) | AE30: =IF(OR(NOT(ISNUMBER(C29)),NOT(ISNUMBER(N30))),"",IF(S30<>"",S30,N30)-C29) | AG30: 138 | AI30: =IF(OR(AG30="",AH30="",AH30=0),"",AG30*4.828/(AH30*24)) | AL30: =IF(OR(AK30="",AK30="",AK30=0),"",4.828/(AK30*24)) | AN30: =IF(OR(NOT(ISNUMBER(C30)),NOT(ISNUMBER(W30))),"",IF(AB30<>"",AB30,W30)-C30) | AP30: =IF($B30="","",TEXT($A30,"yyyymmdd")&"_P"&$C30&"_C"&$F30&"_"&TRIM(RIGHT(SUBSTITUTE(TRIM(SUBSTITUTE($K30,CHAR(160)," "))," ",REPT(" ",60)),60))&IF($O30="","","-"&TRIM(RIGHT(SUBSTITUTE(TRIM(SUBSTITUTE($O30,CHAR(160)," "))," ",REPT(" ",60)),60)))&IF($S30="","","-"&TRIM(RIGHT(SUBSTITUTE(TRIM(SUBSTITUTE($S30,CHAR(160)," "))," ",REPT(" ",60)),60)))&".jpg")
A31: 22240 | B31: Armstrong 500 | C31: 30 | D31: A | E31: 6 | F31: 4 | G31: Finlay Bros. P/L | I31: Lloyd Alexander TS | K31: Kevin Lott | M31: =_xlfn.LET(_xlpm.d,_xlfn.XLOOKUP(K31,'[1]Birth Dates'!$A:$A,'[1]Birth Dates'!$B:$B,"",0),IF(_xlpm.d=0,"",_xlpm.d)) | N31: =IF(OR(M31="",A31="",NOT(ISNUMBER(M31)),M31>A31),"",DATEDIF(M31,A31,"Y")&" years, "&DATEDIF(M31,A31,"YM")&" months, "&DATEDIF(M31,A31,"MD")&" days") | O31: G. Petty | Q31: =_xlfn.LET(_xlpm.d,_xlfn.XLOOKUP(O31,'[1]Birth Dates'!$A:$A,'[1]Birth Dates'!$B:$B,"",0),IF(_xlpm.d=0,"",_xlpm.d)) | R31: =IF(OR(Q31="",A31="",NOT(ISNUMBER(Q31)),Q31>A31),"",DATEDIF(Q31,A31,"Y")&" years, "&DATEDIF(Q31,A31,"YM")&" months, "&DATEDIF(Q31,A31,"MD")&" days") | U31: =_xlfn.LET(_xlpm.d,_xlfn.XLOOKUP(S31,'[1]Birth Dates'!$A:$A,'[1]Birth Dates'!$B:$B,"",0),IF(_xlpm.d=0,"",_xlpm.d)) | V31: =IF(OR(U31="",A31="",NOT(ISNUMBER(U31)),U31>A31),"",DATEDIF(U31,A31,"Y")&" years, "&DATEDIF(U31,A31,"YM")&" months, "&DATEDIF(U31,A31,"MD")&" days") | Z31: 0 | AA31: =IF(OR(Y31="",Z31="",Z31=0),"",Y31*4.828/(Z31*24)) | AD31: =IF(OR(AB31="",AC31="",AC31=0),"",AB31*4.828/(AC31*24)) | AE31: =IF(OR(NOT(ISNUMBER(C30)),NOT(ISNUMBER(N31))),"",IF(S31<>"",S31,N31)-C30) | AG31: 135 | AI31: =IF(OR(AG31="",AH31="",AH31=0),"",AG31*4.828/(AH31*24)) | AL31: =IF(OR(AK31="",AK31="",AK31=0),"",4.828/(AK31*24)) | AN31: =IF(OR(NOT(ISNUMBER(C31)),NOT(ISNUMBER(W31))),"",IF(AB31<>"",AB31,W31)-C31) | AP31: =IF($B31="","",TEXT($A31,"yyyymmdd")&"_P"&$C31&"_C"&$F31&"_"&TRIM(RIGHT(SUBSTITUTE(TRIM(SUBSTITUTE($K31,CHAR(160)," "))," ",REPT(" ",60)),60))&IF($O31="","","-"&TRIM(RIGHT(SUBSTITUTE(TRIM(SUBSTITUTE($O31,CHAR(160)," "))," ",REPT(" ",60)),60)))&IF($S31="","","-"&TRIM(RIGHT(SUBSTITUTE(TRIM(SUBSTITUTE($S31,CHAR(160)," "))," ",REPT(" ",60)),60)))&".jpg")
A32: 22240 | B32: Armstrong 500 | C32: 31 | D32: A | E32: 7 | F32: 16 | G32: Torino Motors P/L | I32: Fiat 600 | K32: Brian Pyers | M32: =_xlfn.LET(_xlpm.d,_xlfn.XLOOKUP(K32,'[1]Birth Dates'!$A:$A,'[1]Birth Dates'!$B:$B,"",0),IF(_xlpm.d=0,"",_xlpm.d)) | N32: =IF(OR(M32="",A32="",NOT(ISNUMBER(M32)),M32>A32),"",DATEDIF(M32,A32,"Y")&" years, "&DATEDIF(M32,A32,"YM")&" months, "&DATEDIF(M32,A32,"MD")&" days") | O32: Frank Elkins | Q32: =_xlfn.LET(_xlpm.d,_xlfn.XLOOKUP(O32,'[1]Birth Dates'!$A:$A,'[1]Birth Dates'!$B:$B,"",0),IF(_xlpm.d=0,"",_xlpm.d)) | R32: =IF(OR(Q32="",A32="",NOT(ISNUMBER(Q32)),Q32>A32),"",DATEDIF(Q32,A32,"Y")&" years, "&DATEDIF(Q32,A32,"YM")&" months, "&DATEDIF(Q32,A32,"MD")&" days") | U32: =_xlfn.LET(_xlpm.d,_xlfn.XLOOKUP(S32,'[1]Birth Dates'!$A:$A,'[1]Birth Dates'!$B:$B,"",0),IF(_xlpm.d=0,"",_xlpm.d)) | V32: =IF(OR(U32="",A32="",NOT(ISNUMBER(U32)),U32>A32),"",DATEDIF(U32,A32,"Y")&" years, "&DATEDIF(U32,A32,"YM")&" months, "&DATEDIF(U32,A32,"MD")&" days") | Z32: 0 | AA32: =IF(OR(Y32="",Z32="",Z32=0),"",Y32*4.828/(Z32*24)) | AD32: =IF(OR(AB32="",AC32="",AC32=0),"",AB32*4.828/(AC32*24)) | AE32: =IF(OR(NOT(ISNUMBER(C31)),NOT(ISNUMBER(N32))),"",IF(S32<>"",S32,N32)-C31) | AG32: 135 | AI32: =IF(OR(AG32="",AH32="",AH32=0),"",AG32*4.828/(AH32*24)) | AL32: =IF(OR(AK32="",AK32="",AK32=0),"",4.828/(AK32*24)) | AN32: =IF(OR(NOT(ISNUMBER(C32)),NOT(ISNUMBER(W32))),"",IF(AB32<>"",AB32,W32)-C32) | AP32: =IF($B32="","",TEXT($A32,"yyyymmdd")&"_P"&$C32&"_C"&$F32&"_"&TRIM(RIGHT(SUBSTITUTE(TRIM(SUBSTITUTE($K32,CHAR(160)," "))," ",REPT(" ",60)),60))&IF($O32="","","-"&TRIM(RIGHT(SUBSTITUTE(TRIM(SUBSTITUTE($O32,CHAR(160)," "))," ",REPT(" ",60)),60)))&IF($S32="","","-"&TRIM(RIGHT(SUBSTITUTE(TRIM(SUBSTITUTE($S32,CHAR(160)," "))," ",REPT(" ",60)),60)))&".jpg")
A33: 22240 | B33: Armstrong 500 | C33: 32 | D33: A | E33: 8 | F33: 7 | G33: Finlay Bros. P/L | I33: Lloyd Alexander TS | K33: R. Slaney | M33: =_xlfn.LET(_xlpm.d,_xlfn.XLOOKUP(K33,'[1]Birth Dates'!$A:$A,'[1]Birth Dates'!$B:$B,"",0),IF(_xlpm.d=0,"",_xlpm.d)) | N33: =IF(OR(M33="",A33="",NOT(ISNUMBER(M33)),M33>A33),"",DATEDIF(M33,A33,"Y")&" years, "&DATEDIF(M33,A33,"YM")&" months, "&DATEDIF(M33,A33,"MD")&" days") | O33: G. White | Q33: =_xlfn.LET(_xlpm.d,_xlfn.XLOOKUP(O33,'[1]Birth Dates'!$A:$A,'[1]Birth Dates'!$B:$B,"",0),IF(_xlpm.d=0,"",_xlpm.d)) | R33: =IF(OR(Q33="",A33="",NOT(ISNUMBER(Q33)),Q33>A33),"",DATEDIF(Q33,A33,"Y")&" years, "&DATEDIF(Q33,A33,"YM")&" months, "&DATEDIF(Q33,A33,"MD")&" days") | U33: =_xlfn.LET(_xlpm.d,_xlfn.XLOOKUP(S33,'[1]Birth Dates'!$A:$A,'[1]Birth Dates'!$B:$B,"",0),IF(_xlpm.d=0,"",_xlpm.d)) | V33: =IF(OR(U33="",A33="",NOT(ISNUMBER(U33)),U33>A33),"",DATEDIF(U33,A33,"Y")&" years, "&DATEDIF(U33,A33,"YM")&" months, "&DATEDIF(U33,A33,"MD")&" days") | Z33: 0 | AA33: =IF(OR(Y33="",Z33="",Z33=0),"",Y33*4.828/(Z33*24)) | AD33: =IF(OR(AB33="",AC33="",AC33=0),"",AB33*4.828/(AC33*24)) | AE33: =IF(OR(NOT(ISNUMBER(C32)),NOT(ISNUMBER(N33))),"",IF(S33<>"",S33,N33)-C32) | AG33: 134 | AI33: =IF(OR(AG33="",AH33="",AH33=0),"",AG33*4.828/(AH33*24)) | AL33: =IF(OR(AK33="",AK33="",AK33=0),"",4.828/(AK33*24)) | AN33: =IF(OR(NOT(ISNUMBER(C33)),NOT(ISNUMBER(W33))),"",IF(AB33<>"",AB33,W33)-C33) | AP33: =IF($B33="","",TEXT($A33,"yyyymmdd")&"_P"&$C33&"_C"&$F33&"_"&TRIM(RIGHT(SUBSTITUTE(TRIM(SUBSTITUTE($K33,CHAR(160)," "))," ",REPT(" ",60)),60))&IF($O33="","","-"&TRIM(RIGHT(SUBSTITUTE(TRIM(SUBSTITUTE($O33,CHAR(160)," "))," ",REPT(" ",60)),60)))&IF($S33="","","-"&TRIM(RIGHT(SUBSTITUTE(TRIM(SUBSTITUTE($S33,CHAR(160)," "))," ",REPT(" ",60)),60)))&".jpg")
A34: 22240 | B34: Armstrong 500 | C34: 33 | D34: A | E34: 9 | F34: 5 | G34: Finlay Bros. P/L | I34: Lloyd Alexander TS | K34: Graham Levingston | M34: =_xlfn.LET(_xlpm.d,_xlfn.XLOOKUP(K34,'[1]Birth Dates'!$A:$A,'[1]Birth Dates'!$B:$B,"",0),IF(_xlpm.d=0,"",_xlpm.d)) | N34: =IF(OR(M34="",A34="",NOT(ISNUMBER(M34)),M34>A34),"",DATEDIF(M34,A34,"Y")&" years, "&DATEDIF(M34,A34,"YM")&" months, "&DATEDIF(M34,A34,"MD")&" days") | O34: Peter Candy | Q34: =_xlfn.LET(_xlpm.d,_xlfn.XLOOKUP(O34,'[1]Birth Dates'!$A:$A,'[1]Birth Dates'!$B:$B,"",0),IF(_xlpm.d=0,"",_xlpm.d)) | R34: =IF(OR(Q34="",A34="",NOT(ISNUMBER(Q34)),Q34>A34),"",DATEDIF(Q34,A34,"Y")&" years, "&DATEDIF(Q34,A34,"YM")&" months, "&DATEDIF(Q34,A34,"MD")&" days") | U34: =_xlfn.LET(_xlpm.d,_xlfn.XLOOKUP(S34,'[1]Birth Dates'!$A:$A,'[1]Birth Dates'!$B:$B,"",0),IF(_xlpm.d=0,"",_xlpm.d)) | V34: =IF(OR(U34="",A34="",NOT(ISNUMBER(U34)),U34>A34),"",DATEDIF(U34,A34,"Y")&" years, "&DATEDIF(U34,A34,"YM")&" months, "&DATEDIF(U34,A34,"MD")&" days") | Z34: 0 | AA34: =IF(OR(Y34="",Z34="",Z34=0),"",Y34*4.828/(Z34*24)) | AD34: =IF(OR(AB34="",AC34="",AC34=0),"",AB34*4.828/(AC34*24)) | AE34: =IF(OR(NOT(ISNUMBER(C33)),NOT(ISNUMBER(N34))),"",IF(S34<>"",S34,N34)-C33) | AG34: 132 | AI34: =IF(OR(AG34="",AH34="",AH34=0),"",AG34*4.828/(AH34*24)) | AL34: =IF(OR(AK34="",AK34="",AK34=0),"",4.828/(AK34*24)) | AN34: =IF(OR(NOT(ISNUMBER(C34)),NOT(ISNUMBER(W34))),"",IF(AB34<>"",AB34,W34)-C34) | AP34: =IF($B34="","",TEXT($A34,"yyyymmdd")&"_P"&$C34&"_C"&$F34&"_"&TRIM(RIGHT(SUBSTITUTE(TRIM(SUBSTITUTE($K34,CHAR(160)," "))," ",REPT(" ",60)),60))&IF($O34="","","-"&TRIM(RIGHT(SUBSTITUTE(TRIM(SUBSTITUTE($O34,CHAR(160)," "))," ",REPT(" ",60)),60)))&IF($S34="","","-"&TRIM(RIGHT(SUBSTITUTE(TRIM(SUBSTITUTE($S34,CHAR(160)," "))," ",REPT(" ",60)),60)))&".jpg")
A35: 22240 | B35: Armstrong 500 | C35: 34 | D35: A | E35: 10 | F35: 8 | G35: B.P. Batteries P/L | I35: Renault 750 | K35: Les Park | L35: AUS | M35: =_xlfn.LET(_xlpm.d,_xlfn.XLOOKUP(K35,'[1]Birth Dates'!$A:$A,'[1]Birth Dates'!$B:$B,"",0),IF(_xlpm.d=0,"",_xlpm.d)) | N35: =IF(OR(M35="",A35="",NOT(ISNUMBER(M35)),M35>A35),"",DATEDIF(M35,A35,"Y")&" years, "&DATEDIF(M35,A35,"YM")&" months, "&DATEDIF(M35,A35,"MD")&" days") | O35: J. Fleming | Q35: =_xlfn.LET(_xlpm.d,_xlfn.XLOOKUP(O35,'[1]Birth Dates'!$A:$A,'[1]Birth Dates'!$B:$B,"",0),IF(_xlpm.d=0,"",_xlpm.d)) | R35: =IF(OR(Q35="",A35="",NOT(ISNUMBER(Q35)),Q35>A35),"",DATEDIF(Q35,A35,"Y")&" years, "&DATEDIF(Q35,A35,"YM")&" months, "&DATEDIF(Q35,A35,"MD")&" days") | U35: =_xlfn.LET(_xlpm.d,_xlfn.XLOOKUP(S35,'[1]Birth Dates'!$A:$A,'[1]Birth Dates'!$B:$B,"",0),IF(_xlpm.d=0,"",_xlpm.d)) | V35: =IF(OR(U35="",A35="",NOT(ISNUMBER(U35)),U35>A35),"",DATEDIF(U35,A35,"Y")&" years, "&DATEDIF(U35,A35,"YM")&" months, "&DATEDIF(U35,A35,"MD")&" days") | Z35: 0 | AA35: =IF(OR(Y35="",Z35="",Z35=0),"",Y35*4.828/(Z35*24)) | AD35: =IF(OR(AB35="",AC35="",AC35=0),"",AB35*4.828/(AC35*24)) | AE35: =IF(OR(NOT(ISNUMBER(C34)),NOT(ISNUMBER(N35))),"",IF(S35<>"",S35,N35)-C34) | AG35: 0 | AI35: =IF(OR(AG35="",AH35="",AH35=0),"",AG35*4.828/(AH35*24)) | AL35: =IF(OR(AK35="",AK35="",AK35=0),"",4.828/(AK35*24)) | AN35: =IF(OR(NOT(ISNUMBER(C35)),NOT(ISNUMBER(W35))),"",IF(AB35<>"",AB35,W35)-C35) | AP35: =IF($B35="","",TEXT($A35,"yyyymmdd")&"_P"&$C35&"_C"&$F35&"_"&TRIM(RIGHT(SUBSTITUTE(TRIM(SUBSTITUTE($K35,CHAR(160)," "))," ",REPT(" ",60)),60))&IF($O35="","","-"&TRIM(RIGHT(SUBSTITUTE(TRIM(SUBSTITUTE($O35,CHAR(160)," "))," ",REPT(" ",60)),60)))&IF($S35="","","-"&TRIM(RIGHT(SUBSTITUTE(TRIM(SUBSTITUTE($S35,CHAR(160)," "))," ",REPT(" ",60)),60)))&".jpg")
